Workbook
Name ABP_NOV25_DATA_range: 'ABP Nov 25 BWP'!$B$1:$FT$101
Name ABPAPR25_DATA_RANGE: 'ABP Apr 25 DG Khan and Vehari'!$B$5:$FS$203
Name Consolidated_data_range: 'HF R37-16 Consolidated Data'!$A$1:$FV$600
Name hf_core_data_range: 'HF core data'!$B$1:$FV$646

Sheet Dashboard
A1: HF Core Data | D1: ABP Nov 25 Data | G1: AABP Apr 25 Data | J1: DG KHAN | O1: interval " k " | P1: indexes
A2: Bahawalpur | B2: =COUNTIF(INDEX(hf_core_data_range, 0, 9), A2) -> 57 | D2: Bahawalpur | E2: =COUNTIF(INDEX(ABP_NOV25_DATA_range, 0, 9), D2) -> 100 | G2: Bahawalpur | H2: =COUNTIF(INDEX(ABPAPR25_DATA_RANGE, 0, 9), G2) -> 0 | J2: category | K2: HF | L2: ABP available | M2: selected from ABP Data | N2: sub total
A3: Jhang | B3: =COUNTIF(INDEX(hf_core_data_range, 0, 9), A3) -> 101 | D3: Jhang | E3: =COUNTIF(INDEX(ABP_NOV25_DATA_range, 0, 9), D3) -> 0 | G3: Jhang | H3: =COUNTIF(INDEX(ABPAPR25_DATA_RANGE, 0, 9), G3) -> 0 | J3: Public Place | K3: 55 | L3: 18 | M3: 0 | N3: =M3+K3 -> 55
A4: Sahiwal | B4: =COUNTIF(INDEX(hf_core_data_range, 0, 9), A4) -> 100 | D4: Sahiwal | E4: =COUNTIF(INDEX(ABP_NOV25_DATA_range, 0, 9), D4) -> 0 | G4: Sahiwal | H4: =COUNTIF(INDEX(ABPAPR25_DATA_RANGE, 0, 9), G4) -> 0 | J4: PSV | K4: 0 | L4: 16 | M4: 10 | N4: =M4+K4 -> 10 | O4: 1.67 | P4: 172, 174, 175, 177, 179, 180, 182, 184, 185, 187
A5: Dera Ghazi Khan | B5: =COUNTIF(INDEX(hf_core_data_range, 0, 9), A5) -> 72 | D5: Dera Ghazi Khan | E5: =COUNTIF(INDEX(ABP_NOV25_DATA_range, 0, 9), D5) -> 0 | G5: DG Khan | H5: =COUNTIF(INDEX(ABPAPR25_DATA_RANGE, 0, 9), G5) -> 50 | J5: Retail | K5: 17 | L5: 16 | M5: 16 | N5: =M5+K5 -> 33
A6: Mirpurkhas | B6: =COUNTIF(INDEX(hf_core_data_range, 0, 9), A6) -> 142 | D6: Mirpurkhas | E6: =COUNTIF(INDEX(ABP_NOV25_DATA_range, 0, 9), D6) -> 0 | G6: Mirpurkhas | H6: =COUNTIF(INDEX(ABPAPR25_DATA_RANGE, 0, 9), G6) -> 0 | J6: total | N6: =SUM(N3:N5) -> 98
A7: Mansehra | B7: =COUNTIF(INDEX(hf_core_data_range, 0, 9), A7) -> 103 | D7: Mansehra | E7: =COUNTIF(INDEX(ABP_NOV25_DATA_range, 0, 9), D7) -> 0 | G7: toba_tek_singh | H7: =COUNTIF(INDEX(ABPAPR25_DATA_RANGE, 0, 9), G7) -> 49 | J7: Vihari
A8: Vehari | B8: =COUNTIF(INDEX(hf_core_data_range, 0, 9), A8) -> 70 | D8: Vehari | E8: =COUNTIF(INDEX(ABP_NOV25_DATA_range, 0, 9), D8) -> 0 | G8: vihari | H8: =COUNTIF(INDEX(ABPAPR25_DATA_RANGE, 0, 9), G8) -> 50 | J8: category | K8: HF | L8: ABP available | M8: selected from ABP Data | N8: sub total
A9: total | B9: =SUM(B2:B8) -> 645 | D9: total | E9: =SUM(E2:E8) -> 100 | G9: total | H9: =SUM(H2:H8) -> 149 | J9: Public Place | K9: 56 | L9: 18 | M9: 0 | N9: 56
J10: PSV | K10: 0 | L10: 16 | M10: 10 | N10: 10 | O10: 1.67 | P10: 72, 74, 75, 77, 79, 80, 82, 84, 85, 87
A11: CONSOLDATED DATA SHEET | J11: Retail | K11: 15 | L11: 16 | M11: 16 | N11: =M11+K11 -> 31
A12: city | B12: Public place | C12: Public Service Vehicle (PSV) | D12: Retail outlet /Point of Sale (POS) | E12: Total | J12: total | N12: =SUM(N9:N11) -> 97
A13: Bahawalpur | B13: =COUNTIFS('HF R37-16 Consolidated Data'!$J$2:$J$590,$A13,'HF R37-16 Consolidated Data'!$S$2:$S$590,B$12) -> 57 | C13: =COUNTIFS('HF R37-16 Consolidated Data'!$J$2:$J$590,$A13,'HF R37-16 Consolidated Data'!$S$2:$S$590,C$12) -> 10 | D13: =COUNTIFS('HF R37-16 Consolidated Data'!$J$2:$J$590,$A13,'HF R37-16 Consolidated Data'!$S$2:$S$590,D$12) -> 33 | E13: =SUM(B13:D13) -> 100 | J13: BWP
A14: Jhang | B14: =COUNTIFS('HF R37-16 Consolidated Data'!$J$2:$J$590,$A14,'HF R37-16 Consolidated Data'!$S$2:$S$590,B$12) -> 56 | C14: =COUNTIFS('HF R37-16 Consolidated Data'!$J$2:$J$590,$A14,'HF R37-16 Consolidated Data'!$S$2:$S$590,C$12) -> 11 | D14: =COUNTIFS('HF R37-16 Consolidated Data'!$J$2:$J$590,$A14,'HF R37-16 Consolidated Data'!$S$2:$S$590,D$12) -> 34 | E14: =SUM(B14:D14) -> 101 | J14: category | K14: HF | L14: ABP available | M14: selected from ABP Data | N14: sub total
A15: Sahiwal | B15: =COUNTIFS('HF R37-16 Consolidated Data'!$J$2:$J$590,$A15,'HF R37-16 Consolidated Data'!$S$2:$S$590,B$12) -> 62 | C15: =COUNTIFS('HF R37-16 Consolidated Data'!$J$2:$J$590,$A15,'HF R37-16 Consolidated Data'!$S$2:$S$590,C$12) -> 10 | D15: =COUNTIFS('HF R37-16 Consolidated Data'!$J$2:$J$590,$A15,'HF R37-16 Consolidated Data'!$S$2:$S$590,D$12) -> 28 | E15: =SUM(B15:D15) -> 100 | J15: Public Place | K15: 57 | L15: 32 | M15: 0 | N15: 57
A16: DG Khan | B16: =COUNTIFS('HF R37-16 Consolidated Data'!$J$2:$J$590,$A16,'HF R37-16 Consolidated Data'!$S$2:$S$590,B$12) -> 55 | C16: =COUNTIFS('HF R37-16 Consolidated Data'!$J$2:$J$590,$A16,'HF R37-16 Consolidated Data'!$S$2:$S$590,C$12) -> 10 | D16: =COUNTIFS('HF R37-16 Consolidated Data'!$J$2:$J$590,$A16,'HF R37-16 Consolidated Data'!$S$2:$S$590,D$12) -> 33 | E16: =SUM(B16:D16) -> 98 | J16: PSV | K16: 0 | L16: 33 | M16: 10 | N16: 10 | O16: 3.56 | P16: 34, 38, 41, 45, 48, 52, 55, 59, 62, 66
A17: Mirpurkhas | B17: =COUNTIFS('HF R37-16 Consolidated Data'!$J$2:$J$720,$A17,'HF R37-16 Consolidated Data'!$S$2:$S$720,B$12) -> 57 | C17: =COUNTIFS('HF R37-16 Consolidated Data'!$J$2:$J$720,$A17,'HF R37-16 Consolidated Data'!$S$2:$S$720,C$12) -> 10 | D17: =COUNTIFS('HF R37-16 Consolidated Data'!$J$2:$J$720,$A17,'HF R37-16 Consolidated Data'!$S$2:$S$720,D$12) -> 33 | E17: =SUM(B17:D17) -> 100 | F17: 1.75 | G17: 277, 279, 281, 282, 284, 286, 288, 289, 291, 293, 295, 296, 298, 300, 302, 303, 305, 307, 309, 310, 312, 314, 316, 317, 319, 321, 323, 324, 326, 328, 330, 331, 333, 335, 337, 338, 340,342, 344,345, 347, 349, 351, 352, 354, 356, 358, 359, 361, 363, 365, 366, 368, 370, 372, 373,375 | J17: Retail | K17: 0 | L17: 35 | M17: 33 | N17: 33 | O17: 1.06
A18: Mansehra | B18: =COUNTIFS('HF R37-16 Consolidated Data'!$J$2:$J$590,$A18,'HF R37-16 Consolidated Data'!$S$2:$S$590,B$12) -> 59 | C18: =COUNTIFS('HF R37-16 Consolidated Data'!$J$2:$J$590,$A18,'HF R37-16 Consolidated Data'!$S$2:$S$590,C$12) -> 10 | D18: =COUNTIFS('HF R37-16 Consolidated Data'!$J$2:$J$590,$A18,'HF R37-16 Consolidated Data'!$S$2:$S$590,D$12) -> 34 | E18: =SUM(B18:D18) -> 103 | J18: total | N18: =SUM(N15:N17) -> 100
A19: Vihari | B19: =COUNTIFS('HF R37-16 Consolidated Data'!$J$2:$J$590,$A19,'HF R37-16 Consolidated Data'!$S$2:$S$590,B$12) -> 56 | C19: =COUNTIFS('HF R37-16 Consolidated Data'!$J$2:$J$600,$A19,'HF R37-16 Consolidated Data'!$S$2:$S$600,C$12) -> 10 | D19: =COUNTIFS('HF R37-16 Consolidated Data'!$J$2:$J$720,$A19,'HF R37-16 Consolidated Data'!$S$2:$S$720,D$12) -> 31 | E19: =SUM(B19:D19) -> 97
A20: TOTAL | B20: =SUM(B13:B19) -> 402 | C20: =SUM(C13:C19) -> 71 | D20: =SUM(D13:D19) -> 226 | E20: =SUM(B20:D20) -> 699

Sheet HF R37-16 Consolidated Data
A1: Row Addition Mode | B1: start | C1: end | D1: Form Number | E1: Date of Visit | F1: Start Time | G1: End time | H1: Enumerator | I1: Division | J1: District | K1: city/ Tehsil | L1: Geo Location | M1: _Geo Location _latitude | N1: _Geo Location _longitude | O1: _Geo Location _altitude | P1: _Geo Location _precision | Q1: Urban/ Rural? | R1: Name of Place | S1: Category of Place | T1: OLD A1:Type of public place | U1: Mapping status:Is the venue a Listed Venue or an unlisted venue? | V1: Mapping status:Is the venue a Listed Venue or an unlisted venue?/Listed Venue | W1: Mapping status:Is the venue a Listed Venue or an unlisted venue?/Unlisted Venue | X1: A2: Name of Public place | Y1: A3: “No Smoking Area”, “Smoking is illegal here” or similar boards are visible? | Z1: If yes, add photo Evidence | AA1: If yes, add photo Evidence _URL | AB1: If yes how many | AC1: A4: PEOPLE found smoking in the indoor area at the time of visit? | AD1: If yes, how many? | AE1: A5: STAFF found smoking in the indoor area at the time of visit? | AF1: If yes, how many? | AG1: A6: STAFF is aware of ban on smoking in public place? | AH1: A7: Authorized officer of the public place is aware of legal responsibility to stop persons from smoking indoors? | AI1: A8: Authorized officer of the public place is aware of legal responsibility to display ‘no smoking’ signboard? | AJ1: A9: If any persons were found USING any type of tobacco or nicotine product, what type are they using? | AK1: A9: If any persons were found USING any type of tobacco or nicotine product, what type are they using?/Cigarette | AL1: A9: If any persons were found USING any type of tobacco or nicotine product, what type are they using?/Naswar | AM1: A9: If any persons were found USING any type of tobacco or nicotine product, what type are they using?/Shisha / Hookah | AN1: A9: If any persons were found USING any type of tobacco or nicotine product, what type are they using?/Nicotine pouch | AO1: A9: If any persons were found USING any type of tobacco or nicotine product, what type are they using?/Heated Tobacco Products (HTPs) | AP1: A9: If any persons were found USING any type of tobacco or nicotine product, what type are they using?/E- cigarettes / vapes | AQ1: A9: If any persons were found USING any type of tobacco or nicotine product, what type are they using?/Does not apply / no one using tobacco or nicotine products | AR1: A9: If any persons were found USING any type of tobacco or nicotine product, what type are they using?/other | AS1: specify "other" | AT1: A10: If any persons were USING any type of tobacco or nicotine product, did authorized officer or staff member of the public place try to stop them? | AU1: A11: Cigarette butts are visible in the indoor area? | AV1: IIf Yes, add photo Evidence | AW1: IIf Yes, add photo Evidence _URL | AX1: A12: Ashtrays or matches are visible in the indoor area? | AY1: add photo Evidence | AZ1: add photo Evidence _URL | BA1: A13: Is there a “designated smoking area” in the public place? | BB1: add photo Evidence | BC1: add photo Evidence _URL | BD1: A14: Are there any tobacco or nicotine products being SOLD on the premises? | BE1: add photo Evidence | BF1: add photo Evidence _URL | BG1: A15: If tobacco or nicotine products are being SOLD on the premises, which products are being sold? | BH1: A15: If tobacco or nicotine products are being SOLD on the premises, which products are being sold?/Cigarette | BI1: A15: If tobacco or nicotine products are being SOLD on the premises, which products are being sold?/Naswar | BJ1: A15: If tobacco or nicotine products are being SOLD on the premises, which products are being sold?/Shisha / Hookah | BK1: A15: If tobacco or nicotine products are being SOLD on the premises, which products are being sold?/Nicotine pouch | BL1: A15: If tobacco or nicotine products are being SOLD on the premises, which products are being sold?/Heated Tobacco Products (HTPs) | BM1: A15: If tobacco or nicotine products are being SOLD on the premises, which products are being sold?/E- cigarettes / vapes | BN1: A15: If tobacco or nicotine products are being SOLD on the premises, which products are being sold?/Does not apply / no one using tobacco or nicotine products | BO1: A15: If tobacco or nicotine products are being SOLD on the premises, which products are being sold?/other | BP1: specify "other" | BQ1: A16: If tobacco products are being SOLD on the premises, does the seller have a license under TVA? | BR1: add photo Evidence | BS1: add photo Evidence _URL | BT1: A17: Were you able to complete the observation? | BU1: A18: Reason for incompletion. | BV1: A19: Additional comments (if any) | BW1: B1: Type of public service vehicle | BX1: specify "other" | BY1: B2: Name of PSV or PSV company (if applicable) | BZ1: B3: Route number or name of PSV company (if applicable) | CA1: B4: “No Smoking” sign displayed inside PSV? | CB1: B5: Driver found smoking in public vehicle? | CC1: B6: Conductor found smoking inside PSV? | CD1: B7: Passenger found smoking inside PSV? | CE1: if yes, how many? | CF1: B8: If any persons were found using Tobacco Products, what type of tobacco or nicotine product were they using? | CG1: B8: If any persons were found using Tobacco Products, what type of tobacco or nicotine product were they using?/Cigarette | CH1: B8: If any persons were found using Tobacco Products, what type of tobacco or nicotine product were they using?/Naswar | CI1: B8: If any persons were found using Tobacco Products, what type of tobacco or nicotine product were they using?/Shisha / Hookah | CJ1: B8: If any persons were found using Tobacco Products, what type of tobacco or nicotine product were they using?/Nicotine pouch | CK1: B8: If any persons were found using Tobacco Products, what type of tobacco or nicotine product were they using?/Heated Tobacco Products (HTPs) | CL1: B8: If any persons were found using Tobacco Products, what type of tobacco or nicotine product were they using?/E- cigarettes / vapes | CM1: B8: If any persons were found using Tobacco Products, what type of tobacco or nicotine product were they using?/Does not apply / no one using tobacco or nicotine products | CN1: B8: If any persons were found using Tobacco Products, what type of tobacco or nicotine product were they using?/other | CO1: specify "other" | CP1: B9: If any persons were smoking, did driver/conductor try to stop them? | CQ1: B10: Cigarette butts are visible inside the PSV? | CR1: IIf Yes, add photo Evidence | CS1: IIf Yes, add photo Evidence _URL | CT1: B11: Ashtrays are visible inside the PSV? | CU1: If Yes, add photo Evidence | CV1: If Yes, add photo Evidence _URL | CW1: B12: PSV staff is aware of ban on smoking in PSVs? | CX1: B13: PSV staff is aware of legal responsibility to display ‘no smoking’ signboard? | CY1: B14: PSV staff is aware of legal responsibility to stop persons from smoking in the vehicle? | CZ1: B15: were you able to complete the observation? | DA1: B16: Reason for incompletion. | DB1: B17: Additional comments (if any). | DC1: C1: Type of outlet | DD1: specify "other" | DE1: C2: Name of outlet | DF1: C3: Market / neighborhood of outlet | DG1: C4: Sales of tobacco products to minors (under 18 years of age) taking place at time of visit? | DH1: C5: Was the vendor checking ID cards of YOUNG buyers of tobacco products during purchase at time of visit? | DI1: C6: Is there a ‘No Sales to Minors/Persons Under 18’ sign (or similar ) on display? | DJ1: If Yes, add photo Evidence | DK1: If Yes, add photo Evidence _URL | DL1: C7: Cigarette packs without graphic health warning available for sale? | DM1: if Yes, specify brands | DN1: add photo Evidence | DO1: add photo Evidence _URL | DP1: C8: Cigarette packs without excise stamps available for sale? | DQ1: if Yes, specify brands | DR1: add photo Evidence | DS1: add photo Evidence _URL | DT1: C9: Does the seller have a license under TVA? | DU1: add photo Evidence | DV1: add photo Evidence _URL | DW1: C10: Loose cigarettes are available for sale? | DX1: C11: Cigarettes are placed next to candies, snacks or children’s products? | DY1: add photo Evidence | DZ1: add photo Evidence _URL | EA1: C12-Cig-indoor-advert: Are Cigarette brands advertized indoors? | EB1: C12-Cig-indoor-advert-brands: If yes, which brands? | EC1: C12-Cig-indoor-advert-evidence: add photo Evidence of INDOOR advertisements | ED1: C12-Cig-indoor-advert-evidence: add photo Evidence of INDOOR advertisements_URL | EE1: C12-Cig-Outdoor-advert: Are Cigarette brands advertized Outdoors? | EF1: C12-Cig-Outdoor-advert-brands: If yes, which brands? | EG1: C12-Cig-outdoor-advert-evidence: add photo Evidence of OUTDOOR advertisements | EH1: C12-Cig-outdoor-advert-evidence: add photo Evidence of OUTDOOR advertisements_URL | EI1: C12-ONP-indoor-advert: Are Nicotine Pouches advertized indoors? | EJ1: C12-ONP-indoor-advert-brands: If yes, which brands? | EK1: C12-ONP-indoor-advert-evidence: add photo Evidence of INDOOR advertisements | EL1: C12-ONP-indoor-advert-evidence: add photo Evidence of INDOOR advertisements_URL | EM1: C12-ONP-Outdoor-advert: Are Nicotine Pouches advertized outdoors? | EN1: C12-ONP-Outdoor-advert-brands: If yes, which brands? | EO1: C12-ONP-outdoor-advert-evidence: add photo Evidence of OUTDOOR advertisements | EP1: C12-ONP-outdoor-advert-evidence: add photo Evidence of OUTDOOR advertisements_URL | EQ1: C12-Other-tobacco-indoor-advert: Are "any other Tobacco Products" advertized indoors? | ER1: C12-Other-tobacco-indoor-advert-brands:If yes, which brands? | ES1: C12-Other-tobacco-advert-evidence: add photo Evidence of INDOOR advertisements | ET1: C12-Other-tobacco-advert-evidence: add photo Evidence of INDOOR advertisements_URL | EU1: C12-Other-tobacco-Outdoor-advert: Are "any other Tobacco Products" advertized outdoors? | EV1: C12-Other-tobacco-Outdoor-advert-brands: If yes, which brands? | EW1: C12-Other-tobacco-advert-evidence: add photo Evidence of OUTDOOR advertisements | EX1: C12-Other-tobacco-advert-evidence: add photo Evidence of OUTDOOR advertisements_URL | EY1: C13: Special promotions or discounts offered on purchase of tobacco products | EZ1: If Yes, add photo Evidence | FA1: If Yes, add photo Evidence _URL | FB1: If Yes, provide details | FC1: C14: Any giveaways/gifts associated with tobacco products | FD1: add photo Evidence | FE1: add photo Evidence _URL | FF1: If Yes, provide details | FG1: C15: Is the store located within 50m of an educational institution | FH1: C16: Were you able to complete the observation? | FI1: C17: Reason for incompletion. | FJ1: C18: Additional comments (if any) | FK1: City/Tehsil | FL1: _id | FM1: _uuid | FN1: _submission_time | FO1: _validation_status | FP1: _notes | FQ1: _status | FR1: _submitted_by | FS1: __version__ | FT1: _tags | FU1: meta/rootUuid | FV1: _index
A2: HF core data | B2: 46131.631 | C2: 46131.636 | D2: Sahiwal 001 | E2: 46131 | F2: 15:08:00.000+05:00 | G2: 15:20:00.000+05:00 | H2: Ashfaq Ahmed Rao | I2: Sahiwal Division | J2: Sahiwal | K2: Sahiwal | L2: 30.712628 73.055794 123 82.5 | M2: 30.712628 | N2: 73.055794 | O2: 123 | P2: 82.5 | Q2: Urban | R2: On Board Daewoo Bus | S2: Public Service Vehicle (PSV) | BW2: other | BX2: Daewoo bus sahiwal to faisalabad | BY2: Daewoo bus | BZ2: Sahiwal to faisalabad | CA2: No | CB2: No | CC2: No | CD2: No | CF2: Does not apply / no one using tobacco or nicotine products | CG2: 0 | CH2: 0 | CI2: 0 | CJ2: 0 | CK2: 0 | CL2: 0 | CM2: 1 | CN2: 0 | CP2: Does not apply / no one smoking | CQ2: No | CT2: No | CW2: No | CX2: No | CY2: Yes | CZ2: Yes | DB2: Daewoo is a well disciplined company but conductor was quite unaware of TC laws. | FL2: 729311753 | FM2: ed50e636-4f87-4e82-a888-13da994b8282 | FN2: 46131.427 | FQ2: submitted_via_web | FS2: vjiNwcPYvtjoD8cL5yiJdz | FU2: uuid:ed50e636-4f87-4e82-a888-13da994b8282 | FV2: 1
A3: HF core data | B3: 46131.636 | C3: 46131.649 | D3: Sahiwal 002 | E3: 46131 | F3: 15:22:00.000+05:00 | G3: 15:35:00.000+05:00 | H3: Ashfaq Ahmed Rao | I3: Sahiwal Division | J3: Sahiwal | K3: Sahiwal | L3: 30.647913 73.095845 131.00001525878906 31.024999618530273 | M3: 30.647913 | N3: 73.095845 | O3: 131.00002 | P3: 31.025 | Q3: Urban | R3: Daewoo Bus terminal | S3: Public place | T3: Transport Terminal (Bus terminal) | U3: Listed Venue | V3: 1 | W3: 0 | X3: Daewoo Bus terminal | Y3: Yes( add photo evidence) | Z3: 20260419_152705-15_27_30.jpg | AA3: https://kf.kobotoolbox.org/api/v2/assets/a7B4UGoSq7bg72YxNv837d/data/729322035/attachments/attggMx9uX6AD9pUkDESpzZm/ | AB3: 2 | AC3: No | AE3: No | AG3: Yes | AH3: Yes | AI3: No | AJ3: Does not apply / no one using tobacco or nicotine products | AK3: 0 | AL3: 0 | AM3: 0 | AN3: 0 | AO3: 0 | AP3: 0 | AQ3: 1 | AR3: 0 | AT3: Does not apply / no one using tobacco or nicotine products | AU3: No | AX3: No | BA3: No | BD3: No | BT3: Yes | BV3: Daewoo is a well established terminal. | FL3: 729322035 | FM3: 235bab69-dd8f-4594-9f19-e661437d2179 | FN3: 46131.441 | FQ3: submitted_via_web | FS3: vjiNwcPYvtjoD8cL5yiJdz | FU3: uuid:235bab69-dd8f-4594-9f19-e661437d2179 | FV3: 2
A4: HF core data | B4: 46131.649 | C4: 46131.657 | D4: Sahiwal 003 | E4: 46131 | F4: 15:39:00.000+05:00 | G4: 15:50:00.000+05:00 | H4: Ashfaq Ahmed Rao | I4: Sahiwal Division | J4: Sahiwal | K4: Sahiwal | L4: 30.649059 73.099694 130.60000610351562 14.022000312805176 | M4: 30.649059 | N4: 73.099694 | O4: 130.60001 | P4: 14.022 | Q4: Urban | R4: Faisal Movers Bus terminal | S4: Public place | T4: Transport Terminal (Bus terminal) | U4: Listed Venue | V4: 1 | W4: 0 | X4: Faisal Movers | Y4: No | AC4: No | AE4: Yes | AF4: 3 | AG4: Yes | AH4: Yes | AI4: No | AJ4: Cigarette | AK4: 1 | AL4: 0 | AM4: 0 | AN4: 0 | AO4: 0 | AP4: 0 | AQ4: 0 | AR4: 0 | AT4: Yes | AU4: No | AX4: No | BA4: No | BD4: No | BT4: Yes | FL4: 729329290 | FM4: c1438d41-bd27-4ca3-8d49-cdb03c35bbad | FN4: 46131.449 | FQ4: submitted_via_web | FS4: vjiNwcPYvtjoD8cL5yiJdz | FU4: uuid:c1438d41-bd27-4ca3-8d49-cdb03c35bbad | FV4: 3
A5: HF core data | B5: 46131.657 | C5: 46131.805 | D5: Sahiwal 004 | E5: 46131 | F5: 19:10:00.000+05:00 | G5: 19:25:00.000+05:00 | H5: Ashfaq Ahmed Rao | I5: Sahiwal Division | J5: Sahiwal | K5: Sahiwal | L5: 30.673535 73.108809 134.20001220703125 15.222999572753906 | M5: 30.673535 | N5: 73.108809 | O5: 134.20001 | P5: 15.223 | Q5: Urban | R5: Nomnosh Restaurant | S5: Public place | T5: Eatery ( Restaurant) | U5: Listed Venue | V5: 1 | W5: 0 | X5: Nomnosh Restaurant | Y5: Yes( add photo evidence) | Z5: 20260419_191524-19_15_37.jpg | AA5: https://kf.kobotoolbox.org/api/v2/assets/a7B4UGoSq7bg72YxNv837d/data/729448613/attachments/attekpyUWxQ3Zo7pEFaYiD58/ | AB5: 1 | AC5: No | AE5: No | AG5: Yes | AH5: Yes | AI5: Yes | AJ5: Does not apply / no one using tobacco or nicotine products | AK5: 0 | AL5: 0 | AM5: 0 | AN5: 0 | AO5: 0 | AP5: 0 | AQ5: 1 | AR5: 0 | AT5: Does not apply / no one using tobacco or nicotine products | AU5: No | AX5: No | BA5: No | BD5: No | BT5: Yes | BV5: No one allows to smoke or vape within premises. | FL5: 729448613 | FM5: 987191d7-ddc4-451f-85ae-44975b221227 | FN5: 46131.597 | FQ5: submitted_via_web | FS5: vjiNwcPYvtjoD8cL5yiJdz | FU5: uuid:987191d7-ddc4-451f-85ae-44975b221227 | FV5: 4
A6: HF core data | B6: 46131.805 | C6: 46131.815 | D6: Sahiwal 005 | E6: 46131 | F6: 19:29:00.000+05:00 | G6: 19:40:00.000+05:00 | H6: Ashfaq Ahmed Rao | I6: Sahiwal Division | J6: Sahiwal | K6: Sahiwal | L6: 30.673768 73.107722 129.8000030517578 12.095000267028809 | M6: 30.673768 | N6: 73.107722 | O6: 129.8 | P6: 12.095 | Q6: Urban | R6: KR Restaurant | S6: Public place | T6: Eatery ( Restaurant) | U6: Listed Venue | V6: 1 | W6: 0 | X6: KR Restaurant | Y6: No | AC6: No | AE6: No | AG6: Yes | AH6: Yes | AI6: Yes | AJ6: Does not apply / no one using tobacco or nicotine products | AK6: 0 | AL6: 0 | AM6: 0 | AN6: 0 | AO6: 0 | AP6: 0 | AQ6: 1 | AR6: 0 | AT6: Does not apply / no one using tobacco or nicotine products | AU6: No | AX6: No | BA6: No | BD6: No | BT6: Yes | FL6: 729456370 | FM6: ef8eeff1-d76a-45b2-af4a-3d4f55c92482 | FN6: 46131.607 | FQ6: submitted_via_web | FS6: vjiNwcPYvtjoD8cL5yiJdz | FU6: uuid:ef8eeff1-d76a-45b2-af4a-3d4f55c92482 | FV6: 5
A7: HF core data | B7: 46131.815 | C7: 46131.831 | D7: Sahiwal 006 | E7: 46131 | F7: 19:50:00.000+05:00 | G7: 19:59:00.000+05:00 | H7: Ashfaq Ahmed Rao | I7: Sahiwal Division | J7: Sahiwal | K7: Sahiwal | L7: 30.671369 73.109928 130.90000915527344 92.9000015258789 | M7: 30.671369 | N7: 73.109928 | O7: 130.90001 | P7: 92.900002 | Q7: Urban | R7: 14th Street | S7: Public place | T7: Eatery ( Restaurant) | U7: Listed Venue | V7: 1 | W7: 0 | X7: 14th Street | Y7: No | AC7: No | AE7: No | AG7: Yes | AH7: Yes | AI7: Yes | AJ7: Does not apply / no one using tobacco or nicotine products | AK7: 0 | AL7: 0 | AM7: 0 | AN7: 0 | AO7: 0 | AP7: 0 | AQ7: 1 | AR7: 0 | AT7: Does not apply / no one using tobacco or nicotine products | AU7: No | AX7: No | BA7: No | BD7: No | BT7: Yes | FL7: 729469151 | FM7: 81e01791-5ddb-4b0b-954b-37bfbc7eaa2c | FN7: 46131.623 | FQ7: submitted_via_web | FS7: vjiNwcPYvtjoD8cL5yiJdz | FU7: uuid:81e01791-5ddb-4b0b-954b-37bfbc7eaa2c | FV7: 6
A8: HF core data | B8: 46131.831 | C8: 46131.841 | D8: Sahiwal 007 | E8: 46131 | F8: 20:04:00.000+05:00 | G8: 20:17:00.000+05:00 | H8: Ashfaq Ahmed Rao | I8: Sahiwal Division | J8: Sahiwal | K8: Sahiwal | L8: 30.669103 73.109867 131.10000610351562 16.236000061035156 | M8: 30.669103 | N8: 73.109867 | O8: 131.10001 | P8: 16.236 | Q8: Urban | R8: TenDoz Restaurant | S8: Public place | T8: Eatery ( Restaurant) | U8: Listed Venue | V8: 1 | W8: 0 | X8: TenDoz | Y8: No | AC8: No | AE8: No | AG8: Yes | AH8: Yes | AI8: Yes | AJ8: Does not apply / no one using tobacco or nicotine products | AK8: 0 | AL8: 0 | AM8: 0 | AN8: 0 | AO8: 0 | AP8: 0 | AQ8: 1 | AR8: 0 | AT8: Does not apply / no one using tobacco or nicotine products | AU8: No | AX8: No | BA8: No | BD8: No | BT8: Yes | BV8: Staff was totally aware and knowledgeable regarding above questions. | FL8: 729477083 | FM8: e9253ee9-20ef-47e3-9927-b9b7c8b31851 | FN8: 46131.633 | FQ8: submitted_via_web | FS8: vjiNwcPYvtjoD8cL5yiJdz | FU8: uuid:e9253ee9-20ef-47e3-9927-b9b7c8b31851 | FV8: 7
A9: HF core data | B9: 46131.841 | C9: 46131.854 | D9: Sahiwal 008 | E9: 46131 | F9: 20:22:00.000+05:00 | G9: 20:35:00.000+05:00 | H9: Ashfaq Ahmed Rao | I9: Sahiwal Division | J9: Sahiwal | K9: Sahiwal | L9: 30.67211 73.113588 130.50001525878906 20 | M9: 30.67211 | N9: 73.113588 | O9: 130.50002 | P9: 20 | Q9: Urban | R9: The Oven Piza | S9: Public place | T9: Eatery ( Restaurant) | U9: Listed Venue | V9: 1 | W9: 0 | X9: The Oven Pizza | Y9: Yes( add photo evidence) | Z9: 20260419_202714-20_27_51.jpg | AA9: https://kf.kobotoolbox.org/api/v2/assets/a7B4UGoSq7bg72YxNv837d/data/729486742/attachments/attQmWurb2xnk5vQYUXcBZP8/ | AB9: 1 | AC9: No | AE9: No | AG9: Yes | AH9: Yes | AI9: Yes | AJ9: Does not apply / no one using tobacco or nicotine products | AK9: 0 | AL9: 0 | AM9: 0 | AN9: 0 | AO9: 0 | AP9: 0 | AQ9: 1 | AR9: 0 | AT9: Does not apply / no one using tobacco or nicotine products | AU9: No | AX9: No | BA9: No | BD9: No | BT9: Yes | FL9: 729486742 | FM9: 32a5cd2c-460b-47a4-931b-210d71ad0b2d | FN9: 46131.645 | FQ9: submitted_via_web | FS9: vjiNwcPYvtjoD8cL5yiJdz | FU9: uuid:32a5cd2c-460b-47a4-931b-210d71ad0b2d | FV9: 8
A10: HF core data | B10: 46131.854 | C10: 46131.862 | D10: Sahiwal 009 | E10: 46131 | F10: 20:35:00.000+05:00 | G10: 20:48:00.000+05:00 | H10: Ashfaq Ahmed Rao | I10: Sahiwal Division | J10: Sahiwal | K10: Sahiwal | L10: 30.669333 73.112147 131.70001220703125 11.572999954223633 | M10: 30.669333 | N10: 73.112147 | O10: 131.70001 | P10: 11.573 | Q10: Urban | R10: Cheezious | S10: Public place | T10: Eatery ( Restaurant) | U10: Listed Venue | V10: 1 | W10: 0 | X10: Cheezious Restaurant | Y10: Yes( add photo evidence) | Z10: 20260419_203831-20_39_4.jpg | AA10: https://kf.kobotoolbox.org/api/v2/assets/a7B4UGoSq7bg72YxNv837d/data/729493008/attachments/attTaqdJGpRepv7S32meV9Xh/ | AB10: 1 | AC10: No | AE10: No | AG10: Yes | AH10: Yes | AI10: Yes | AJ10: Does not apply / no one using tobacco or nicotine products | AK10: 0 | AL10: 0 | AM10: 0 | AN10: 0 | AO10: 0 | AP10: 0 | AQ10: 1 | AR10: 0 | AT10: Does not apply / no one using tobacco or nicotine products | AU10: No | AX10: No | BA10: No | BD10: No | BT10: Yes | FL10: 729493008 | FM10: 6993718c-e9eb-4af4-88f9-a32b38db888a | FN10: 46131.653 | FQ10: submitted_via_web | FS10: vjiNwcPYvtjoD8cL5yiJdz | FU10: uuid:6993718c-e9eb-4af4-88f9-a32b38db888a | FV10: 9
A11: HF core data | B11: 46131.862 | C11: 46131.905 | D11: Sahiwal 10 | E11: 46131 | F11: 21:38:00.000+05:00 | G11: 21:55:00.000+05:00 | H11: Ashfaq Ahmed Rao | I11: Sahiwal Division | J11: Sahiwal | K11: Sahiwal | L11: 30.678097 73.0888 127.4000015258789 18.014999389648438 | M11: 30.678097 | N11: 73.0888 | O11: 127.4 | P11: 18.014999 | Q11: Urban | R11: Spice Villa | S11: Public place | T11: Eatery ( Restaurant) | U11: Listed Venue | V11: 1 | W11: 0 | X11: Spice Villa | Y11: Yes( add photo evidence) | Z11: 20260419_214050-21_41_0.jpg | AA11: https://kf.kobotoolbox.org/api/v2/assets/a7B4UGoSq7bg72YxNv837d/data/729526431/attachments/attHDaZGttmRVxddMD2Ba7Mo/ | AB11: 1 | AC11: No | AE11: No | AG11: No | AH11: Yes | AI11: Yes | AJ11: Does not apply / no one using tobacco or nicotine products | AK11: 0 | AL11: 0 | AM11: 0 | AN11: 0 | AO11: 0 | AP11: 0 | AQ11: 1 | AR11: 0 | AT11: Does not apply / no one using tobacco or nicotine products | AU11: No | AX11: No | BA11: No | BD11: No | BT11: Yes | FL11: 729526431 | FM11: 7c9eb1ed-dcab-401e-836b-d7c958e26c98 | FN11: 46131.697 | FQ11: submitted_via_web | FS11: vjiNwcPYvtjoD8cL5yiJdz | FU11: uuid:7c9eb1ed-dcab-401e-836b-d7c958e26c98 | FV11: 10
A12: HF core data | B12: 46128.619 | C12: 46132.341 | D12: Jhang0079 | E12: 46128 | F12: 15:13:00.000+05:00 | G12: 15:28:00.000+05:00 | H12: Tahir Mustafa | I12: Faisalabad Division | J12: Jhang | K12: Jhang | L12: 31.260871 72.352786 115.5999984741211 21.773000717163086 | M12: 31.260871 | N12: 72.352786 | O12: 115.6 | P12: 21.773001 | Q12: Urban | R12: Town guest house | S12: Public place | T12: Accommodation - Guesthouse | U12: Listed Venue | V12: 1 | W12: 0 | X12: Town guest house | Y12: No | AC12: No | AE12: No | AG12: Yes | AH12: Yes | AI12: Yes | AJ12: Does not apply / no one using tobacco or nicotine products | AK12: 0 | AL12: 0 | AM12: 0 | AN12: 0 | AO12: 0 | AP12: 0 | AQ12: 1 | AR12: 0 | AT12: Does not apply / no one using tobacco or nicotine products | AU12: No | AX12: No | BA12: No | BD12: No | BT12: Yes | BV12: Al Madina guest house map ma town guest tha TU liya ma na town guest Kya ha | FL12: 729957908 | FM12: c8f2d82c-001c-4dd6-93da-d2a8f57ad3a4 | FN12: 46132.328 | FQ12: submitted_via_web | FS12: vjiNwcPYvtjoD8cL5yiJdz | FU12: uuid:c8f2d82c-001c-4dd6-93da-d2a8f57ad3a4 | FV12: 11
A13: HF core data | B13: 46127.43 | C13: 46132.536 | D13: 0051 | E13: 46127 | F13: 11:20:00.000+05:00 | G13: 11:35:00.000+05:00 | H13: Tahir Mustafa | I13: Faisalabad Division | J13: Jhang | K13: Jhang | L13: 31.262447 72.330422 112.69999694824219 13.836000442504883 | M13: 31.262447 | N13: 72.330422 | O13: 112.7 | P13: 13.836 | Q13: Urban | R13: Chief Executive Office District Health Authority Jhang - Gojra Rd, Jhan | S13: Public place | T13: Government Offices - District Authorities Offices e.g. (Health, Education, DC Office, C & W Office, Social Welfare etc.) | U13: Listed Venue | V13: 1 | W13: 0 | X13: Chief Executive Office District Health Authority Jhang - Gojra Rd, Jhan | Y13: No | AC13: No | AE13: No | AG13: Yes | AH13: Yes | AI13: Yes | AJ13: Does not apply / no one using tobacco or nicotine products | AK13: 0 | AL13: 0 | AM13: 0 | AN13: 0 | AO13: 0 | AP13: 0 | AQ13: 1 | AR13: 0 | AT13: No | AU13: Yes ( add photo Evidence) | AV13: 1000074957-11_33_11.jpg | AW13: https://kf.kobotoolbox.org/api/v2/assets/a7B4UGoSq7bg72YxNv837d/data/729957928/attachments/attQqiFcFBKHZNXSE56A7oCR/ | AX13: Yes (add photo Evidence) | AY13: 1000074956-11_31_27.jpg | AZ13: https://kf.kobotoolbox.org/api/v2/assets/a7B4UGoSq7bg72YxNv837d/data/729957928/attachments/attErBzjuf28RHZRnZuFFuZK/ | BA13: No | BD13: No | BT13: Yes | BV13: Cooperative staff | FL13: 729957928 | FM13: 6081b523-71ce-42c4-b0af-2da5a35a61fc | FN13: 46132.328 | FQ13: submitted_via_web | FS13: vjiNwcPYvtjoD8cL5yiJdz | FU13: uuid:6081b523-71ce-42c4-b0af-2da5a35a61fc | FV13: 12
A14: HF core data | B14: 46127.488 | C14: 46132.537 | D14: Jhang 0052 | E14: 46128 | F14: 11:48:00.000+05:00 | G14: 12:05:00.000+05:00 | H14: Tahir Mustafa | I14: Faisalabad Division | J14: Jhang | K14: Jhang | L14: 31.279195 72.354852 113.5999984741211 0.9459999799728394 | M14: 31.279195 | N14: 72.354852 | O14: 113.6 | P14: 0.94599998 | Q14: Urban | R14: Expire college group of jhang | S14: Public place | T14: Entertainment/sports venue - Cinema | U14: Listed Venue Unlisted Venue | V14: 1 | W14: 1 | X14: Aspir college group jhang | Y14: No | AC14: No | AE14: No | AG14: Yes | AH14: Yes | AI14: Yes | AJ14: Does not apply / no one using tobacco or nicotine products | AK14: 0 | AL14: 0 | AM14: 0 | AN14: 0 | AO14: 0 | AP14: 0 | AQ14: 1 | AR14: 0 | AT14: Does not apply / no one using tobacco or nicotine products | AU14: No | AX14: No | BA14: No | BD14: No | BT14: Yes | FL14: 729958274 | FM14: bd7acc68-5518-48e9-adfd-33467a217a76 | FN14: 46132.328 | FQ14: submitted_via_web | FS14: vjiNwcPYvtjoD8cL5yiJdz | FU14: uuid:bd7acc68-5518-48e9-adfd-33467a217a76 | FV14: 13
A15: HF core data | B15: 46127.524 | C15: 46132.537 | D15: Jhang 0053 | E15: 46127 | F15: 12:35:00.000+05:00 | G15: 12:50:00.000+05:00 | H15: Tahir Mustafa | I15: Faisalabad Division | J15: Jhang | K15: Jhang | L15: 31.279135 72.313275 115.0999984741211 32.45100021362305 | M15: 31.279135 | N15: 72.313275 | O15: 115.1 | P15: 32.451 | Q15: Urban | R15: Municipal Corporation Circular Rd, Madina Colony, Jhang | S15: Public place | T15: Government Offices - District court/ Bar council | U15: Listed Venue | V15: 1 | W15: 0 | X15: Municipal Corporation Circular Rd, Madina Colony, Jhang | Y15: No | AC15: Yes | AD15: 1 | AE15: No | AG15: Yes | AH15: No | AI15: No | AJ15: Cigarette | AK15: 1 | AL15: 0 | AM15: 0 | AN15: 0 | AO15: 0 | AP15: 0 | AQ15: 0 | AR15: 0 | AT15: No | AU15: Yes ( add photo Evidence) | AV15: 1000074964-12_41_27.jpg | AW15: https://kf.kobotoolbox.org/api/v2/assets/a7B4UGoSq7bg72YxNv837d/data/729958722/attachments/attdTwZpgLCufAc3XqPDPTPz/ | AX15: No | BA15: No | BD15: No | BT15: Yes | FL15: 729958722 | FM15: 7ae4a41e-e745-44e2-82dd-55727f6a9143 | FN15: 46132.329 | FQ15: submitted_via_web | FS15: vjiNwcPYvtjoD8cL5yiJdz | FU15: uuid:7ae4a41e-e745-44e2-82dd-55727f6a9143 | FV15: 14
A16: HF core data | B16: 46127.552 | C16: 46132.537 | D16: Jhang 0054 | E16: 46127 | F16: 13:15:00.000+05:00 | G16: 13:30:00.000+05:00 | H16: Tahir Mustafa | I16: Faisalabad Division | J16: Jhang | K16: Jhang | L16: 31.277981 72.32404 123.77 1.4390000104904175 | M16: 31.277981 | N16: 72.32404 | O16: 123.77 | P16: 1.439 | Q16: Urban | R16: Punjab Food Authority Jhang Sadar | S16: Public place | T16: Government Offices - District Authorities Offices e.g. (Health, Education, DC Office, C & W Office, Social Welfare etc.) | U16: Listed Venue | V16: 1 | W16: 0 | X16: Punjab Food Authority Jhang Sadar | Y16: Yes( add photo evidence) | Z16: 1000074971-13_16_49.jpg | AA16: https://kf.kobotoolbox.org/api/v2/assets/a7B4UGoSq7bg72YxNv837d/data/729958993/attachments/attzL2764tSCcDhaQXSXVYxo/ | AB16: 1 | AC16: No | AE16: No | AG16: Yes | AH16: Yes | AI16: Yes | AJ16: Does not apply / no one using tobacco or nicotine products | AK16: 0 | AL16: 0 | AM16: 0 | AN16: 0 | AO16: 0 | AP16: 0 | AQ16: 1 | AR16: 0 | AT16: Does not apply / no one using tobacco or nicotine products | AU16: Yes ( add photo Evidence) | AV16: 1000074972-13_20_23.jpg | AW16: https://kf.kobotoolbox.org/api/v2/assets/a7B4UGoSq7bg72YxNv837d/data/729958993/attachments/attAwsRPSSoszhV74iJ33bVk/ | AX16: No | BA16: Yes (add photo Evidence) | BB16: 1000074974-13_24_2.jpg | BC16: https://kf.kobotoolbox.org/api/v2/assets/a7B4UGoSq7bg72YxNv837d/data/729958993/attachments/attnB39MHzPAofL28DgJF6pK/ | BD16: Yes (add photo Evidence) | BE16: 1000074973-13_23_10.jpg | BF16: https://kf.kobotoolbox.org/api/v2/assets/a7B4UGoSq7bg72YxNv837d/data/729958993/attachments/attnycw62XjaY7iMniXfsDrL/ | BG16: Does not apply / no one using tobacco or nicotine products | BH16: 0 | BI16: 0 | BJ16: 0 | BK16: 0 | BL16: 0 | BM16: 0 | BN16: 1 | BO16: 0 | BQ16: TVA not enforced in the district | BT16: Yes | FL16: 729958993 | FM16: 1725fbef-afb9-4b4f-b2a1-e333496e7f33 | FN16: 46132.329 | FQ16: submitted_via_web | FS16: vjiNwcPYvtjoD8cL5yiJdz | FU16: uuid:1725fbef-afb9-4b4f-b2a1-e333496e7f33 | FV16: 15
A17: HF core data | B17: 46127.578 | C17: 46132.537 | D17: Jhang 0055 | E17: 46127 | F17: 13:52:00.000+05:00 | G17: 14:08:00.000+05:00 | H17: Tahir Mustafa | I17: Faisalabad Division | J17: Jhang | K17: Jhang | L17: 31.27184 72.318195 115 16.93600082397461 | M17: 31.27184 | N17: 72.318195 | O17: 115 | P17: 16.936001 | Q17: Urban | R17: Habib Bank Limited (HBL) Shaheed Rd, | S17: Public place | T17: Bank - private | U17: Listed Venue | V17: 1 | W17: 0 | X17: Habib Bank Limited (HBL) Shaheed Rd, | Y17: No | AC17: No | AE17: No | AG17: Yes | AH17: Yes | AI17: No | AJ17: Does not apply / no one using tobacco or nicotine products | AK17: 0 | AL17: 0 | AM17: 0 | AN17: 0 | AO17: 0 | AP17: 0 | AQ17: 1 | AR17: 0 | AT17: No | AU17: No | AX17: No | BA17: No | BD17: No | BT17: Yes | FL17: 729959159 | FM17: efadde04-c949-4814-8daa-d8f1c10ee3da | FN17: 46132.329 | FQ17: submitted_via_web | FS17: vjiNwcPYvtjoD8cL5yiJdz | FU17: uuid:efadde04-c949-4814-8daa-d8f1c10ee3da | FV17: 16
A18: HF core data | B18: 46127.604 | C18: 46132.537 | D18: Jhang0056 | E18: 46127 | F18: 14:29:00.000+05:00 | G18: 14:45:00.000+05:00 | H18: Tahir Mustafa | I18: Faisalabad Division | J18: Jhang | K18: Jhang | L18: 31.268795 72.316982 115.19999694824219 12.597999572753906 | M18: 31.268795 | N18: 72.316982 | O18: 115.2 | P18: 12.598 | Q18: Urban | R18: Nighat Medical Complex Gojra Rd, near Post Office | S18: Public place | T18: Health Facility - Hospital | U18: Listed Venue | V18: 1 | W18: 0 | X18: Nighat Medical Complex Gojra Rd, near Post Office | Y18: Yes( add photo evidence) | Z18: 1000074977-14_43_44.jpg | AA18: https://kf.kobotoolbox.org/api/v2/assets/a7B4UGoSq7bg72YxNv837d/data/729959559/attachments/attAhyxwNri4LKK5kLaALrSy/ | AB18: 1 | AC18: No | AE18: No | AG18: Yes | AH18: Yes | AI18: Yes | AJ18: Does not apply / no one using tobacco or nicotine products | AK18: 0 | AL18: 0 | AM18: 0 | AN18: 0 | AO18: 0 | AP18: 0 | AQ18: 1 | AR18: 0 | AT18: Does not apply / no one using tobacco or nicotine products | AU18: No | AX18: No | BA18: No | BD18: No | BT18: Yes | FL18: 729959559 | FM18: 3ef1fc9a-01eb-4133-a224-4d3c3fe1632f | FN18: 46132.329 | FQ18: submitted_via_web | FS18: vjiNwcPYvtjoD8cL5yiJdz | FU18: uuid:3ef1fc9a-01eb-4133-a224-4d3c3fe1632f | FV18: 17
A19: HF core data | B19: 46127.624 | C19: 46132.538 | D19: Jhang 0057 | E19: 46127 | F19: 14:58:00.000+05:00 | G19: 15:12:00.000+05:00 | H19: Tahir Mustafa | I19: Faisalabad Division | J19: Jhang | K19: Jhang | L19: 31.261565 72.306956 116.58 10.428999900817871 | M19: 31.261565 | N19: 72.306956 | O19: 116.58 | P19: 10.429 | Q19: Urban | R19: Iqbal Memorial Hospital Bhakkar Rd, Jhang Sadar | S19: Public place | T19: Health Facility - Hospital | U19: Listed Venue | V19: 1 | W19: 0 | X19: Iqbal Memorial Hospital Bhakkar Rd, Jhang Sadar | Y19: Yes( add photo evidence) | Z19: 1000074982-15_3_7.jpg | AA19: https://kf.kobotoolbox.org/api/v2/assets/a7B4UGoSq7bg72YxNv837d/data/729959818/attachments/attWHi2rLujorkU4h5nMhNep/ | AB19: 1 | AC19: No | AE19: No | AG19: Yes | AH19: Yes | AI19: Yes | AJ19: Does not apply / no one using tobacco or nicotine products | AK19: 0 | AL19: 0 | AM19: 0 | AN19: 0 | AO19: 0 | AP19: 0 | AQ19: 1 | AR19: 0 | AT19: Does not apply / no one using tobacco or nicotine products | AU19: No | AX19: No | BA19: No | BD19: No | BT19: Yes | FL19: 729959818 | FM19: f41f2fd5-90f4-426d-8483-88b10a215bbf | FN19: 46132.329 | FQ19: submitted_via_web | FS19: vjiNwcPYvtjoD8cL5yiJdz | FU19: uuid:f41f2fd5-90f4-426d-8483-88b10a215bbf | FV19: 18
A20: HF core data | B20: 46127.663 | C20: 46132.538 | D20: Jhang0058 | E20: 46127 | F20: 15:55:00.000+05:00 | G20: 16:10:00.000+05:00 | H20: Tahir Mustafa | I20: Faisalabad Division | J20: Jhang | K20: Jhang | L20: 31.274381 72.316068 115.80000305175781 17.81599998474121 | M20: 31.274381 | N20: 72.316068 | O20: 115.8 | P20: 17.816 | Q20: Rural | R20: Telenor Pakistan Franchise Shaheed Rd, Jhang Private Offices 2 | S20: Public place | T20: Bank - private | U20: Listed Venue | V20: 1 | W20: 0 | X20: Telenor Pakistan Franchise Shaheed Rd, Jhang Private Offices 2 | Y20: No | AC20: No | AE20: No | AG20: Yes | AH20: Yes | AI20: Yes | AJ20: Does not apply / no one using tobacco or nicotine products | AK20: 0 | AL20: 0 | AM20: 0 | AN20: 0 | AO20: 0 | AP20: 0 | AQ20: 1 | AR20: 0 | AT20: Does not apply / no one using tobacco or nicotine products | AU20: No | AX20: No | BA20: No | BD20: No | BT20: Yes | FL20: 729960840 | FM20: e7416257-7c09-4d1d-9834-81b48e09f794 | FN20: 46132.33 | FQ20: submitted_via_web | FS20: vjiNwcPYvtjoD8cL5yiJdz | FU20: uuid:e7416257-7c09-4d1d-9834-81b48e09f794 | FV20: 19
A21: HF core data | B21: 46127.682 | C21: 46132.538 | D21: Jhang 0059 | E21: 46127 | F21: 16:21:00.000+05:00 | G21: 16:37:00.000+05:00 | H21: Tahir Mustafa | I21: Faisalabad Division | J21: Jhang | K21: Jhang | L21: 31.262903 72.335495 115.4000015258789 21.83799934387207 | M21: 31.262903 | N21: 72.335495 | O21: 115.4 | P21: 21.837999 | Q21: Urban | R21: Meet And Eat Opp DHQ Hospital Jhang Gojra Rd | S21: Public place | T21: Eatery ( Restaurant) | U21: Listed Venue | V21: 1 | W21: 0 | X21: Meet And Eat Opp DHQ Hospital Jhang Gojra Rd | Y21: No | AC21: No | AE21: No | AG21: Yes | AH21: Yes | AI21: Yes | AJ21: Does not apply / no one using tobacco or nicotine products | AK21: 0 | AL21: 0 | AM21: 0 | AN21: 0 | AO21: 0 | AP21: 0 | AQ21: 1 | AR21: 0 | AT21: Does not apply / no one using tobacco or nicotine products | AU21: No | AX21: No | BA21: No | BD21: No | BT21: Yes | FL21: 729961044 | FM21: 3f8b283a-bd5b-4871-8f87-097bc60c414d | FN21: 46132.33 | FQ21: submitted_via_web | FS21: vjiNwcPYvtjoD8cL5yiJdz | FU21: uuid:3f8b283a-bd5b-4871-8f87-097bc60c414d | FV21: 20
A22: HF core data | B22: 46127.702 | C22: 46132.538 | D22: Jhang 0060 | E22: 46127 | F22: 17:15:00.000+05:00 | G22: 17:30:00.000+05:00 | H22: Tahir Mustafa | I22: Faisalabad Division | J22: Jhang | K22: Jhang | L22: 31.268155 72.345802 78.42 1.784999966621399 | M22: 31.268155 | N22: 72.345802 | O22: 78.42 | P22: 1.785 | Q22: Urban | R22: Sakina Hospital Dar-ul-Sakina Rd, Ghaziabad, Jhang | S22: Public place | T22: Health Facility - Hospital | U22: Listed Venue | V22: 1 | W22: 0 | X22: Sakina Hospital Dar-ul-Sakina Rd, Ghaziabad, Jhang | Y22: Yes( add photo evidence) | Z22: 1000075023-17_26_41.jpg | AA22: https://kf.kobotoolbox.org/api/v2/assets/a7B4UGoSq7bg72YxNv837d/data/729961277/attachments/attr6A2SWaG37uqQmLsEzHy5/ | AB22: 1 | AC22: No | AE22: No | AG22: Yes | AH22: Yes | AI22: Yes | AJ22: Does not apply / no one using tobacco or nicotine products | AK22: 0 | AL22: 0 | AM22: 0 | AN22: 0 | AO22: 0 | AP22: 0 | AQ22: 1 | AR22: 0 | AT22: Does not apply / no one using tobacco or nicotine products | AU22: No | AX22: No | BA22: No | BD22: No | BT22: Yes | FL22: 729961277 | FM22: 28ec7e7a-907a-4cf3-ac41-88a04d877eb4 | FN22: 46132.33 | FQ22: submitted_via_web | FS22: vjiNwcPYvtjoD8cL5yiJdz | FU22: uuid:28ec7e7a-907a-4cf3-ac41-88a04d877eb4 | FV22: 21
A23: HF core data | B23: 46127.747 | C23: 46132.539 | D23: Jhang 0061 | E23: 46127 | F23: 17:56:00.000+05:00 | G23: 18:11:00.000+05:00 | H23: Tahir Mustafa | I23: Faisalabad Division | J23: Jhang | K23: Jhang | L23: 31.27016 72.317782 113.69999694824219 20 | M23: 31.27016 | N23: 72.317782 | O23: 113.7 | P23: 20 | Q23: Urban | R23: The hot spot cafe and restaurants | S23: Public place | T23: Eatery ( Restaurant) | U23: Listed Venue | V23: 1 | W23: 0 | X23: The hot spot cafe and restaurants | Y23: No | AC23: No | AE23: No | AG23: Yes | AH23: No | AI23: No | AJ23: Does not apply / no one using tobacco or nicotine products | AK23: 0 | AL23: 0 | AM23: 0 | AN23: 0 | AO23: 0 | AP23: 0 | AQ23: 1 | AR23: 0 | AT23: Does not apply / no one using tobacco or nicotine products | AU23: No | AX23: No | BA23: No | BD23: No | BT23: Yes | FL23: 729961744 | FM23: 3427bdd2-120c-4314-b5ef-1edbb59f523c | FN23: 46132.33 | FQ23: submitted_via_web | FS23: vjiNwcPYvtjoD8cL5yiJdz | FU23: uuid:3427bdd2-120c-4314-b5ef-1edbb59f523c | FV23: 22
A24: HF core data | B24: 46127.813 | C24: 46132.539 | D24: Jhang 0062 | E24: 46127 | F24: 19:35:00.000+05:00 | G24: 19:50:00.000+05:00 | H24: Tahir Mustafa | I24: Faisalabad Division | J24: Jhang | K24: Jhang | L24: 31.277684 72.321064 114.80000305175781 24.851999282836914 | M24: 31.277684 | N24: 72.321064 | O24: 114.8 | P24: 24.851999 | Q24: Urban | R24: al jannat bakery | S24: Public place | T24: Eatery ( Bakery) | U24: Unlisted Venue | V24: 0 | W24: 1 | X24: Al jannat bakery | Y24: No | AC24: No | AE24: No | AG24: No | AH24: Yes | AI24: Yes | AJ24: Does not apply / no one using tobacco or nicotine products | AK24: 0 | AL24: 0 | AM24: 0 | AN24: 0 | AO24: 0 | AP24: 0 | AQ24: 1 | AR24: 0 | AT24: Does not apply / no one using tobacco or nicotine products | AU24: Yes ( add photo Evidence) | AV24: 1000075056-19_41_16.jpg | AW24: https://kf.kobotoolbox.org/api/v2/assets/a7B4UGoSq7bg72YxNv837d/data/729962050/attachments/att58Q7qxVkogZtx7RzFbAd6/ | AX24: Yes (add photo Evidence) | AY24: 1000075057-19_41_39.jpg | AZ24: https://kf.kobotoolbox.org/api/v2/assets/a7B4UGoSq7bg72YxNv837d/data/729962050/attachments/attMmB3pb3QG4FStoGiBqa6N/ | BA24: No | BD24: No | BT24: Yes | FL24: 729962050 | FM24: 95e833c7-0812-4681-9d52-842e64f54d57 | FN24: 46132.331 | FQ24: submitted_via_web | FS24: vjiNwcPYvtjoD8cL5yiJdz | FU24: uuid:95e833c7-0812-4681-9d52-842e64f54d57 | FV24: 23
A25: HF core data | B25: 46127.823 | C25: 46132.539 | D25: Jhang0063 | E25: 46127 | F25: 19:55:00.000+05:00 | G25: 20:10:00.000+05:00 | H25: Tahir Mustafa | I25: Faisalabad Division | J25: Jhang | K25: Jhang | L25: 31.276723 72.320416 115 18.354000091552734 | M25: 31.276723 | N25: 72.320416 | O25: 115 | P25: 18.354 | Q25: Urban | R25: Pso of jhang | S25: Retail outlet /Point of Sale (POS) | DC25: Fuel station | DE25: Pso of jhang | DF25: Ayub Chowk | DG25: No | DH25: Not Applicable/ No Young buyers visited | DI25: No | DL25: No | DP25: No | DT25: No | DW25: No | DX25: No | EA25: No | EE25: Yes | EF25: Capstan | EG25: 1000075070-19_56_49.jpg | EH25: https://kf.kobotoolbox.org/api/v2/assets/a7B4UGoSq7bg72YxNv837d/data/729962878/attachments/attNuj4aWvMr8n6QrsjazZmY/ | EI25: No | EM25: No | EQ25: No | EU25: No | EY25: No | FC25: No | FG25: Yes | FH25: Yes | FL25: 729962878 | FM25: 81ecf395-5223-4a18-bdd0-9c1114322db3 | FN25: 46132.331 | FQ25: submitted_via_web | FS25: vjiNwcPYvtjoD8cL5yiJdz | FU25: uuid:81ecf395-5223-4a18-bdd0-9c1114322db3 | FV25: 24
A26: HF core data | B26: 46128.255 | C26: 46132.54 | D26: Jhang0064 | E26: 46128 | F26: 06:06:00.000+05:00 | G26: 06:18:00.000+05:00 | H26: Tahir Mustafa | I26: Faisalabad Division | J26: Jhang | K26: Jhang | L26: 31.277014 72.320864 114.80000305175781 23.39299964904785 | M26: 31.277014 | N26: 72.320864 | O26: 114.8 | P26: 23.393 | Q26: Urban | R26: Abdul Majid panwala | S26: Retail outlet /Point of Sale (POS) | DC26: Tobacco shop | DE26: Abdul Majid panwala | DF26: Ayub Chowk | DG26: No | DH26: Not Applicable/ No Young buyers visited | DI26: No | DL26: No | DP26: No | DT26: No | DW26: Yes | DX26: Yes ( add photo evidence) | DY26: 1000075119-6_10_15.jpg | DZ26: https://kf.kobotoolbox.org/api/v2/assets/a7B4UGoSq7bg72YxNv837d/data/729963344/attachments/att6P7dBLtzPnHBdMFjRCwah/ | EA26: Yes | EB26: Capstan | EC26: 1000075119-6_10_31.jpg | ED26: https://kf.kobotoolbox.org/api/v2/assets/a7B4UGoSq7bg72YxNv837d/data/729963344/attachments/attjqK9bS8LDua3GPqoqVNWH/ | EE26: Yes | EF26: Capstan | EG26: 1000075119-6_10_44.jpg | EH26: https://kf.kobotoolbox.org/api/v2/assets/a7B4UGoSq7bg72YxNv837d/data/729963344/attachments/attLk2ZUxqHycuQACbMqRxeV/ | EI26: No | EM26: No | EQ26: Yes | ER26: Zyx | ES26: 1000075120-11_36_54.jpg | ET26: https://kf.kobotoolbox.org/api/v2/assets/a7B4UGoSq7bg72YxNv837d/data/729963344/attachments/attKWpqxzNpmHRtowptQmekf/ | EU26: Yes | EV26: Zyx | EW26: 1000075120-6_11_57.jpg | EX26: https://kf.kobotoolbox.org/api/v2/assets/a7B4UGoSq7bg72YxNv837d/data/729963344/attachments/attRWZj4wxaSmijKh2Zfjsc8/ | EY26: Yes ( add photo evidence) | EZ26: 1000075121-6_12_20.jpg | FA26: https://kf.kobotoolbox.org/api/v2/assets/a7B4UGoSq7bg72YxNv837d/data/729963344/attachments/attXdGBdZp3DPcoa86NsJrud/ | FB26: World no 1 | FC26: No | FG26: Yes | FH26: Yes | FL26: 729963344 | FM26: 898b69c6-4f10-4896-8047-e74ec02fac21 | FN26: 46132.331 | FQ26: submitted_via_web | FS26: vjiNwcPYvtjoD8cL5yiJdz | FU26: uuid:898b69c6-4f10-4896-8047-e74ec02fac21 | FV26: 25
A27: HF core data | B27: 46128.261 | C27: 46132.542 | D27: Jhang0065 | E27: 46128 | F27: 06:21:00.000+05:00 | G27: 06:26:00.000+05:00 | H27: Tahir Mustafa | I27: Faisalabad Division | J27: Jhang | K27: Jhang | L27: 31.282936 72.33188 111.0999984741211 77.5999984741211 | M27: 31.282936 | N27: 72.33188 | O27: 111.1 | P27: 77.599998 | Q27: Urban | R27: Sargodha road | S27: Public Service Vehicle (PSV) | BW27: other | BX27: Raksha | BY27: Raksha | BZ27: Sargodha road | CA27: No | CB27: No | CC27: No | CD27: No | CF27: Does not apply / no one using tobacco or nicotine products | CG27: 0 | CH27: 0 | CI27: 0 | CJ27: 0 | CK27: 0 | CL27: 0 | CM27: 1 | CN27: 0 | CP27: Does not apply / no one smoking | CQ27: No | CT27: No | CW27: Yes | CX27: Yes | CY27: Yes | CZ27: Yes | FL27: 729967349 | FM27: cee959d5-d6a5-439a-b8ee-6cf07e16d329 | FN27: 46132.334 | FQ27: submitted_via_web | FS27: vjiNwcPYvtjoD8cL5yiJdz | FU27: uuid:cee959d5-d6a5-439a-b8ee-6cf07e16d329 | FV27: 26
A28: HF core data | B28: 46128.272 | C28: 46132.542 | D28: Jhang066 | E28: 46128 | F28: 06:31:00.000+05:00 | G28: 06:45:00.000+05:00 | H28: Tahir Mustafa | I28: Faisalabad Division | J28: Jhang | K28: Jhang | L28: 31.282935 72.331878 111.0999984741211 87.5999984741211 | M28: 31.282935 | N28: 72.331878 | O28: 111.1 | P28: 87.599998 | Q28: Urban | R28: Akhtar pan shop | S28: Retail outlet /Point of Sale (POS) | DC28: Tobacco shop | DE28: Akhtar pan shop | DF28: Sargodha road | DG28: No | DH28: Not Applicable/ No Young buyers visited | DI28: No | DL28: No | DP28: No | DT28: No | DW28: Yes | DX28: Yes ( add photo evidence) | DY28: 1000075123-6_36_5.jpg | DZ28: https://kf.kobotoolbox.org/api/v2/assets/a7B4UGoSq7bg72YxNv837d/data/729967485/attachments/attiRf2LaEN5ABPLtRswB3X9/ | EA28: Yes | EB28: Capstan | EC28: 1000075123-6_36_18.jpg | ED28: https://kf.kobotoolbox.org/api/v2/assets/a7B4UGoSq7bg72YxNv837d/data/729967485/attachments/attyszacAmb5PooL4Qc6QiK4/ | EE28: No | EI28: No | EM28: No | EQ28: No | EU28: No | EY28: Yes ( add photo evidence) | EZ28: 1000075124-6_36_57.jpg | FA28: https://kf.kobotoolbox.org/api/v2/assets/a7B4UGoSq7bg72YxNv837d/data/729967485/attachments/attPUAArxai2hBjMheznqAUP/ | FB28: Capstan 172 sale | FC28: No | FG28: Yes | FH28: Yes | FL28: 729967485 | FM28: 669206a7-6433-405f-89c5-37172d6fb27e | FN28: 46132.334 | FQ28: submitted_via_web | FS28: vjiNwcPYvtjoD8cL5yiJdz | FU28: uuid:669206a7-6433-405f-89c5-37172d6fb27e | FV28: 27
A29: HF core data | B29: 46128.292 | C29: 46132.542 | D29: Jhang0067 | E29: 46128 | F29: 07:00:00.000+05:00 | G29: 07:11:00.000+05:00 | H29: Tahir Mustafa | I29: Faisalabad Division | J29: Jhang | K29: Jhang | L29: 31.273754 72.319133 114.19999694824219 5.494999885559082 | M29: 31.273754 | N29: 72.319133 | O29: 114.2 | P29: 5.4949999 | Q29: Urban | R29: Shell v power petrol | S29: Retail outlet /Point of Sale (POS) | DC29: Fuel station | DE29: Shell v power | DF29: Car wash | DG29: No | DH29: Not Applicable/ No Young buyers visited | DI29: No | DL29: No | DP29: No | DT29: No | DW29: No | DX29: No | EA29: No | EE29: No | EI29: No | EM29: No | EQ29: No | EU29: No | EY29: No | FC29: No | FG29: No | FH29: Yes | FL29: 729967601 | FM29: cc7e7013-7357-40e8-a6d6-9ad41bbbb465 | FN29: 46132.334 | FQ29: submitted_via_web | FS29: vjiNwcPYvtjoD8cL5yiJdz | FU29: uuid:cc7e7013-7357-40e8-a6d6-9ad41bbbb465 | FV29: 28
A30: HF core data | B30: 46128.299 | C30: 46132.542 | D30: Jhang0068 | E30: 46128 | F30: 07:15:00.000+05:00 | G30: 07:28:00.000+05:00 | H30: Tahir Mustafa | I30: Faisalabad Division | J30: Jhang | K30: Jhang | L30: 31.257982 72.306018 112.5 32.0989990234375 | M30: 31.257982 | N30: 72.306018 | O30: 112.5 | P30: 32.098999 | Q30: Urban | R30: Daewoo Express Terminal Jhang–Faisalabad Rd, Jhang | S30: Public place | T30: Transport Terminal (Bus terminal) | U30: Listed Venue | V30: 1 | W30: 0 | X30: Daewoo Express Terminal Jhang–Faisalabad Rd, Jhang | Y30: Yes( add photo evidence) | Z30: 1000075126-7_13_32.jpg | AA30: https://kf.kobotoolbox.org/api/v2/assets/a7B4UGoSq7bg72YxNv837d/data/729967768/attachments/attn3JSCpCy25LcgfFfJSQPV/ | AB30: 1 | AC30: No | AE30: No | AG30: Yes | AH30: Yes | AI30: Yes | AJ30: Does not apply / no one using tobacco or nicotine products | AK30: 0 | AL30: 0 | AM30: 0 | AN30: 0 | AO30: 0 | AP30: 0 | AQ30: 1 | AR30: 0 | AT30: Does not apply / no one using tobacco or nicotine products | AU30: No | AX30: No | BA30: No | BD30: No | BT30: Yes | FL30: 729967768 | FM30: 7907d647-6261-4a01-b052-7d1903d0edd2 | FN30: 46132.334 | FQ30: submitted_via_web | FS30: vjiNwcPYvtjoD8cL5yiJdz | FU30: uuid:7907d647-6261-4a01-b052-7d1903d0edd2 | FV30: 29
A31: HF core data | B31: 46128.302 | C31: 46132.543 | D31: Jhang0069 | E31: 46128 | F31: 07:39:00.000+05:00 | G31: 07:50:00.000+05:00 | H31: Tahir Mustafa | I31: Faisalabad Division | J31: Jhang | K31: Jhang | L31: 31.280103 72.31512 114.30000305175781 33.499000549316406 | M31: 31.280103 | N31: 72.31512 | O31: 114.3 | P31: 33.499001 | Q31: Urban | R31: Altron permium | S31: Retail outlet /Point of Sale (POS) | DC31: Fuel station | DE31: Altron permum | DF31: Farooq e Azam road | DG31: No | DH31: Not Applicable/ No Young buyers visited | DI31: No | DL31: No | DP31: No | DT31: No | DW31: No | DX31: No | EA31: No | EE31: No | EI31: No | EM31: No | EQ31: No | EU31: No | EY31: No | FC31: No | FG31: Yes | FH31: Yes | FL31: 729968050 | FM31: b4d0312d-d418-4aef-89a1-f3752929f67a | FN31: 46132.334 | FQ31: submitted_via_web | FS31: vjiNwcPYvtjoD8cL5yiJdz | FU31: uuid:b4d0312d-d418-4aef-89a1-f3752929f67a | FV31: 30
A32: HF core data | B32: 46128.336 | C32: 46132.543 | D32: Jhang 70 | E32: 46128 | F32: 08:04:00.000+05:00 | G32: 08:19:00.000+05:00 | H32: Tahir Mustafa | I32: Faisalabad Division | J32: Jhang | K32: Jhang | L32: 31.277041 72.32083 114.69999694824219 23.10099983215332 | M32: 31.277041 | N32: 72.32083 | O32: 114.7 | P32: 23.101 | Q32: Urban | R32: Gilani restaurant | S32: Public place | T32: Eatery ( Restaurant) | U32: Unlisted Venue | V32: 0 | W32: 1 | X32: Gilani restaurant | Y32: No | AC32: No | AE32: No | AG32: Yes | AH32: Yes | AI32: Yes | AJ32: Does not apply / no one using tobacco or nicotine products | AK32: 0 | AL32: 0 | AM32: 0 | AN32: 0 | AO32: 0 | AP32: 0 | AQ32: 1 | AR32: 0 | AT32: Does not apply / no one using tobacco or nicotine products | AU32: No | AX32: Yes (add photo Evidence) | AY32: 1000075127-8_7_43.jpg | AZ32: https://kf.kobotoolbox.org/api/v2/assets/a7B4UGoSq7bg72YxNv837d/data/729968199/attachments/attctcfKdGsHxxkRUiT8SdTm/ | BA32: No | BD32: Yes (add photo Evidence) | BE32: 1000075129-8_8_18.jpg | BF32: https://kf.kobotoolbox.org/api/v2/assets/a7B4UGoSq7bg72YxNv837d/data/729968199/attachments/attJYhTM6NLPyL2kZAhQpR69/ | BG32: Does not apply / no one using tobacco or nicotine products | BH32: 0 | BI32: 0 | BJ32: 0 | BK32: 0 | BL32: 0 | BM32: 0 | BN32: 1 | BO32: 0 | BQ32: No | BT32: Yes | FL32: 729968199 | FM32: 724ebff3-bdf9-478b-8c3d-852694303771 | FN32: 46132.334 | FQ32: submitted_via_web | FS32: vjiNwcPYvtjoD8cL5yiJdz | FU32: uuid:724ebff3-bdf9-478b-8c3d-852694303771 | FV32: 31
A33: HF core data | B33: 46128.353 | C33: 46132.543 | D33: Jhang0071 | E33: 46128 | F33: 08:29:00.000+05:00 | G33: 08:34:00.000+05:00 | H33: Tahir Mustafa | I33: Faisalabad Division | J33: Jhang | K33: Jhang | L33: 31.275648 72.322076 114.30000305175781 17.91900062561035 | M33: 31.275648 | N33: 72.322076 | O33: 114.3 | P33: 17.919001 | Q33: Urban | R33: Kachhari road | S33: Public Service Vehicle (PSV) | BW33: other | BX33: Raksha | BY33: Raksha | BZ33: Kachhari road | CA33: No | CB33: No | CC33: No | CD33: No | CF33: Does not apply / no one using tobacco or nicotine products | CG33: 0 | CH33: 0 | CI33: 0 | CJ33: 0 | CK33: 0 | CL33: 0 | CM33: 1 | CN33: 0 | CP33: Does not apply / no one smoking | CQ33: No | CT33: No | CW33: No | CX33: Yes | CY33: Yes | CZ33: Yes | FL33: 729968338 | FM33: cbcf5ab8-06cd-4172-ac4f-9ce1e0ce1a4e | FN33: 46132.334 | FQ33: submitted_via_web | FS33: vjiNwcPYvtjoD8cL5yiJdz | FU33: uuid:cbcf5ab8-06cd-4172-ac4f-9ce1e0ce1a4e | FV33: 32
A34: HF core data | B34: 46128.358 | C34: 46132.543 | D34: Jhang72 | E34: 46128 | F34: 08:40:00.000+05:00 | G34: 08:55:00.000+05:00 | H34: Tahir Mustafa | I34: Faisalabad Division | J34: Jhang | K34: Jhang | L34: 31.260842 72.351215 114.69999694824219 46.869998931884766 | M34: 31.260842 | N34: 72.351215 | O34: 114.7 | P34: 46.869999 | Q34: Urban | R34: Hockey stadium | S34: Public place | T34: Entertainment/sports venue - sport ground | U34: Listed Venue | V34: 1 | W34: 0 | X34: Hockey stadium | Y34: No | AC34: No | AE34: No | AG34: Yes | AH34: No | AI34: No | AJ34: Does not apply / no one using tobacco or nicotine products | AK34: 0 | AL34: 0 | AM34: 0 | AN34: 0 | AO34: 0 | AP34: 0 | AQ34: 1 | AR34: 0 | AT34: Does not apply / no one using tobacco or nicotine products | AU34: No | AX34: No | BA34: No | BD34: No | BT34: Yes | FL34: 729968499 | FM34: 9b933d40-b699-4b06-aaa5-8ab8c9aad8bb | FN34: 46132.335 | FQ34: submitted_via_web | FS34: vjiNwcPYvtjoD8cL5yiJdz | FU34: uuid:9b933d40-b699-4b06-aaa5-8ab8c9aad8bb | FV34: 33
A35: HF core data | B35: 46128.368 | C35: 46132.543 | D35: Jhang0073 | E35: 46128 | F35: 00:25:00.000+05:00 | G35: 00:39:00.000+05:00 | H35: Tahir Mustafa | I35: Faisalabad Division | J35: Jhang | K35: Jhang | L35: 31.270794 72.329522 120.637 1.6480000019073486 | M35: 31.270794 | N35: 72.329522 | O35: 120.637 | P35: 1.648 | Q35: Urban | R35: THE ROOMI EDUCATION SYSTEM JHANG opposite M | S35: Public place | T35: Educational institution - School (Private) | U35: Listed Venue | V35: 1 | W35: 0 | X35: THE ROOMI EDUCATION SYSTEM JHANG opposite M | Y35: No | AC35: No | AE35: No | AG35: Yes | AH35: Yes | AI35: Yes | AJ35: Does not apply / no one using tobacco or nicotine products | AK35: 0 | AL35: 0 | AM35: 0 | AN35: 0 | AO35: 0 | AP35: 0 | AQ35: 1 | AR35: 0 | AT35: Does not apply / no one using tobacco or nicotine products | AU35: No | AX35: Yes (add photo Evidence) | AY35: 1000075234-12_28_12.jpg | AZ35: https://kf.kobotoolbox.org/api/v2/assets/a7B4UGoSq7bg72YxNv837d/data/729968642/attachments/attUnfvLyjXBaYPNctTGiqqc/ | BA35: No | BD35: No | BT35: Yes | FL35: 729968642 | FM35: b2cb1100-7f9d-4887-8900-b25dacca2701 | FN35: 46132.335 | FQ35: submitted_via_web | FS35: vjiNwcPYvtjoD8cL5yiJdz | FU35: uuid:b2cb1100-7f9d-4887-8900-b25dacca2701 | FV35: 34
A36: HF core data | B36: 46128.395 | C36: 46132.543 | D36: Jhang0074 | E36: 46128 | F36: 13:00:00.000+05:00 | G36: 01:15:00.000+05:00 | H36: Tahir Mustafa | I36: Faisalabad Division | J36: Jhang | K36: Jhang | L36: 31.26616 72.322457 131.659 15 | M36: 31.26616 | N36: 72.322457 | O36: 131.659 | P36: 15 | Q36: Urban | R36: Beaconhouse school system jhang camp | S36: Public place | T36: Educational institution - School (Private) | U36: Unlisted Venue | V36: 0 | W36: 1 | X36: Beaconhouse school system jhang camp | Y36: No | AC36: No | AE36: No | AG36: Yes | AH36: Yes | AI36: Yes | AJ36: Does not apply / no one using tobacco or nicotine products | AK36: 0 | AL36: 0 | AM36: 0 | AN36: 0 | AO36: 0 | AP36: 0 | AQ36: 1 | AR36: 0 | AT36: Does not apply / no one using tobacco or nicotine products | AU36: No | AX36: No | BA36: No | BD36: No | BT36: Yes | BV36: 6 THE INNOVATIVE HOUSE (BOYS) HIGH SCHOOL Block No 7 Jhang City map is not correct provide so unlisted give | FL36: 729968859 | FM36: 6ed01fac-36e8-46a2-9f7d-e0f624c27c94 | FN36: 46132.335 | FQ36: submitted_via_web | FS36: vjiNwcPYvtjoD8cL5yiJdz | FU36: uuid:6ed01fac-36e8-46a2-9f7d-e0f624c27c94 | FV36: 35
A37: HF core data | B37: 46128.52 | C37: 46132.543 | D37: Jhang 0075 | E37: 46128 | F37: 13:20:00.000+05:00 | G37: 13:35:00.000+05:00 | H37: Tahir Mustafa | I37: Faisalabad Division | J37: Jhang | K37: Jhang | L37: 31.25488 72.362708 113.9000015258789 52.400001525878906 | M37: 31.25488 | N37: 72.362708 | O37: 113.9 | P37: 52.400002 | Q37: Urban | R37: Punjab college of jhang | S37: Public place | T37: Educational institution - College | U37: Listed Venue | V37: 1 | W37: 0 | X37: Punjab college of jhang | Y37: No | AC37: No | AE37: No | AG37: Yes | AH37: Yes | AI37: Yes | AJ37: Does not apply / no one using tobacco or nicotine products | AK37: 0 | AL37: 0 | AM37: 0 | AN37: 0 | AO37: 0 | AP37: 0 | AQ37: 1 | AR37: 0 | AT37: Does not apply / no one using tobacco or nicotine products | AU37: No | AX37: No | BA37: No | BD37: No | BT37: Yes | FL37: 729968988 | FM37: 95c9ce7f-e695-48ae-8c41-bf93a929b1eb | FN37: 46132.335 | FQ37: submitted_via_web | FS37: vjiNwcPYvtjoD8cL5yiJdz | FU37: uuid:95c9ce7f-e695-48ae-8c41-bf93a929b1eb | FV37: 36
A38: HF core data | B38: 46128.564 | C38: 46132.543 | D38: Jhang 0076 | E38: 46128 | F38: 13:36:00.000+05:00 | G38: 13:50:00.000+05:00 | H38: Tahir Mustafa | I38: Faisalabad Division | J38: Jhang | K38: Jhang | L38: 31.25439 72.360583 113.69999694824219 38.45000076293945 | M38: 31.25439 | N38: 72.360583 | O38: 113.7 | P38: 38.450001 | Q38: Urban | R38: Govt graduate college of jhang | S38: Public place | T38: Educational institution - College | U38: Listed Venue | V38: 1 | W38: 0 | X38: Govt granted college gojor rd | Y38: No | AC38: No | AE38: No | AG38: Yes | AH38: Yes | AI38: Yes | AJ38: Does not apply / no one using tobacco or nicotine products | AK38: 0 | AL38: 0 | AM38: 0 | AN38: 0 | AO38: 0 | AP38: 0 | AQ38: 1 | AR38: 0 | AT38: Does not apply / no one using tobacco or nicotine products | AU38: No | AX38: No | BA38: No | BD38: No | BT38: Yes | FL38: 729969246 | FM38: b2fdee1e-5315-4172-a4a7-ecc78ecef048 | FN38: 46132.335 | FQ38: submitted_via_web | FS38: vjiNwcPYvtjoD8cL5yiJdz | FU38: uuid:b2fdee1e-5315-4172-a4a7-ecc78ecef048 | FV38: 37
A39: HF core data | B39: 46128.569 | C39: 46132.543 | D39: Jhang 0077 | E39: 46128 | F39: 13:54:00.000+05:00 | G39: 14:00:00.000+05:00 | H39: Tahir Mustafa | I39: Sahiwal Division | J39: Jhang | K39: Jhang | L39: 31.256604 72.350908 113.4000015258789 49.551998138427734 | M39: 31.256604 | N39: 72.350908 | O39: 113.4 | P39: 49.551998 | Q39: Urban | R39: Gojra road | S39: Public Service Vehicle (PSV) | BW39: other | BX39: Raksha | BY39: Raksha | BZ39: Gojra road | CA39: No | CB39: No | CC39: No | CD39: No | CF39: Does not apply / no one using tobacco or nicotine products | CG39: 0 | CH39: 0 | CI39: 0 | CJ39: 0 | CK39: 0 | CL39: 0 | CM39: 1 | CN39: 0 | CP39: Does not apply / no one smoking | CQ39: No | CT39: No | CW39: Yes | CX39: Yes | CY39: Yes | CZ39: Yes | FL39: 729969371 | FM39: ecd30efa-2987-4bc9-8d4d-ee817a2ac131 | FN39: 46132.335 | FQ39: submitted_via_web | FS39: vjiNwcPYvtjoD8cL5yiJdz | FU39: uuid:ecd30efa-2987-4bc9-8d4d-ee817a2ac131 | FV39: 38
A40: HF core data | B40: 46128.574 | C40: 46132.544 | D40: Jhang0078 | E40: 46128 | F40: 14:02:00.000+05:00 | G40: 14:17:00.000+05:00 | H40: Tahir Mustafa | I40: Faisalabad Division | J40: Jhang | K40: Jhang | L40: 31.262425 72.335754 114.80000305175781 26.19300079345703 | M40: 31.262425 | N40: 72.335754 | O40: 114.8 | P40: 26.193001 | Q40: Urban | R40: Total parco petrol | S40: Retail outlet /Point of Sale (POS) | DC40: Fuel station | DE40: Total parco | DF40: Gojor rd | DG40: No | DH40: Not Applicable/ No Young buyers visited | DI40: No | DL40: No | DP40: No | DT40: No | DW40: No | DX40: No | EA40: No | EE40: No | EI40: No | EM40: No | EQ40: No | EU40: No | EY40: No | FC40: No | FG40: No | FH40: Yes | FL40: 729969508 | FM40: 4c5781f9-a5cd-4cd7-b9cb-af2162593ac5 | FN40: 46132.335 | FQ40: submitted_via_web | FS40: vjiNwcPYvtjoD8cL5yiJdz | FU40: uuid:4c5781f9-a5cd-4cd7-b9cb-af2162593ac5 | FV40: 39
A41: HF core data | B41: 46128.664 | C41: 46132.544 | D41: Jhang0080 | E41: 46128 | F41: 15:57:00.000+05:00 | G41: 16:11:00.000+05:00 | H41: Tahir Mustafa | I41: Faisalabad Division | J41: Jhang | K41: Jhang | L41: 31.271727 72.31831 117.4000015258789 52.400001525878906 | M41: 31.271727 | N41: 72.31831 | O41: 117.4 | P41: 52.400002 | Q41: Urban | R41: Jigar chines restaurant | S41: Public place | T41: Eatery ( Restaurant) | U41: Listed Venue | V41: 1 | W41: 0 | X41: Jigar chines restaurant | Y41: No | AC41: No | AE41: No | AG41: Yes | AH41: Yes | AI41: Yes | AJ41: Does not apply / no one using tobacco or nicotine products | AK41: 0 | AL41: 0 | AM41: 0 | AN41: 0 | AO41: 0 | AP41: 0 | AQ41: 1 | AR41: 0 | AT41: Does not apply / no one using tobacco or nicotine products | AU41: No | AX41: No | BA41: No | BD41: No | BT41: Yes | FL41: 729969880 | FM41: 63b40d96-94a1-4fee-befe-d0811b0b31e3 | FN41: 46132.336 | FQ41: submitted_via_web | FS41: vjiNwcPYvtjoD8cL5yiJdz | FU41: uuid:63b40d96-94a1-4fee-befe-d0811b0b31e3 | FV41: 40
A42: HF core data | B42: 46128.667 | C42: 46132.544 | D42: Jhang0081 | E42: 46128 | F42: 16:32:00.000+05:00 | G42: 16:48:00.000+05:00 | H42: Tahir Mustafa | I42: Faisalabad Division | J42: Jhang | K42: Jhang | L42: 31.262105 72.30971 114.69999694824219 27.173999786376953 | M42: 31.262105 | N42: 72.30971 | O42: 114.7 | P42: 27.174 | Q42: Urban | R42: Sabir restaurant | S42: Public place | T42: Eatery ( Restaurant) | U42: Listed Venue | V42: 1 | W42: 0 | X42: Sabir restaurant | Y42: No | AC42: No | AE42: No | AG42: No | AH42: No | AI42: No | AJ42: Does not apply / no one using tobacco or nicotine products | AK42: 0 | AL42: 0 | AM42: 0 | AN42: 0 | AO42: 0 | AP42: 0 | AQ42: 1 | AR42: 0 | AT42: No | AU42: No | AX42: No | BA42: No | BD42: No | BT42: Yes | FL42: 729970132 | FM42: 566ad239-7cd9-4f60-8edd-18e0f1446cca | FN42: 46132.336 | FQ42: submitted_via_web | FS42: vjiNwcPYvtjoD8cL5yiJdz | FU42: uuid:566ad239-7cd9-4f60-8edd-18e0f1446cca | FV42: 41
A43: HF core data | B43: 46128.69 | C43: 46132.544 | D43: Jhang0082 | E43: 46128 | F43: 16:54:00.000+05:00 | G43: 17:10:00.000+05:00 | H43: Tahir Mustafa | I43: Faisalabad Division | J43: Jhang | K43: Jhang | L43: 31.268031 72.320138 114.30000305175781 20 | M43: 31.268031 | N43: 72.320138 | O43: 114.3 | P43: 20 | Q43: Urban | R43: Hotway fast food and pizza | S43: Public place | T43: Eatery ( Restaurant) | U43: Listed Venue | V43: 1 | W43: 0 | X43: Hotway fast food and pizza 🍕 | Y43: No | AC43: No | AE43: No | AG43: No | AH43: No | AI43: No | AJ43: Does not apply / no one using tobacco or nicotine products | AK43: 0 | AL43: 0 | AM43: 0 | AN43: 0 | AO43: 0 | AP43: 0 | AQ43: 1 | AR43: 0 | AT43: Does not apply / no one using tobacco or nicotine products | AU43: Yes ( add photo Evidence) | AV43: 1000075237-16_56_4.jpg | AW43: https://kf.kobotoolbox.org/api/v2/assets/a7B4UGoSq7bg72YxNv837d/data/729970429/attachments/attyjGKU263JbeHjh8oVDgYE/ | AX43: No | BA43: No | BD43: No | BT43: Yes | FL43: 729970429 | FM43: 81d5e04c-f01d-4461-90ff-31618805a8ec | FN43: 46132.336 | FQ43: submitted_via_web | FS43: vjiNwcPYvtjoD8cL5yiJdz | FU43: uuid:81d5e04c-f01d-4461-90ff-31618805a8ec | FV43: 42
A44: HF core data | B44: 46128.716 | C44: 46132.544 | D44: Jhang0083 | E44: 46128 | F44: 17:15:00.000+05:00 | G44: 17:30:00.000+05:00 | H44: Tahir Mustafa | I44: Faisalabad Division | J44: Jhang | K44: Jhang | L44: 31.271165 72.320264 114.19999694824219 13.342000007629395 | M44: 31.271165 | N44: 72.320264 | O44: 114.2 | P44: 13.342 | Q44: Urban | R44: Rfc fast food and pizza | S44: Public place | T44: Eatery ( Restaurant) | U44: Listed Venue | V44: 1 | W44: 0 | X44: Rfc fast food and pizza | Y44: Yes( add photo evidence) | Z44: 1000075238-17_15_59.jpg | AA44: https://kf.kobotoolbox.org/api/v2/assets/a7B4UGoSq7bg72YxNv837d/data/729970631/attachments/attM8cgpkw9VyDLU2Mz88qUF/ | AB44: 1 | AC44: No | AE44: No | AG44: Yes | AH44: Yes | AI44: Yes | AJ44: Does not apply / no one using tobacco or nicotine products | AK44: 0 | AL44: 0 | AM44: 0 | AN44: 0 | AO44: 0 | AP44: 0 | AQ44: 1 | AR44: 0 | AT44: Does not apply / no one using tobacco or nicotine products | AU44: No | AX44: No | BA44: No | BD44: No | BT44: Yes | FL44: 729970631 | FM44: 1813d6b3-74af-4125-8e02-bbfce4e69dba | FN44: 46132.336 | FQ44: submitted_via_web | FS44: vjiNwcPYvtjoD8cL5yiJdz | FU44: uuid:1813d6b3-74af-4125-8e02-bbfce4e69dba | FV44: 43
A45: HF core data | B45: 46128.72 | C45: 46132.544 | D45: Jhang0084 | E45: 46128 | F45: 18:03:00.000+05:00 | G45: 18:25:00.000+05:00 | H45: Tahir Mustafa | I45: Faisalabad Division | J45: Jhang | K45: Jhang | L45: 31.273507 72.318891 114.0999984741211 19.797000885009766 | M45: 31.273507 | N45: 72.318891 | O45: 114.1 | P45: 19.797001 | Q45: Urban | R45: Elysian sweet by unze London | S45: Public place | T45: Eatery ( Restaurant) | U45: Listed Venue | V45: 1 | W45: 0 | X45: Elysian sweet by unze London | Y45: No | AC45: No | AE45: No | AG45: Yes | AH45: Yes | AI45: Yes | AJ45: Does not apply / no one using tobacco or nicotine products | AK45: 0 | AL45: 0 | AM45: 0 | AN45: 0 | AO45: 0 | AP45: 0 | AQ45: 1 | AR45: 0 | AT45: Does not apply / no one using tobacco or nicotine products | AU45: No | AX45: No | BA45: No | BD45: No | BT45: Yes | FL45: 729970802 | FM45: 55034dda-71d3-4070-ba8a-9293f5238ba7 | FN45: 46132.336 | FQ45: submitted_via_web | FS45: vjiNwcPYvtjoD8cL5yiJdz | FU45: uuid:55034dda-71d3-4070-ba8a-9293f5238ba7 | FV45: 44
A46: HF core data | B46: 46129.17 | C46: 46132.545 | D46: Jhang 0085 | E46: 46129 | F46: 06:24:00.000+05:00 | G46: 06:41:00.000+05:00 | H46: Tahir Mustafa | I46: Faisalabad Division | J46: Jhang | K46: Jhang | L46: 31.277882 72.321428 114.5 47.970001220703125 | M46: 31.277882 | N46: 72.321428 | O46: 114.5 | P46: 47.970001 | Q46: Urban | R46: Adrish general store | S46: Retail outlet /Point of Sale (POS) | DC46: Convenience / grocery store | DE46: Idrish general store | DF46: Ayub Chowk | DG46: No | DH46: Not Applicable/ No Young buyers visited | DI46: No | DL46: No | DP46: No | DT46: No | DW46: Yes | DX46: Yes ( add photo evidence) | DY46: 1000075370-6_28_7.jpg | DZ46: https://kf.kobotoolbox.org/api/v2/assets/a7B4UGoSq7bg72YxNv837d/data/729971031/attachments/att9GrMhyBzsSYEA3DYVLjSP/ | EA46: Yes | EB46: Capsten 'gold | EC46: 1000075370-6_28_42.jpg | ED46: https://kf.kobotoolbox.org/api/v2/assets/a7B4UGoSq7bg72YxNv837d/data/729971031/attachments/att8pBXb5PZJVorvUmGSr9Pz/ | EE46: No | EI46: No | EM46: No | EQ46: Yes | ER46: Zyx | ES46: 1000075370-8_31_7.jpg | ET46: https://kf.kobotoolbox.org/api/v2/assets/a7B4UGoSq7bg72YxNv837d/data/729971031/attachments/attURHzHQHy6eApKpvrGidpz/ | EU46: No | EY46: No | FC46: No | FG46: No | FH46: Yes | FL46: 729971031 | FM46: 54dc17b6-d906-4e5a-a2ce-1ebdc1240df1 | FN46: 46132.336 | FQ46: submitted_via_web | FS46: vjiNwcPYvtjoD8cL5yiJdz | FU46: uuid:54dc17b6-d906-4e5a-a2ce-1ebdc1240df1 | FV46: 45
A47: HF core data | B47: 46129.271 | C47: 46132.545 | D47: Jhang0086 | E47: 46129 | F47: 06:45:00.000+05:00 | G47: 07:00:00.000+05:00 | H47: Tahir Mustafa | I47: Faisalabad Division | J47: Jhang | K47: Jhang | L47: 31.278306 72.321115 114.30000305175781 38.15999984741211 | M47: 31.278306 | N47: 72.321115 | O47: 114.3 | P47: 38.16 | Q47: Urban | R47: Yusuf bhai pan shop | S47: Retail outlet /Point of Sale (POS) | DC47: Tobacco shop | DE47: Yusuf bhai paan shop | DF47: Ayub Chowk | DG47: No | DH47: Not Applicable/ No Young buyers visited | DI47: No | DL47: No | DP47: No | DT47: No | DW47: Yes | DX47: No | EA47: Yes | EB47: Capstan | EC47: 1000075375-6_49_20.jpg | ED47: https://kf.kobotoolbox.org/api/v2/assets/a7B4UGoSq7bg72YxNv837d/data/729971156/attachments/attLZzfiNJqQWfeFXHGx8G7G/ | EE47: Yes | EF47: Capstan | EG47: 1000075374-6_49_41.jpg | EH47: https://kf.kobotoolbox.org/api/v2/assets/a7B4UGoSq7bg72YxNv837d/data/729971156/attachments/atttJnM98or7fZYhN7c7NMrM/ | EI47: No | EM47: No | EQ47: No | EU47: No | EY47: Yes ( add photo evidence) | EZ47: 1000075376-6_50_6.jpg | FA47: https://kf.kobotoolbox.org/api/v2/assets/a7B4UGoSq7bg72YxNv837d/data/729971156/attachments/attQnP5NbUrftpB9SEw3WrvM/ | FB47: World no 1 | FC47: No | FG47: No | FH47: Yes | FL47: 729971156 | FM47: effa65d6-c222-4a99-ad81-3a76204db55a | FN47: 46132.336 | FQ47: submitted_via_web | FS47: vjiNwcPYvtjoD8cL5yiJdz | FU47: uuid:effa65d6-c222-4a99-ad81-3a76204db55a | FV47: 46
A48: HF core data | B48: 46129.285 | C48: 46132.545 | D48: Jhang0087 | E48: 46129 | F48: 07:11:00.000+05:00 | G48: 07:16:00.000+05:00 | H48: Tahir Mustafa | I48: Faisalabad Division | J48: Jhang | K48: Jhang | L48: 31.273247 72.318835 113.69999694824219 17.291000366210938 | M48: 31.273247 | N48: 72.318835 | O48: 113.7 | P48: 17.291 | Q48: Urban | R48: Bukhara road | S48: Public Service Vehicle (PSV) | BW48: Metro | BY48: Metro | BZ48: Bukhara road | CA48: No | CB48: No | CC48: No | CD48: No | CF48: Does not apply / no one using tobacco or nicotine products | CG48: 0 | CH48: 0 | CI48: 0 | CJ48: 0 | CK48: 0 | CL48: 0 | CM48: 1 | CN48: 0 | CP48: Does not apply / no one smoking | CQ48: No | CT48: No | CW48: Yes | CX48: Yes | CY48: Yes | CZ48: Yes | FL48: 729971330 | FM48: acae8373-c2e1-4692-8b22-03f37ea9e622 | FN48: 46132.336 | FQ48: submitted_via_web | FS48: vjiNwcPYvtjoD8cL5yiJdz | FU48: uuid:acae8373-c2e1-4692-8b22-03f37ea9e622 | FV48: 47
A49: HF core data | B49: 46129.304 | C49: 46132.545 | D49: Jhang0088 | E49: 46129 | F49: 07:19:00.000+05:00 | G49: 07:34:00.000+05:00 | H49: Tahir Mustafa | I49: Faisalabad Division | J49: Jhang | K49: Jhang | L49: 31.276708 72.320463 114.9000015258789 26.041000366210938 | M49: 31.276708 | N49: 72.320463 | O49: 114.9 | P49: 26.041 | Q49: Urban | R49: Subhan store shop | S49: Retail outlet /Point of Sale (POS) | DC49: Convenience / grocery store | DE49: Subhan store shop | DF49: Pso neighborhood | DG49: No | DH49: Not Applicable/ No Young buyers visited | DI49: No | DL49: Yes (add photo Evidence) | DM49: Nicotine | DN49: 1000075378-11_51_44.jpg | DO49: https://kf.kobotoolbox.org/api/v2/assets/a7B4UGoSq7bg72YxNv837d/data/729971735/attachments/attVhb4CNpWZpfjNywmZ4vko/ | DP49: Yes ( add photo evidence) | DQ49: Hamid | DR49: 1000075378-11_52_36.jpg | DS49: https://kf.kobotoolbox.org/api/v2/assets/a7B4UGoSq7bg72YxNv837d/data/729971735/attachments/att3HLTjGr9NfpesYhwAb5pf/ | DT49: No | DW49: Yes | DX49: Yes ( add photo evidence) | DY49: 1000075379-7_36_33.jpg | DZ49: https://kf.kobotoolbox.org/api/v2/assets/a7B4UGoSq7bg72YxNv837d/data/729971735/attachments/attNfxNZSYTnad7swzELrAec/ | EA49: Yes | EB49: Capstan Gold | EC49: 1000075377-7_36_54.jpg | ED49: https://kf.kobotoolbox.org/api/v2/assets/a7B4UGoSq7bg72YxNv837d/data/729971735/attachments/attFRiZKghraMChqNkpo4hzG/ | EE49: No | EI49: No | EM49: Yes | EN49: Hamid | EO49: 1000075378-7_37_40.jpg | EP49: https://kf.kobotoolbox.org/api/v2/assets/a7B4UGoSq7bg72YxNv837d/data/729971735/attachments/attazJ9YBJSXLMPvCVMRQjx4/ | EQ49: No | EU49: No | EY49: No | FC49: No | FG49: No | FH49: Yes | FL49: 729971735 | FM49: 3550f11d-ee16-4556-a273-d316332352e8 | FN49: 46132.337 | FQ49: submitted_via_web | FS49: vjiNwcPYvtjoD8cL5yiJdz | FU49: uuid:3550f11d-ee16-4556-a273-d316332352e8 | FV49: 48
A50: HF core data | B50: 46129.319 | C50: 46132.545 | D50: Jhang0089 | E50: 46129 | F50: 07:40:00.000+05:00 | G50: 07:55:00.000+05:00 | H50: Tahir Mustafa | I50: Faisalabad Division | J50: Jhang | K50: Jhang | L50: 31.277165 72.321037 114.69999694824219 19.09000015258789 | M50: 31.277165 | N50: 72.321037 | O50: 114.7 | P50: 19.09 | Q50: Urban | R50: Imran pan shop | S50: Retail outlet /Point of Sale (POS) | DC50: Tobacco shop | DE50: Imran pan shop | DF50: Ayub chowk | DG50: No | DH50: Not Applicable/ No Young buyers visited | DI50: No | DL50: No | DP50: No | DT50: No | DW50: Yes | DX50: No | EA50: Yes | EB50: Capstan | EC50: 1000075381-7_42_9.jpg | ED50: https://kf.kobotoolbox.org/api/v2/assets/a7B4UGoSq7bg72YxNv837d/data/729971935/attachments/attX76zVUohqjevSX2ATBEd8/ | EE50: No | EI50: No | EM50: No | EQ50: Yes | ER50: Zyn | ES50: 1000075380-7_42_32.jpg | ET50: https://kf.kobotoolbox.org/api/v2/assets/a7B4UGoSq7bg72YxNv837d/data/729971935/attachments/attVozoPih7mMLXbgAJ5mnZ2/ | EU50: Yes | EV50: Zyn | EW50: 1000075380-7_43_4.jpg | EX50: https://kf.kobotoolbox.org/api/v2/assets/a7B4UGoSq7bg72YxNv837d/data/729971935/attachments/attaYfkLoenZszPLm83aqSeY/ | EY50: Yes ( add photo evidence) | EZ50: 1000075382-7_44_24.jpg | FA50: https://kf.kobotoolbox.org/api/v2/assets/a7B4UGoSq7bg72YxNv837d/data/729971935/attachments/attEVAibcJHPsrMctmJeLNQ5/ | FB50: World no1 | FC50: No | FG50: No | FH50: Yes | FL50: 729971935 | FM50: dba4b08a-c1e7-485f-8a1c-db8b61295840 | FN50: 46132.337 | FQ50: submitted_via_web | FS50: vjiNwcPYvtjoD8cL5yiJdz | FU50: uuid:dba4b08a-c1e7-485f-8a1c-db8b61295840 | FV50: 49
A51: HF core data | B51: 46129.343 | C51: 46132.546 | D51: Jhang 090 | E51: 46129 | F51: 08:00:00.000+05:00 | G51: 08:15:00.000+05:00 | H51: Tahir Mustafa | I51: Faisalabad Division | J51: Jhang | K51: Jhang | L51: 31.270716 72.329534 113.5 1.031999945640564 | M51: 31.270716 | N51: 72.329534 | O51: 113.5 | P51: 1.0319999 | Q51: Urban | R51: Ravian school system jhang | S51: Public place | T51: Educational institution - School (Private) | U51: Unlisted Venue | V51: 0 | W51: 1 | X51: Ravian school system jhang | Y51: No | AC51: No | AE51: No | AG51: Yes | AH51: No | AI51: No | AJ51: Does not apply / no one using tobacco or nicotine products | AK51: 0 | AL51: 0 | AM51: 0 | AN51: 0 | AO51: 0 | AP51: 0 | AQ51: 1 | AR51: 0 | AT51: Does not apply / no one using tobacco or nicotine products | AU51: No | AX51: No | BA51: No | BD51: No | BT51: Yes | FL51: 729972431 | FM51: 56918982-7c87-4313-88eb-e37efd7b3037 | FN51: 46132.337 | FQ51: submitted_via_web | FS51: vjiNwcPYvtjoD8cL5yiJdz | FU51: uuid:56918982-7c87-4313-88eb-e37efd7b3037 | FV51: 50
A52: HF core data | B52: 46129.344 | C52: 46132.546 | D52: Jhang091 | E52: 46129 | F52: 08:16:00.000+05:00 | G52: 08:31:00.000+05:00 | H52: Tahir Mustafa | I52: Faisalabad Division | J52: Jhang | K52: Jhang | L52: 31.270707 72.329534 113.80000305175781 3.0920000076293945 | M52: 31.270707 | N52: 72.329534 | O52: 113.8 | P52: 3.092 | Q52: Urban | R52: Haq Farid store | S52: Retail outlet /Point of Sale (POS) | DC52: Convenience / grocery store | DE52: Haq Farid store | DF52: Mubashir general store | DG52: Yes | DH52: Never | DI52: No | DL52: No | DP52: No | DT52: No | DW52: Yes | DX52: No | EA52: Yes | EB52: Pall mall | EC52: 1000075383-8_21_2.jpg | ED52: https://kf.kobotoolbox.org/api/v2/assets/a7B4UGoSq7bg72YxNv837d/data/729972571/attachments/attwLfYWUiDehuff3izca2bz/ | EE52: No | EI52: No | EM52: No | EQ52: No | EU52: No | EY52: No | FC52: No | FG52: Yes | FH52: Yes | FL52: 729972571 | FM52: 66c93173-de58-44c3-850a-dcca17918edc | FN52: 46132.337 | FQ52: submitted_via_web | FS52: vjiNwcPYvtjoD8cL5yiJdz | FU52: uuid:66c93173-de58-44c3-850a-dcca17918edc | FV52: 51
A53: HF core data | B53: 46129.349 | C53: 46132.546 | D53: Jhang 0092 | E53: 46129 | F53: 08:32:00.000+05:00 | G53: 08:40:00.000+05:00 | H53: Tahir Mustafa | I53: Faisalabad Division | J53: Jhang | K53: Jhang | L53: 31.270033 72.327923 114.19999694824219 29.10700035095215 | M53: 31.270033 | N53: 72.327923 | O53: 114.2 | P53: 29.107 | Q53: Urban | R53: Dar sakina road | S53: Public Service Vehicle (PSV) | BW53: other | BX53: Raksha | BY53: Raksha | BZ53: Dar sakina road | CA53: No | CB53: No | CC53: No | CD53: No | CF53: Does not apply / no one using tobacco or nicotine products | CG53: 0 | CH53: 0 | CI53: 0 | CJ53: 0 | CK53: 0 | CL53: 0 | CM53: 1 | CN53: 0 | CP53: Does not apply / no one smoking | CQ53: No | CT53: No | CW53: No | CX53: No | CY53: No | CZ53: Yes | FL53: 729972857 | FM53: dbf1452e-c069-4953-abfd-074450e95b6a | FN53: 46132.337 | FQ53: submitted_via_web | FS53: vjiNwcPYvtjoD8cL5yiJdz | FU53: uuid:dbf1452e-c069-4953-abfd-074450e95b6a | FV53: 52
A54: HF core data | B54: 46129.354 | C54: 46132.546 | D54: Jhang 093 | E54: 46129 | F54: 08:37:00.000+05:00 | G54: 08:53:00.000+05:00 | H54: Tahir Mustafa | I54: Faisalabad Division | J54: Jhang | K54: Jhang | L54: 31.277982 72.321496 114.30000305175781 11.9399995803833 | M54: 31.277982 | N54: 72.321496 | O54: 114.3 | P54: 11.94 | Q54: Urban | R54: Karim bahaduri store | S54: Retail outlet /Point of Sale (POS) | DC54: Convenience / grocery store | DE54: Karim bahaduri store | DF54: Ayub Chowk | DG54: No | DH54: Not Applicable/ No Young buyers visited | DI54: No | DL54: No | DP54: No | DT54: No | DW54: Yes | DX54: Yes ( add photo evidence) | DY54: 1000075385-8_41_24.jpg | DZ54: https://kf.kobotoolbox.org/api/v2/assets/a7B4UGoSq7bg72YxNv837d/data/729973069/attachments/attW67iCuRCRt6H9ZHtKjYtJ/ | EA54: Yes | EB54: Pall mall | EC54: 1000075385-8_41_35.jpg | ED54: https://kf.kobotoolbox.org/api/v2/assets/a7B4UGoSq7bg72YxNv837d/data/729973069/attachments/attfKABhRzh22EF2hRYBxXb7/ | EE54: Yes | EF54: Pall mall | EG54: 1000075385-8_41_45.jpg | EH54: https://kf.kobotoolbox.org/api/v2/assets/a7B4UGoSq7bg72YxNv837d/data/729973069/attachments/attxcttx6BYirwMueiLqsuTX/ | EI54: No | EM54: No | EQ54: No | EU54: No | EY54: No | FC54: No | FG54: Yes | FH54: Yes | FL54: 729973069 | FM54: 6f0ab759-5242-496e-8414-5e3c68cd4ea4 | FN54: 46132.338 | FQ54: submitted_via_web | FS54: vjiNwcPYvtjoD8cL5yiJdz | FU54: uuid:6f0ab759-5242-496e-8414-5e3c68cd4ea4 | FV54: 53
A55: HF core data | B55: 46129.393 | C55: 46132.546 | D55: Jhang0094 | E55: 46129 | F55: 09:30:00.000+05:00 | G55: 09:45:00.000+05:00 | H55: Tahir Mustafa | I55: Faisalabad Division | J55: Jhang | K55: Jhang | L55: 31.277274 72.320896 114.5999984741211 26.43600082397461 | M55: 31.277274 | N55: 72.320896 | O55: 114.6 | P55: 26.436001 | Q55: Urban | R55: Aziz Banu Kala niswar | S55: Retail outlet /Point of Sale (POS) | DC55: Tobacco shop | DE55: Aziz Banu Kala niswar | DF55: Gilani restaurant | DG55: No | DH55: Not Applicable/ No Young buyers visited | DI55: No | DL55: Yes (add photo Evidence) | DM55: Aziz niswal | DN55: 1000075427-12_21_50.jpg | DO55: https://kf.kobotoolbox.org/api/v2/assets/a7B4UGoSq7bg72YxNv837d/data/729973276/attachments/attagHpMdEEYPdLZ5XMhdq7N/ | DP55: Yes ( add photo evidence) | DQ55: Aziz niswal WW2 | DR55: 1000075427-12_22_36.jpg | DS55: https://kf.kobotoolbox.org/api/v2/assets/a7B4UGoSq7bg72YxNv837d/data/729973276/attachments/atthUYpxarhg5Cy4cfiVS6Nr/ | DT55: No | DW55: Yes | DX55: No | EA55: No | EE55: No | EI55: Yes | EJ55: Aziz niswal | EK55: 1000075427-9_44_53.jpg | EL55: https://kf.kobotoolbox.org/api/v2/assets/a7B4UGoSq7bg72YxNv837d/data/729973276/attachments/attrXWCcWkBoZyURyv8DRymV/ | EM55: No | EQ55: No | EU55: No | EY55: No | FC55: No | FG55: No | FH55: Yes | FL55: 729973276 | FM55: 52ede1e5-b5e2-480d-9492-8dfc8eec1cda | FN55: 46132.338 | FQ55: submitted_via_web | FS55: vjiNwcPYvtjoD8cL5yiJdz | FU55: uuid:52ede1e5-b5e2-480d-9492-8dfc8eec1cda | FV55: 54
A56: HF core data | B56: 46129.407 | C56: 46132.546 | D56: Jhang0095 | E56: 46129 | F56: 09:46:00.000+05:00 | G56: 10:01:00.000+05:00 | H56: Tahir Mustafa | I56: Faisalabad Division | J56: Jhang | K56: Jhang | L56: 31.276355 72.320207 114.9000015258789 39.53900146484375 | M56: 31.276355 | N56: 72.320207 | O56: 114.9 | P56: 39.539001 | Q56: Urban | R56: Shani drink corner | S56: Retail outlet /Point of Sale (POS) | DC56: Convenience / grocery store | DE56: Shani drink karnat | DF56: Pso jhang near | DG56: No | DH56: Not Applicable/ No Young buyers visited | DI56: No | DL56: No | DP56: No | DT56: No | DW56: Yes | DX56: No | EA56: Yes | EB56: Capstan | EC56: 1000075428-9_50_43.jpg | ED56: https://kf.kobotoolbox.org/api/v2/assets/a7B4UGoSq7bg72YxNv837d/data/729973508/attachments/attvqctjob3tPSu8HELZApwu/ | EE56: Yes | EF56: Capstan | EG56: 1000075428-9_51_2.jpg | EH56: https://kf.kobotoolbox.org/api/v2/assets/a7B4UGoSq7bg72YxNv837d/data/729973508/attachments/attE5x887fPGRVwZxAUMy2tX/ | EI56: No | EM56: No | EQ56: Yes | ER56: Velo | ES56: 1000075428-9_51_32.jpg | ET56: https://kf.kobotoolbox.org/api/v2/assets/a7B4UGoSq7bg72YxNv837d/data/729973508/attachments/attpAtXtGDg3QjNtCwHK7Brw/ | EU56: Yes | EV56: Velo | EW56: 1000075428-9_52_0.jpg | EX56: https://kf.kobotoolbox.org/api/v2/assets/a7B4UGoSq7bg72YxNv837d/data/729973508/attachments/attL7aV68URWnnU3x73XSaQh/ | EY56: Yes ( add photo evidence) | EZ56: 1000075430-9_52_5.jpg | FA56: https://kf.kobotoolbox.org/api/v2/assets/a7B4UGoSq7bg72YxNv837d/data/729973508/attachments/attMk7AAbxi8DUxvdX5fq2Bm/ | FB56: Sale | FC56: Yes ( add photo evidence) | FD56: 1000075430-9_52_20.jpg | FE56: https://kf.kobotoolbox.org/api/v2/assets/a7B4UGoSq7bg72YxNv837d/data/729973508/attachments/attxMkL8QoaQQhFf2nMvJ9zz/ | FF56: Sale | FG56: No | FH56: Yes | FL56: 729973508 | FM56: f52ac9b1-dbf9-4a66-bfc3-a00ef0e19e0e | FN56: 46132.338 | FQ56: submitted_via_web | FS56: vjiNwcPYvtjoD8cL5yiJdz | FU56: uuid:f52ac9b1-dbf9-4a66-bfc3-a00ef0e19e0e | FV56: 55
A57: HF core data | B57: 46129.417 | C57: 46132.546 | D57: Jhang0096 | E57: 46129 | F57: 10:05:00.000+05:00 | G57: 10:20:00.000+05:00 | H57: Tahir Mustafa | I57: Faisalabad Division | J57: Jhang | K57: Jhang | L57: 31.274001 72.319217 115.69999694824219 19.39299964904785 | M57: 31.274001 | N57: 72.319217 | O57: 115.7 | P57: 19.393 | Q57: Urban | R57: Raheem pan shop | S57: Retail outlet /Point of Sale (POS) | DC57: Convenience / grocery store | DE57: Reheem pan shop | DF57: Shell v power pso | DG57: No | DH57: Not Applicable/ No Young buyers visited | DI57: No | DL57: No | DP57: No | DT57: No | DW57: Yes | DX57: Yes ( add photo evidence) | DY57: 1000075432-10_8_15.jpg | DZ57: https://kf.kobotoolbox.org/api/v2/assets/a7B4UGoSq7bg72YxNv837d/data/729973841/attachments/att3f7NXTSaEsJ3mLP3WHYZp/ | EA57: Yes | EB57: Capstan morven | EC57: 1000075431-10_8_42.jpg | ED57: https://kf.kobotoolbox.org/api/v2/assets/a7B4UGoSq7bg72YxNv837d/data/729973841/attachments/att4JdqaiodMMFSP6qqZtsTj/ | EE57: Yes | EF57: Capstan | EG57: 1000075432-10_9_23.jpg | EH57: https://kf.kobotoolbox.org/api/v2/assets/a7B4UGoSq7bg72YxNv837d/data/729973841/attachments/attgzS9qEFf82GNfZLG73aEj/ | EI57: No | EM57: No | EQ57: Yes | ER57: Velo | ES57: 1000075432-10_9_46.jpg | ET57: https://kf.kobotoolbox.org/api/v2/assets/a7B4UGoSq7bg72YxNv837d/data/729973841/attachments/atth6EAJV3itsCWSTUBZsyDh/ | EU57: Yes | EV57: Velo | EW57: 1000075432-10_9_57.jpg | EX57: https://kf.kobotoolbox.org/api/v2/assets/a7B4UGoSq7bg72YxNv837d/data/729973841/attachments/attmkxkjUvYBcq6GyFEuP3Yf/ | EY57: Yes ( add photo evidence) | EZ57: 1000075433-10_10_4.jpg | FA57: https://kf.kobotoolbox.org/api/v2/assets/a7B4UGoSq7bg72YxNv837d/data/729973841/attachments/attdRLoJmH4owENbaemBHe2E/ | FB57: Promotion | FC57: No | FG57: No | FH57: Yes | FL57: 729973841 | FM57: a3f1c47e-04c2-41a7-b394-e1c132831926 | FN57: 46132.338 | FQ57: submitted_via_web | FS57: vjiNwcPYvtjoD8cL5yiJdz | FU57: uuid:a3f1c47e-04c2-41a7-b394-e1c132831926 | FV57: 56
A58: HF core data | B58: 46129.433 | C58: 46132.546 | D58: Jhang0097 | E58: 46129 | F58: 10:25:00.000+05:00 | G58: 10:40:00.000+05:00 | H58: Tahir Mustafa | I58: Faisalabad Division | J58: Jhang | K58: Jhang | L58: 31.266919 72.3141 115.19999694824219 17.347999572753906 | M58: 31.266919 | N58: 72.3141 | O58: 115.2 | P58: 17.348 | Q58: Urban | R58: Usman kariyana store | S58: Retail outlet /Point of Sale (POS) | DC58: Convenience / grocery store | DE58: Usman kariyana store | DF58: Near go petal | DG58: No | DH58: Not Applicable/ No Young buyers visited | DI58: No | DL58: No | DP58: No | DT58: No | DW58: Yes | DX58: Yes ( add photo evidence) | DY58: 1000075442-10_26_52.jpg | DZ58: https://kf.kobotoolbox.org/api/v2/assets/a7B4UGoSq7bg72YxNv837d/data/729974093/attachments/attQBnNLiYPgFJ4LwB3eAErH/ | EA58: Yes | EB58: Capstan | EC58: 1000075442-10_27_13.jpg | ED58: https://kf.kobotoolbox.org/api/v2/assets/a7B4UGoSq7bg72YxNv837d/data/729974093/attachments/attekBnS4FBiLdZxZgbkxJpZ/ | EE58: No | EI58: No | EM58: No | EQ58: No | EU58: No | EY58: Yes ( add photo evidence) | EZ58: 1000075440-10_27_31.jpg | FA58: https://kf.kobotoolbox.org/api/v2/assets/a7B4UGoSq7bg72YxNv837d/data/729974093/attachments/attCuHP9jKJVnnaoZkTmiRtq/ | FB58: One ka sath second free | FC58: Yes ( add photo evidence) | FD58: 1000075441-10_28_10.jpg | FE58: https://kf.kobotoolbox.org/api/v2/assets/a7B4UGoSq7bg72YxNv837d/data/729974093/attachments/attYZwtjavKbW5xzeVCxhN49/ | FF58: Sale | FG58: Yes | FH58: Yes | FL58: 729974093 | FM58: 3bd270cf-47c3-46a4-9ad7-60823e24962f | FN58: 46132.338 | FQ58: submitted_via_web | FS58: vjiNwcPYvtjoD8cL5yiJdz | FU58: uuid:3bd270cf-47c3-46a4-9ad7-60823e24962f | FV58: 57
A59: HF core data | B59: 46129.442 | C59: 46132.547 | D59: Jhang0098 | E59: 46129 | F59: 10:45:00.000+05:00 | G59: 11:00:00.000+05:00 | H59: Tahir Mustafa | I59: Faisalabad Division | J59: Jhang | K59: Jhang | L59: 31.2692 72.315891 115.30000305175781 26.923999786376953 | M59: 31.2692 | N59: 72.315891 | O59: 115.3 | P59: 26.924 | Q59: Urban | R59: Ali karyana store | S59: Retail outlet /Point of Sale (POS) | DC59: Convenience / grocery store | DE59: Ali Karyana store | DF59: Khat Maine buata chauk | DG59: No | DH59: Not Applicable/ No Young buyers visited | DI59: No | DL59: No | DP59: No | DT59: No | DW59: Yes | DX59: No | EA59: Yes | EB59: Red white | EC59: 1000075449-10_53_31.jpg | ED59: https://kf.kobotoolbox.org/api/v2/assets/a7B4UGoSq7bg72YxNv837d/data/729974295/attachments/atteAvwXn6BWGYAuLSDyzWQz/ | EE59: No | EI59: No | EM59: No | EQ59: No | EU59: No | EY59: Yes ( add photo evidence) | EZ59: 1000075447-10_54_8.jpg | FA59: https://kf.kobotoolbox.org/api/v2/assets/a7B4UGoSq7bg72YxNv837d/data/729974295/attachments/atti2ihuRisNUVGPXMB64Bai/ | FB59: Promotion | FC59: No | FG59: No | FH59: Yes | FL59: 729974295 | FM59: b71bc39b-45ff-401d-834c-9b78b6e36f2a | FN59: 46132.338 | FQ59: submitted_via_web | FS59: vjiNwcPYvtjoD8cL5yiJdz | FU59: uuid:b71bc39b-45ff-401d-834c-9b78b6e36f2a | FV59: 58
A60: HF core data | B60: 46129.455 | C60: 46132.547 | D60: Jhang099 | E60: 46129 | F60: 11:05:00.000+05:00 | G60: 11:20:00.000+05:00 | H60: Tahir Mustafa | I60: Faisalabad Division | J60: Jhang | K60: Jhang | L60: 31.271534 72.317267 113.5999984741211 16.270999908447266 | M60: 31.271534 | N60: 72.317267 | O60: 113.6 | P60: 16.271 | Q60: Urban | R60: Riyaz karyanian store | S60: Retail outlet /Point of Sale (POS) | DC60: Convenience / grocery store | DE60: Riyaz kariyana store | DF60: Bakkar road near | DG60: No | DH60: Not Applicable/ No Young buyers visited | DI60: No | DL60: No | DP60: No | DT60: No | DW60: Yes | DX60: No | EA60: Yes | EB60: Liston | EC60: 1000075451-11_8_45.jpg | ED60: https://kf.kobotoolbox.org/api/v2/assets/a7B4UGoSq7bg72YxNv837d/data/729974747/attachments/attyqDXLpQZfd5spRgjYh9MW/ | EE60: No | EI60: No | EM60: No | EQ60: No | EU60: No | EY60: No | FC60: Yes ( add photo evidence) | FD60: 1000075450-11_9_17.jpg | FE60: https://kf.kobotoolbox.org/api/v2/assets/a7B4UGoSq7bg72YxNv837d/data/729974747/attachments/attESnw2mMtZNH8ZDYAn6aHs/ | FF60: Sale | FG60: No | FH60: Yes | FL60: 729974747 | FM60: 379f64bf-25ff-44e5-bdd9-416fcfae7b46 | FN60: 46132.338 | FQ60: submitted_via_web | FS60: vjiNwcPYvtjoD8cL5yiJdz | FU60: uuid:379f64bf-25ff-44e5-bdd9-416fcfae7b46 | FV60: 59
A61: HF core data | B61: 46129.545 | C61: 46132.547 | D61: Jhang 100 | E61: 46129 | F61: 13:05:00.000+05:00 | G61: 13:20:00.000+05:00 | H61: Tahir Mustafa | I61: Faisalabad Division | J61: Jhang | K61: Jhang | L61: 31.27724 72.321068 114.80000305175781 20.547000885009766 | M61: 31.27724 | N61: 72.321068 | O61: 114.8 | P61: 20.547001 | Q61: Urban | R61: Allah ho ho restaurant | S61: Public place | T61: Eatery ( Restaurant) | U61: Unlisted Venue | V61: 0 | W61: 1 | X61: Allah ho ho restaurant | Y61: No | AC61: No | AE61: No | AG61: Yes | AH61: No | AI61: No | AJ61: Does not apply / no one using tobacco or nicotine products | AK61: 0 | AL61: 0 | AM61: 0 | AN61: 0 | AO61: 0 | AP61: 0 | AQ61: 1 | AR61: 0 | AT61: Does not apply / no one using tobacco or nicotine products | AU61: No | AX61: No | BA61: No | BD61: No | BT61: Yes | BV61: Fri Chicks Jhang Jhang Gojra Rd Station Chowk two time this listed but off so unlisted file | FL61: 729974937 | FM61: e5b4f9e4-48a0-4f9b-bce7-ba2c8c16f7d5 | FN61: 46132.338 | FQ61: submitted_via_web | FS61: vjiNwcPYvtjoD8cL5yiJdz | FU61: uuid:e5b4f9e4-48a0-4f9b-bce7-ba2c8c16f7d5 | FV61: 60
A62: HF core data | B62: 46131.905 | C62: 46132.55 | D62: Sahiwal 11 | E62: 46132 | F62: 13:07:00.000+05:00 | G62: 13:17:00.000+05:00 | H62: Ashfaq Ahmed Rao | I62: Sahiwal Division | J62: Sahiwal | K62: Sahiwal | L62: 30.665363 73.095463 130.20001220703125 29.118999481201172 | M62: 30.665363 | N62: 73.095463 | O62: 130.20001 | P62: 29.118999 | Q62: Urban | R62: DC Office | S62: Public place | T62: Government Offices - District Authorities Offices e.g. (Health, Education, DC Office, C & W Office, Social Welfare etc.) | U62: Listed Venue | V62: 1 | W62: 0 | X62: DC Office sahiwal | Y62: No | AC62: Yes | AD62: 1 | AE62: No | AG62: Yes | AH62: Yes | AI62: Yes | AJ62: Cigarette | AK62: 1 | AL62: 0 | AM62: 0 | AN62: 0 | AO62: 0 | AP62: 0 | AQ62: 0 | AR62: 0 | AT62: No | AU62: No | AX62: No | BA62: No | BD62: No | BT62: Yes | BV62: Construction is going on in the office, moreover there are jamers inside completed survey after coming out of the office | FL62: 729979813 | FM62: 7d0580af-ce67-4f19-bbe5-a9b039d952a9 | FN62: 46132.341 | FQ62: submitted_via_web | FS62: vjiNwcPYvtjoD8cL5yiJdz | FU62: uuid:7d0580af-ce67-4f19-bbe5-a9b039d952a9 | FV62: 61
A63: HF core data | B63: 46127.462 | C63: 46132.699 | D63: 001 | E63: 46127 | F63: 10:06:00.000+05:00 | G63: 10:21:00.000+05:00 | H63: Syed Nadeem Abbas | I63: Faisalabad Division | J63: Jhang | K63: Jhang | L63: 31.270697 72.325037 113.4000015258789 7.821000099182129 | M63: 31.270697 | N63: 72.325037 | O63: 113.4 | P63: 7.8210001 | Q63: Urban | R63: Excise and taxation office | S63: Public place | T63: Government Offices - District Authorities Offices e.g. (Health, Education, DC Office, C & W Office, Social Welfare etc.) | U63: Listed Venue | V63: 1 | W63: 0 | X63: Excise and taxation office | Y63: Yes( add photo evidence) | Z63: IMG_20260415_111201_825-11_15_22.jpg | AA63: https://kf.kobotoolbox.org/api/v2/assets/a7B4UGoSq7bg72YxNv837d/data/730193339/attachments/attwsB3QAKV9dgHaUnE6Rb83/ | AB63: 1 | AC63: No | AE63: Yes | AF63: 1 | AG63: Yes | AH63: Yes | AI63: Yes | AJ63: Does not apply / no one using tobacco or nicotine products | AK63: 0 | AL63: 0 | AM63: 0 | AN63: 0 | AO63: 0 | AP63: 0 | AQ63: 1 | AR63: 0 | AT63: Does not apply / no one using tobacco or nicotine products | AU63: Yes ( add photo Evidence) | AV63: IMG_20260415_111324_658-11_16_18.jpg | AW63: https://kf.kobotoolbox.org/api/v2/assets/a7B4UGoSq7bg72YxNv837d/data/730193339/attachments/att8EezzcV2sNvZghueJXiyS/ | AX63: No | BA63: No | BD63: No | BT63: Yes | BV63: Cigarettes buds are visible but not found separate place for smoking. | FL63: 730193339 | FM63: 74b4b3bf-22e8-48e8-bc70-797d56905d15 | FN63: 46132.491 | FQ63: submitted_via_web | FS63: vjiNwcPYvtjoD8cL5yiJdz | FU63: uuid:74b4b3bf-22e8-48e8-bc70-797d56905d15 | FV63: 62
A64: HF core data | B64: 46127.47 | C64: 46132.699 | D64: 002 | E64: 46127 | F64: 10:29:00.000+05:00 | G64: 22:44:00.000+05:00 | H64: Syed Nadeem Abbas | I64: Faisalabad Division | J64: Jhang | K64: Jhang | L64: 31.272653 72.323764 112.5999984741211 8 | M64: 31.272653 | N64: 72.323764 | O64: 112.6 | P64: 8 | Q64: Urban | R64: AC office | S64: Public place | T64: Government Offices - District Authorities Offices e.g. (Health, Education, DC Office, C & W Office, Social Welfare etc.) | U64: Listed Venue | V64: 1 | W64: 0 | X64: AC office | Y64: No | AC64: Yes | AD64: 3 | AE64: No | AG64: Yes | AH64: Yes | AI64: Yes | AJ64: Cigarette | AK64: 1 | AL64: 0 | AM64: 0 | AN64: 0 | AO64: 0 | AP64: 0 | AQ64: 0 | AR64: 0 | AT64: No | AU64: Yes ( add photo Evidence) | AV64: IMG_20260415_112915_372-11_34_22.jpg | AW64: https://kf.kobotoolbox.org/api/v2/assets/a7B4UGoSq7bg72YxNv837d/data/730193917/attachments/attGbQAaXsTVxRH2qxPuHuk4/ | AX64: No | BA64: No | BD64: No | BT64: Yes | FL64: 730193917 | FM64: 4c752913-31de-47df-9e90-a83758a4ee88 | FN64: 46132.491 | FQ64: submitted_via_web | FS64: vjiNwcPYvtjoD8cL5yiJdz | FU64: uuid:4c752913-31de-47df-9e90-a83758a4ee88 | FV64: 63
A65: HF core data | B65: 46127.483 | C65: 46132.7 | D65: 003 | E65: 46127 | F65: 10:51:00.000+05:00 | G65: 11:05:00.000+05:00 | H65: Syed Nadeem Abbas | I65: Faisalabad Division | J65: Jhang | K65: Jhang | L65: 31.271269 72.324113 113.9000015258789 18.48900032043457 | M65: 31.271269 | N65: 72.324113 | O65: 113.9 | P65: 18.489 | Q65: Urban | R65: DC office | S65: Public place | T65: Government Offices - District Authorities Offices e.g. (Health, Education, DC Office, C & W Office, Social Welfare etc.) | U65: Listed Venue | V65: 1 | W65: 0 | X65: DC office | Y65: No | AC65: No | AE65: No | AG65: Yes | AH65: Yes | AI65: Yes | AJ65: Does not apply / no one using tobacco or nicotine products | AK65: 0 | AL65: 0 | AM65: 0 | AN65: 0 | AO65: 0 | AP65: 0 | AQ65: 1 | AR65: 0 | AT65: Does not apply / no one using tobacco or nicotine products | AU65: Yes ( add photo Evidence) | AV65: IMG_20260415_115836_392-23_17_50.jpg | AW65: https://kf.kobotoolbox.org/api/v2/assets/a7B4UGoSq7bg72YxNv837d/data/730194745/attachments/attoYhkKgjRh5yZd2CGZtMGs/ | AX65: No | BA65: No | BD65: No | BT65: Yes | FL65: 730194745 | FM65: 5e04c82d-abb5-4cad-9442-bf4d06195f8a | FN65: 46132.492 | FQ65: submitted_via_web | FS65: vjiNwcPYvtjoD8cL5yiJdz | FU65: uuid:5e04c82d-abb5-4cad-9442-bf4d06195f8a | FV65: 64
A66: HF core data | B66: 46127.504 | C66: 46132.7 | D66: Jhang004 | E66: 46127 | F66: 11:20:00.000+05:00 | G66: 11:35:00.000+05:00 | H66: Syed Nadeem Abbas | I66: Faisalabad Division | J66: Jhang | K66: Jhang | L66: 31.271592 72.324903 113.9000015258789 14.300000190734863 | M66: 31.271592 | N66: 72.324903 | O66: 113.9 | P66: 14.3 | Q66: Urban | R66: DPO office | S66: Public place | T66: Government Offices - District Authorities Offices e.g. (Health, Education, DC Office, C & W Office, Social Welfare etc.) | U66: Listed Venue | V66: 1 | W66: 0 | X66: DPO office | Y66: No | AC66: No | AE66: No | AG66: Yes | AH66: Yes | AI66: Yes | AJ66: Does not apply / no one using tobacco or nicotine products | AK66: 0 | AL66: 0 | AM66: 0 | AN66: 0 | AO66: 0 | AP66: 0 | AQ66: 1 | AR66: 0 | AT66: Does not apply / no one using tobacco or nicotine products | AU66: No | AX66: No | BA66: No | BD66: No | BT66: Yes | BV66: I take permission from DPO PA and complete my observation all over , PA not allow for DPO because he was busy thats why I take permission and done it. | FL66: 730195235 | FM66: a66261bb-732b-478d-9c49-52b90517ca8b | FN66: 46132.492 | FQ66: submitted_via_web | FS66: vjiNwcPYvtjoD8cL5yiJdz | FU66: uuid:a66261bb-732b-478d-9c49-52b90517ca8b | FV66: 65
A67: HF core data | B67: 46127.505 | C67: 46132.701 | D67: Jhang005 | E67: 46127 | F67: 11:45:00.000+05:00 | G67: 00:00:00.000+05:00 | H67: Syed Nadeem Abbas | I67: Faisalabad Division | J67: Jhang | K67: Jhang | L67: 31.270997 72.321408 113.80000305175781 10.699999809265137 | M67: 31.270997 | N67: 72.321408 | O67: 113.8 | P67: 10.7 | Q67: Urban | R67: Yousuf shah road jhang | S67: Public Service Vehicle (PSV) | BW67: Van | BY67: Toyota | BZ67: Yousuf shah road | CA67: No | CB67: No | CC67: No | CD67: No | CF67: Does not apply / no one using tobacco or nicotine products | CG67: 0 | CH67: 0 | CI67: 0 | CJ67: 0 | CK67: 0 | CL67: 0 | CM67: 1 | CN67: 0 | CP67: Does not apply / no one smoking | CQ67: No | CT67: No | CW67: Yes | CX67: Yes | CY67: Yes | CZ67: Yes | FL67: 730195621 | FM67: f66c3950-ab5f-4458-b0a1-346e52b493a5 | FN67: 46132.492 | FQ67: submitted_via_web | FS67: vjiNwcPYvtjoD8cL5yiJdz | FU67: uuid:f66c3950-ab5f-4458-b0a1-346e52b493a5 | FV67: 66
A68: HF core data | B68: 46132.55 | C68: 46132.701 | D68: Sahiwal 12 | E68: 46132 | F68: 16:42:00.000+05:00 | G68: 16:55:00.000+05:00 | H68: Ashfaq Ahmed Rao | I68: Sahiwal Division | J68: Sahiwal | K68: Sahiwal | L68: 30.663739 73.097206 129 34.400001525878906 | M68: 30.663739 | N68: 73.097206 | O68: 129 | P68: 34.400002 | Q68: Urban | R68: DPO Office | S68: Public place | T68: Government Offices - District Authorities Offices e.g. (Health, Education, DC Office, C & W Office, Social Welfare etc.) | U68: Listed Venue | V68: 1 | W68: 0 | X68: DPO Office | Y68: No | AC68: Yes | AD68: 3,4 | AE68: No | AG68: Yes | AH68: Yes | AI68: Yes | AJ68: Cigarette | AK68: 1 | AL68: 0 | AM68: 0 | AN68: 0 | AO68: 0 | AP68: 0 | AQ68: 0 | AR68: 0 | AT68: No | AU68: Yes ( add photo Evidence) | AV68: 20260420_164729-16_47_44.jpg | AW68: https://kf.kobotoolbox.org/api/v2/assets/a7B4UGoSq7bg72YxNv837d/data/730196394/attachments/att9jfNPrqpb7L9CNiZp97br/ | AX68: No | BA68: No | BD68: No | BT68: Yes | BV68: Staff said people smoke in the lawn of DPO house nobody dare to stop them. As they come for their case and while waiting for the turn they smoke free handedly | FL68: 730196394 | FM68: b7547a93-f5fc-48c5-8c09-7d778c4a0488 | FN68: 46132.493 | FQ68: submitted_via_web | FS68: vjiNwcPYvtjoD8cL5yiJdz | FU68: uuid:b7547a93-f5fc-48c5-8c09-7d778c4a0488 | FV68: 67
A69: HF core data | B69: 46127.522 | C69: 46132.701 | D69: 006 | E69: 46127 | F69: 12:10:00.000+05:00 | G69: 12:25:00.000+05:00 | H69: Syed Nadeem Abbas | I69: Faisalabad Division | J69: Jhang | K69: Jhang | L69: 31.269872 72.319968 114.69999694824219 14.005999565124512 | M69: 31.269872 | N69: 72.319968 | O69: 114.7 | P69: 14.006 | Q69: Urban | R69: Doctors hospital | S69: Public place | T69: Health Facility - Hospital | U69: Listed Venue | V69: 1 | W69: 0 | X69: Doctors hospital | Y69: No | AC69: No | AE69: No | AG69: Yes | AH69: Yes | AI69: Yes | AJ69: Does not apply / no one using tobacco or nicotine products | AK69: 0 | AL69: 0 | AM69: 0 | AN69: 0 | AO69: 0 | AP69: 0 | AQ69: 1 | AR69: 0 | AT69: Does not apply / no one using tobacco or nicotine products | AU69: No | AX69: No | BA69: No | BD69: Yes (add photo Evidence) | BE69: IMG_20260415_130007_276-13_1_14.jpg | BF69: https://kf.kobotoolbox.org/api/v2/assets/a7B4UGoSq7bg72YxNv837d/data/730196460/attachments/attfdYpoi2cewb8ejgyWxWdi/ | BG69: Cigarette | BH69: 1 | BI69: 0 | BJ69: 0 | BK69: 0 | BL69: 0 | BM69: 0 | BN69: 0 | BO69: 0 | BQ69: No | BT69: Yes | FL69: 730196460 | FM69: 2e9116f4-413f-4206-b029-4b41ca2f401d | FN69: 46132.493 | FQ69: submitted_via_web | FS69: vjiNwcPYvtjoD8cL5yiJdz | FU69: uuid:2e9116f4-413f-4206-b029-4b41ca2f401d | FV69: 68
A70: HF core data | B70: 46127.543 | C70: 46132.701 | D70: 007 | E70: 46127 | F70: 12:29:00.000+05:00 | G70: 12:47:00.000+05:00 | H70: Syed Nadeem Abbas | I70: Faisalabad Division | J70: Jhang | K70: Jhang | L70: 31.269583 72.32078 115.19999694824219 30 | M70: 31.269583 | N70: 72.32078 | O70: 115.2 | P70: 30 | Q70: Urban | R70: National bank of Pakistan | S70: Public place | T70: Bank - goverment | U70: Listed Venue | V70: 1 | W70: 0 | X70: National Bank of Pakistan | Y70: No | AC70: No | AE70: No | AG70: Yes | AH70: Yes | AI70: Yes | AJ70: Does not apply / no one using tobacco or nicotine products | AK70: 0 | AL70: 0 | AM70: 0 | AN70: 0 | AO70: 0 | AP70: 0 | AQ70: 1 | AR70: 0 | AT70: Does not apply / no one using tobacco or nicotine products | AU70: No | AX70: No | BA70: No | BD70: No | BT70: Yes | FL70: 730196984 | FM70: 1dc775c4-e36d-40e7-bf6f-73e1e640bd6a | FN70: 46132.493 | FQ70: submitted_via_web | FS70: vjiNwcPYvtjoD8cL5yiJdz | FU70: uuid:1dc775c4-e36d-40e7-bf6f-73e1e640bd6a | FV70: 69
A71: HF core data | B71: 46127.551 | C71: 46132.702 | D71: 008 | E71: 46127 | F71: 13:02:00.000+05:00 | G71: 13:17:00.000+05:00 | H71: Syed Nadeem Abbas | I71: Faisalabad Division | J71: Jhang | K71: Jhnag | L71: 31.267091 72.319633 114.19999694824219 13.880000114440918 | M71: 31.267091 | N71: 72.319633 | O71: 114.2 | P71: 13.88 | Q71: Urban | R71: Yummy tummy restaurant | S71: Public place | T71: Eatery ( Restaurant) | U71: Listed Venue | V71: 1 | W71: 0 | X71: Yummy tummy | Y71: Yes( add photo evidence) | Z71: IMG_20260415_144845_807-18_33_54.jpg | AA71: https://kf.kobotoolbox.org/api/v2/assets/a7B4UGoSq7bg72YxNv837d/data/730197599/attachments/attWqkvont8oADLmMm9iS467/ | AB71: 2 | AC71: No | AE71: No | AG71: Yes | AH71: Yes | AI71: Yes | AJ71: Does not apply / no one using tobacco or nicotine products | AK71: 0 | AL71: 0 | AM71: 0 | AN71: 0 | AO71: 0 | AP71: 0 | AQ71: 1 | AR71: 0 | AT71: Does not apply / no one using tobacco or nicotine products | AU71: No | AX71: No | BA71: No | BD71: No | BT71: Yes | FL71: 730197599 | FM71: bd8d17d5-073e-4754-bc35-4ef811641dc2 | FN71: 46132.494 | FQ71: submitted_via_web | FS71: vjiNwcPYvtjoD8cL5yiJdz | FU71: uuid:bd8d17d5-073e-4754-bc35-4ef811641dc2 | FV71: 70
A72: HF core data | B72: 46127.561 | C72: 46132.702 | D72: Jhang009 | E72: 46127 | F72: 13:21:00.000+05:00 | G72: 13:33:00.000+05:00 | H72: Syed Nadeem Abbas | I72: Faisalabad Division | J72: Jhang | K72: Jhang | L72: 31.266461 72.324414 113.9000015258789 19.35099983215332 | M72: 31.266461 | N72: 72.324414 | O72: 113.9 | P72: 19.351 | Q72: Urban | R72: Gujra road jhang | S72: Public Service Vehicle (PSV) | BW72: Bus (Local) | BY72: Old model bus , not sure | BZ72: gojra road | CA72: No | CB72: No | CC72: No | CD72: No | CF72: Does not apply / no one using tobacco or nicotine products | CG72: 0 | CH72: 0 | CI72: 0 | CJ72: 0 | CK72: 0 | CL72: 0 | CM72: 1 | CN72: 0 | CP72: Does not apply / no one smoking | CQ72: No | CT72: No | CW72: Yes | CX72: Yes | CY72: No | CZ72: Yes | FL72: 730198198 | FM72: 227e9aca-5a10-4133-93d9-5729ad95881f | FN72: 46132.494 | FQ72: submitted_via_web | FS72: vjiNwcPYvtjoD8cL5yiJdz | FU72: uuid:227e9aca-5a10-4133-93d9-5729ad95881f | FV72: 71
A73: HF core data | B73: 46127.573 | C73: 46132.703 | D73: 010 | E73: 46127 | F73: 13:35:00.000+05:00 | G73: 13:51:00.000+05:00 | H73: Syed Nadeem Abbas | I73: Faisalabad Division | J73: Jhang | K73: Jhang | L73: 31.266349 72.324852 113.4000015258789 16.452999114990234 | M73: 31.266349 | N73: 72.324852 | O73: 113.4 | P73: 16.452999 | Q73: Urban | R73: MCB bank | S73: Public place | T73: Bank - private | U73: Listed Venue | V73: 1 | W73: 0 | X73: MCB bank | Y73: No | AC73: No | AE73: No | AG73: Yes | AH73: Yes | AI73: Yes | AJ73: Does not apply / no one using tobacco or nicotine products | AK73: 0 | AL73: 0 | AM73: 0 | AN73: 0 | AO73: 0 | AP73: 0 | AQ73: 1 | AR73: 0 | AT73: Does not apply / no one using tobacco or nicotine products | AU73: No | AX73: No | BA73: No | BD73: No | BT73: Yes | FL73: 730198742 | FM73: 9356be0b-7806-4139-bfdf-705f0b502b59 | FN73: 46132.495 | FQ73: submitted_via_web | FS73: vjiNwcPYvtjoD8cL5yiJdz | FU73: uuid:9356be0b-7806-4139-bfdf-705f0b502b59 | FV73: 72
A74: HF core data | B74: 46127.584 | C74: 46132.704 | D74: 011 | E74: 46127 | F74: 14:00:00.000+05:00 | G74: 14:15:00.000+05:00 | H74: Syed Nadeem Abbas | I74: Faisalabad Division | J74: Jhang | K74: Jhang | L74: 31.26316 72.321758 114.5 17.78700065612793 | M74: 31.26316 | N74: 72.321758 | O74: 114.5 | P74: 17.787001 | Q74: Urban | R74: Shifa medical center | S74: Public place | T74: Health Facility - Hospital | U74: Listed Venue | V74: 1 | W74: 0 | X74: Shifa medical center | Y74: No | AC74: No | AE74: No | AG74: Yes | AH74: Yes | AI74: Yes | AJ74: Does not apply / no one using tobacco or nicotine products | AK74: 0 | AL74: 0 | AM74: 0 | AN74: 0 | AO74: 0 | AP74: 0 | AQ74: 1 | AR74: 0 | AT74: Does not apply / no one using tobacco or nicotine products | AU74: No | AX74: No | BA74: No | BD74: No | BT74: Yes | FL74: 730199970 | FM74: 08864d74-c3c3-4492-be25-bd12f5ba4a86 | FN74: 46132.495 | FQ74: submitted_via_web | FS74: vjiNwcPYvtjoD8cL5yiJdz | FU74: uuid:08864d74-c3c3-4492-be25-bd12f5ba4a86 | FV74: 73
A75: HF core data | B75: 46127.595 | C75: 46132.709 | D75: 012 | E75: 46127 | F75: 14:18:00.000+05:00 | G75: 14:35:00.000+05:00 | H75: Syed Nadeem Abbas | I75: Faisalabad Division | J75: Jhang | K75: Jhang | L75: 31.260963 72.320325 112.9000015258789 8.300000190734863 | M75: 31.260963 | N75: 72.320325 | O75: 112.9 | P75: 8.3000002 | Q75: Urban | R75: Usman General store | S75: Retail outlet /Point of Sale (POS) | DC75: Convenience / grocery store | DE75: Usman general store | DF75: Station chowk | DG75: No | DH75: Not Applicable/ No Young buyers visited | DI75: No | DL75: No | DP75: No | DT75: No | DW75: Yes | DX75: No | EA75: No | EE75: No | EI75: No | EM75: No | EQ75: No | EU75: No | EY75: No | FC75: No | FG75: No | FH75: Yes | FL75: 730206619 | FM75: 665ee4d4-1080-4fae-b3a0-567e4659a57e | FN75: 46132.501 | FQ75: submitted_via_web | FS75: vjiNwcPYvtjoD8cL5yiJdz | FU75: uuid:665ee4d4-1080-4fae-b3a0-567e4659a57e | FV75: 74
A76: HF core data | B76: 46132.701 | C76: 46132.713 | D76: Sahiwal 13 | E76: 46132 | F76: 17:01:00.000+05:00 | G76: 17:10:00.000+05:00 | H76: Ashfaq Ahmed Rao | I76: Sahiwal Division | J76: Sahiwal | K76: Sahiwal | L76: 30.66379 73.095737 129.40000915527344 15.001999855041504 | M76: 30.66379 | N76: 73.095737 | O76: 129.40001 | P76: 15.002 | Q76: Urban | R76: Meezan Bank | S76: Public place | T76: Bank - private | U76: Listed Venue | V76: 1 | W76: 0 | X76: Meezan Bank | Y76: No | AC76: No | AE76: No | AG76: No | AH76: Yes | AI76: No | AJ76: Does not apply / no one using tobacco or nicotine products | AK76: 0 | AL76: 0 | AM76: 0 | AN76: 0 | AO76: 0 | AP76: 0 | AQ76: 1 | AR76: 0 | AT76: No | AU76: No | AX76: No | BA76: No | BD76: No | BT76: Yes | BV76: They said we will not paste no smoking signage unless directed by Head office. | FL76: 730211665 | FM76: 50106cdc-2524-4bbd-ad7f-5d46a829d6fd | FN76: 46132.505 | FQ76: submitted_via_web | FS76: vjiNwcPYvtjoD8cL5yiJdz | FU76: uuid:50106cdc-2524-4bbd-ad7f-5d46a829d6fd | FV76: 75
A77: HF core data | B77: 46132.713 | C77: 46132.728 | D77: Sahiwal 14 | E77: 46132 | F77: 17:24:00.000+05:00 | G77: 17:35:00.000+05:00 | H77: Ashfaq Ahmed Rao | I77: Sahiwal Division | J77: Sahiwal | K77: Sahiwal | L77: 30.667915 73.09363 127.0999984741211 71.81500244140625 | M77: 30.667915 | N77: 73.09363 | O77: 127.1 | P77: 71.815002 | Q77: Urban | R77: DIG prisons Office | S77: Public place | T77: Government Offices - other | U77: Listed Venue | V77: 1 | W77: 0 | X77: DIG Prisons Office | Y77: Yes( add photo evidence) | Z77: 20260420_172810-17_28_20.jpg | AA77: https://kf.kobotoolbox.org/api/v2/assets/a7B4UGoSq7bg72YxNv837d/data/730243297/attachments/att5h2PtGCsEzKfiDHx9qYtS/ | AC77: No | AE77: No | AG77: Yes | AH77: Yes | AI77: Yes | AJ77: Does not apply / no one using tobacco or nicotine products | AK77: 0 | AL77: 0 | AM77: 0 | AN77: 0 | AO77: 0 | AP77: 0 | AQ77: 1 | AR77: 0 | AT77: Does not apply / no one using tobacco or nicotine products | AU77: No | AX77: No | BA77: No | BD77: No | BT77: Yes | BV77: Complete compliance of TC laws found. | FL77: 730243297 | FM77: c13f1bdd-9873-46ca-a13d-d0c17b05ac20 | FN77: 46132.527 | FQ77: submitted_via_web | FS77: vjiNwcPYvtjoD8cL5yiJdz | FU77: uuid:c13f1bdd-9873-46ca-a13d-d0c17b05ac20 | FV77: 76
A78: HF core data | B78: 46132.728 | C78: 46132.732 | D78: Sahiwal 15 | E78: 46132 | F78: 17:30:00.000+05:00 | G78: 17:35:00.000+05:00 | H78: Ashfaq Ahmed Rao | I78: Sahiwal Division | J78: Sahiwal | K78: Sahiwal | L78: 30.667553 73.095274 128.40000915527344 39.599998474121094 | M78: 30.667553 | N78: 73.095274 | O78: 128.40001 | P78: 39.599998 | Q78: Urban | R78: Commissioner Office sahiwal | S78: Public place | T78: Government Offices - District Authorities Offices e.g. (Health, Education, DC Office, C & W Office, Social Welfare etc.) | U78: Listed Venue | V78: 1 | W78: 0 | X78: Commissioner Office | Y78: Yes( add photo evidence) | Z78: 20260402_150149-17_32_45.jpg | AA78: https://kf.kobotoolbox.org/api/v2/assets/a7B4UGoSq7bg72YxNv837d/data/730243309/attachments/attW7ZmuVEkVwrTf8cy6xGU9/ | AB78: 5 | AC78: No | AE78: No | AG78: Yes | AH78: Yes | AI78: Yes | AJ78: Does not apply / no one using tobacco or nicotine products | AK78: 0 | AL78: 0 | AM78: 0 | AN78: 0 | AO78: 0 | AP78: 0 | AQ78: 1 | AR78: 0 | AT78: Does not apply / no one using tobacco or nicotine products | AU78: No | AX78: No | BA78: No | BD78: No | BT78: Yes | FL78: 730243309 | FM78: ae18f51c-9b5b-4997-ab48-18f23960daf4 | FN78: 46132.527 | FQ78: submitted_via_web | FS78: vjiNwcPYvtjoD8cL5yiJdz | FU78: uuid:ae18f51c-9b5b-4997-ab48-18f23960daf4 | FV78: 77
A79: HF core data | B79: 46132.732 | C79: 46132.745 | D79: Sahiwal 16 | E79: 46132 | F79: 17:38:00.000+05:00 | G79: 17:50:00.000+05:00 | H79: Ashfaq Ahmed Rao | I79: Sahiwal Division | J79: Sahiwal | K79: Sahiwal | L79: 30.673167 73.091968 128.6999969482422 16.899999618530273 | M79: 30.673167 | N79: 73.091968 | O79: 128.7 | P79: 16.9 | Q79: Urban | R79: Ravi Tobacco Shop | S79: Retail outlet /Point of Sale (POS) | DC79: Tobacco shop | DE79: Ravi Tobacco Shop | DF79: College Chowk | DG79: Yes | DH79: Never | DI79: Yes ( add photo Evidence) | DJ79: 20260420_174356-17_44_5.jpg | DK79: https://kf.kobotoolbox.org/api/v2/assets/a7B4UGoSq7bg72YxNv837d/data/730257882/attachments/attaoyDoBWzF6ZQ3Kku9RepD/ | DL79: No | DP79: No | DT79: No | DW79: Yes | DX79: Yes ( add photo evidence) | DY79: 20260420_174600-17_46_9.jpg | DZ79: https://kf.kobotoolbox.org/api/v2/assets/a7B4UGoSq7bg72YxNv837d/data/730257882/attachments/att4femqFuNQgx5B9WKD8WLp/ | EA79: No | EE79: Yes | EF79: Dunholme Special | EG79: 20260420_174729-17_47_39.jpg | EH79: https://kf.kobotoolbox.org/api/v2/assets/a7B4UGoSq7bg72YxNv837d/data/730257882/attachments/attfbMnnVwgKvfuJbTNHxB9H/ | EI79: No | EM79: No | EQ79: No | EU79: No | EY79: Yes ( add photo evidence) | EZ79: 20260420_174940-17_49_52.jpg | FA79: https://kf.kobotoolbox.org/api/v2/assets/a7B4UGoSq7bg72YxNv837d/data/730257882/attachments/attNL33ouu9S4H5pQLH8GEcc/ | FB79: Capstan select provide special price of 172 | FC79: No | FG79: Yes | FH79: Yes | FJ79: Shop is located right infront or we can say side by side by Government College University sahiwal | FL79: 730257882 | FM79: 42338fa4-5806-4957-9b96-1bdc9d9583d3 | FN79: 46132.537 | FQ79: submitted_via_web | FS79: vjiNwcPYvtjoD8cL5yiJdz | FU79: uuid:42338fa4-5806-4957-9b96-1bdc9d9583d3 | FV79: 78
A80: HF core data | B80: 46132.745 | C80: 46132.754 | D80: Sahiwal 17 | E80: 46132 | F80: 17:54:00.000+05:00 | G80: 18:05:00.000+05:00 | H80: Ashfaq Ahmed Rao | I80: Sahiwal Division | J80: Sahiwal | K80: Sahiwal | L80: 30.673308 73.091784 128.60000610351562 13.993000030517578 | M80: 30.673308 | N80: 73.091784 | O80: 128.60001 | P80: 13.993 | Q80: Urban | R80: Hafiz cold drink and karyana store | S80: Retail outlet /Point of Sale (POS) | DC80: other | DD80: Hafiz Cold Drink and Karyana store having all cigarettes | DE80: Hafiz cold drink and karyana | DF80: College Cowk | DG80: No | DH80: Never | DI80: No | DL80: No | DP80: No | DT80: No | DW80: Yes | DX80: Yes ( add photo evidence) | DY80: 20260420_180253-18_3_4.jpg | DZ80: https://kf.kobotoolbox.org/api/v2/assets/a7B4UGoSq7bg72YxNv837d/data/730276620/attachments/attYpmrnbRwLMGxmpSbsiVTn/ | EA80: No | EE80: No | EI80: No | EM80: No | EQ80: No | EU80: No | EY80: No | FC80: No | FG80: Yes | FH80: Yes | FJ80: The store located in college chowk sahiwal where government college and university is located. That's why it is called college chowk. | FL80: 730276620 | FM80: 57db762f-e898-46f4-ad5e-c83e6207acb3 | FN80: 46132.551 | FQ80: submitted_via_web | FS80: vjiNwcPYvtjoD8cL5yiJdz | FU80: uuid:57db762f-e898-46f4-ad5e-c83e6207acb3 | FV80: 79
A81: HF core data | B81: 46132.754 | C81: 46132.766 | D81: Sahiwal 18 | E81: 46132 | F81: 18:13:00.000+05:00 | G81: 18:23:00.000+05:00 | H81: Ashfaq Ahmed Rao | I81: Sahiwal Division | J81: Sahiwal | K81: Sahiwal | L81: 30.67434 73.08604 128.60000610351562 17.541000366210938 | M81: 30.67434 | N81: 73.08604 | O81: 128.60001 | P81: 17.541 | Q81: Urban | R81: Bukhari dairy and milk point | S81: Retail outlet /Point of Sale (POS) | DC81: other | DD81: It's name is Bukhari dairy and milk point but it wholly looks like a tobacco shop and drink corner | DE81: Bukhari dairy and milk point | DF81: Farid tow chowk | DG81: No | DH81: Never | DI81: No | DL81: No | DP81: No | DT81: No | DW81: Yes | DX81: Yes ( add photo evidence) | DY81: 20260420_180253-18_20_42.jpg | DZ81: https://kf.kobotoolbox.org/api/v2/assets/a7B4UGoSq7bg72YxNv837d/data/730287604/attachments/attVqXgYtJ6MhB8PuWeCAsav/ | EA81: No | EE81: Yes | EF81: Gold Street, Kiran, B H | EG81: 20260420_182221-18_22_33.jpg | EH81: https://kf.kobotoolbox.org/api/v2/assets/a7B4UGoSq7bg72YxNv837d/data/730287604/attachments/attUgPpyY3DXxT5s2GXkEe5V/ | EI81: No | EM81: No | EQ81: No | EU81: No | EY81: No | FC81: No | FG81: No | FH81: Yes | FL81: 730287604 | FM81: d88eb3ae-58a6-4c63-b5bc-1b25cbe94910 | FN81: 46132.558 | FQ81: submitted_via_web | FS81: vjiNwcPYvtjoD8cL5yiJdz | FU81: uuid:d88eb3ae-58a6-4c63-b5bc-1b25cbe94910 | FV81: 80
A82: HF core data | B82: 46132.766 | C82: 46132.779 | D82: Sahiwal 19 | E82: 46132 | F82: 18:27:00.000+05:00 | G82: 18:37:00.000+05:00 | H82: Ashfaq Ahmed Rao | I82: Sahiwal Division | J82: Sahiwal | K82: Sahiwal | L82: 30.673828 73.084132 128.5 17.14900016784668 | M82: 30.673828 | N82: 73.084132 | O82: 128.5 | P82: 17.149 | Q82: Urban | R82: Farid Town 4 number | S82: Retail outlet /Point of Sale (POS) | DC82: Convenience / grocery store | DE82: Hafiz Jee Cold Drink Corner | DF82: Farid Town 4 Number | DG82: No | DH82: Never | DI82: No | DL82: No | DP82: No | DT82: No | DW82: Yes | DX82: Yes ( add photo evidence) | DY82: 20260420_183933-18_39_44.jpg | DZ82: https://kf.kobotoolbox.org/api/v2/assets/a7B4UGoSq7bg72YxNv837d/data/730308150/attachments/attseidarWm9R2GvHWSzpUSq/ | EA82: No | EE82: Yes | EF82: Highway | EG82: 20260420_184048-18_41_31.jpg | EH82: https://kf.kobotoolbox.org/api/v2/assets/a7B4UGoSq7bg72YxNv837d/data/730308150/attachments/attw9EQTQtptm5sP8qPoKQd5/ | EI82: No | EM82: No | EQ82: No | EU82: No | EY82: No | FC82: No | FG82: No | FH82: Yes | FL82: 730308150 | FM82: 49feae12-89e7-4607-a18b-9b04e5329f57 | FN82: 46132.571 | FQ82: submitted_via_web | FS82: vjiNwcPYvtjoD8cL5yiJdz | FU82: uuid:49feae12-89e7-4607-a18b-9b04e5329f57 | FV82: 81
A83: HF core data | B83: 46127.605 | C83: 46132.791 | D83: 013 | E83: 46127 | F83: 14:48:00.000+05:00 | G83: 15:02:00.000+05:00 | H83: Syed Nadeem Abbas | I83: Faisalabad Division | J83: Jhang | K83: Jhang | L83: 31.263899 72.318888 114.30000305175781 21.09600067138672 | M83: 31.263899 | N83: 72.318888 | O83: 114.3 | P83: 21.096001 | Q83: Urban | R83: Toba road | S83: Public Service Vehicle (PSV) | BW83: Bus (Local) | BY83: Old version bus , | BZ83: Toba road | CA83: No | CB83: No | CC83: No | CD83: No | CF83: Does not apply / no one using tobacco or nicotine products | CG83: 0 | CH83: 0 | CI83: 0 | CJ83: 0 | CK83: 0 | CL83: 0 | CM83: 1 | CN83: 0 | CP83: Does not apply / no one smoking | CQ83: No | CT83: Yes ( add photo evidence) | CU83: 17766869860171712733683420372668-17_10_4.jpg | CV83: https://kf.kobotoolbox.org/api/v2/assets/a7B4UGoSq7bg72YxNv837d/data/730326826/attachments/attYzLG6NqxzTdFbJ96snPQX/ | CW83: Yes | CX83: Yes | CY83: Yes | CZ83: Yes | FL83: 730326826 | FM83: bfc62886-67e8-456f-8152-a3dca62747b7 | FN83: 46132.583 | FQ83: submitted_via_web | FS83: vjiNwcPYvtjoD8cL5yiJdz | FU83: uuid:bfc62886-67e8-456f-8152-a3dca62747b7 | FV83: 82
A84: HF core data | B84: 46127.611 | C84: 46132.792 | D84: 014 | E84: 46127 | F84: 15:14:00.000+05:00 | G84: 15:31:00.000+05:00 | H84: Syed Nadeem Abbas | I84: Faisalabad Division | J84: Jhang | K84: Jhang | L84: 31.269573 72.320441 115.19999694824219 14.907999992370605 | M84: 31.269573 | N84: 72.320441 | O84: 115.2 | P84: 14.908 | Q84: Urban | R84: Masala bites restaurants | S84: Public place | T84: Eatery ( Restaurant) | U84: Listed Venue | V84: 1 | W84: 0 | X84: Masala bite restaurant | Y84: Yes( add photo evidence) | Z84: IMG_20260415_144845_808-17_19_19.jpg | AA84: https://kf.kobotoolbox.org/api/v2/assets/a7B4UGoSq7bg72YxNv837d/data/730327231/attachments/attUzhRV4aajhiSMbPdnqQAo/ | AB84: 1 | AC84: No | AE84: No | AG84: Yes | AH84: Yes | AI84: Yes | AJ84: Does not apply / no one using tobacco or nicotine products | AK84: 0 | AL84: 0 | AM84: 0 | AN84: 0 | AO84: 0 | AP84: 0 | AQ84: 1 | AR84: 0 | AT84: Does not apply / no one using tobacco or nicotine products | AU84: No | AX84: No | BA84: No | BD84: No | BT84: Yes | FL84: 730327231 | FM84: 3bf8a1d9-58fb-42a9-92cb-3024be39bee0 | FN84: 46132.583 | FQ84: submitted_via_web | FS84: vjiNwcPYvtjoD8cL5yiJdz | FU84: uuid:3bf8a1d9-58fb-42a9-92cb-3024be39bee0 | FV84: 83
A85: HF core data | B85: 46127.623 | C85: 46132.792 | D85: 015 | E85: 46127 | F85: 15:50:00.000+05:00 | G85: 16:06:00.000+05:00 | H85: Syed Nadeem Abbas | I85: Faisalabad Division | J85: Jhang | K85: Jhang | L85: 31.26173 72.321035 113.4000015258789 14.112000465393066 | M85: 31.26173 | N85: 72.321035 | O85: 113.4 | P85: 14.112 | Q85: Urban | R85: Let's caffee | S85: Public place | T85: Eatery ( Cafe) | U85: Listed Venue | V85: 1 | W85: 0 | X85: Let's caffee | Y85: Yes( add photo evidence) | Z85: IMG_20260415_150158_100-17_25_3.jpg | AA85: https://kf.kobotoolbox.org/api/v2/assets/a7B4UGoSq7bg72YxNv837d/data/730327762/attachments/attLRPmZwytBQXVfV2NhLM7W/ | AB85: 1 | AC85: No | AE85: No | AG85: Yes | AH85: Yes | AI85: Yes | AJ85: Does not apply / no one using tobacco or nicotine products | AK85: 0 | AL85: 0 | AM85: 0 | AN85: 0 | AO85: 0 | AP85: 0 | AQ85: 1 | AR85: 0 | AT85: Does not apply / no one using tobacco or nicotine products | AU85: No | AX85: No | BA85: No | BD85: No | BT85: Yes | FL85: 730327762 | FM85: e0dc8963-19d8-48c7-ac89-2ce203e33c5b | FN85: 46132.584 | FQ85: submitted_via_web | FS85: vjiNwcPYvtjoD8cL5yiJdz | FU85: uuid:e0dc8963-19d8-48c7-ac89-2ce203e33c5b | FV85: 84
A86: HF core data | B86: 46127.628 | C86: 46132.792 | D86: 016 | E86: 46127 | F86: 16:11:00.000+05:00 | G86: 16:23:00.000+05:00 | H86: Syed Nadeem Abbas | I86: Faisalabad Division | J86: Jhang | K86: Jhang | L86: 31.268113 72.325205 113.9000015258789 32.159000396728516 | M86: 31.268113 | N86: 72.325205 | O86: 113.9 | P86: 32.159 | Q86: Urban | R86: Chai dabba shope | S86: Retail outlet /Point of Sale (POS) | DC86: other | DD86: Dabba | DE86: Chai dabba shope | DF86: Jail road | DG86: No | DH86: Not Applicable/ No Young buyers visited | DI86: No | DL86: No | DP86: No | DT86: No | DW86: Yes | DX86: No | EA86: No | EE86: No | EI86: No | EM86: No | EQ86: No | EU86: No | EY86: No | FC86: No | FG86: Yes | FH86: Yes | FJ86: Shop name was not mention on the board owner tell the shop name as Chai dabba shops which has mixed products collection. | FL86: 730328590 | FM86: 516c37ef-09ce-48e4-8bca-389fe547e370 | FN86: 46132.584 | FQ86: submitted_via_web | FS86: vjiNwcPYvtjoD8cL5yiJdz | FU86: uuid:516c37ef-09ce-48e4-8bca-389fe547e370 | FV86: 85
A87: HF core data | B87: 46127.629 | C87: 46132.793 | D87: 017 | E87: 46127 | F87: 16:30:00.000+05:00 | G87: 16:47:00.000+05:00 | H87: Syed Nadeem Abbas | I87: Faisalabad Division | J87: Jhang | K87: Jhang | L87: 31.271475 72.323213 113.0999984741211 21.450000762939453 | M87: 31.271475 | N87: 72.323213 | O87: 113.1 | P87: 21.450001 | Q87: Urban | R87: Company bagh | S87: Public place | T87: Entertainment/sports venue - Recreational Areas / Snooker club/ Game zone | U87: Listed Venue | V87: 1 | W87: 0 | X87: Company bagh | Y87: No | AC87: No | AE87: No | AG87: Yes | AH87: Yes | AI87: Yes | AJ87: Does not apply / no one using tobacco or nicotine products | AK87: 0 | AL87: 0 | AM87: 0 | AN87: 0 | AO87: 0 | AP87: 0 | AQ87: 1 | AR87: 0 | AT87: Does not apply / no one using tobacco or nicotine products | AU87: No | AX87: No | BA87: No | BD87: No | BT87: Yes | BV87: The area was fully opened garden type , it was located infront of AC DC offices . | FL87: 730329134 | FM87: 2ddf7afd-509d-4a36-8ec8-60e528bda29b | FN87: 46132.585 | FQ87: submitted_via_web | FS87: vjiNwcPYvtjoD8cL5yiJdz | FU87: uuid:2ddf7afd-509d-4a36-8ec8-60e528bda29b | FV87: 86
A88: HF core data | B88: 46127.635 | C88: 46132.793 | D88: 018 | E88: 46127 | F88: 17:00:00.000+05:00 | G88: 17:15:00.000+05:00 | H88: Syed Nadeem Abbas | I88: Faisalabad Division | J88: Jhang | K88: Jhang | L88: 31.273617 72.319577 115.0999984741211 8.25 | M88: 31.273617 | N88: 72.319577 | O88: 115.1 | P88: 8.25 | Q88: Urban | R88: Burger mafia | S88: Public place | T88: Eatery ( Cafe) | U88: Listed Venue | V88: 1 | W88: 0 | X88: Burger mafia | Y88: Yes( add photo evidence) | Z88: IMG_20260415_152150_472-15_28_29.jpg | AA88: https://kf.kobotoolbox.org/api/v2/assets/a7B4UGoSq7bg72YxNv837d/data/730329581/attachments/attVM5pwzC7s7kE8yRHAPoQv/ | AB88: 1 | AC88: No | AE88: No | AG88: Yes | AH88: Yes | AI88: Yes | AJ88: Does not apply / no one using tobacco or nicotine products | AK88: 0 | AL88: 0 | AM88: 0 | AN88: 0 | AO88: 0 | AP88: 0 | AQ88: 1 | AR88: 0 | AT88: Does not apply / no one using tobacco or nicotine products | AU88: No | AX88: No | BA88: No | BD88: No | BT88: Yes | FL88: 730329581 | FM88: e7904130-81b5-4b0d-8067-c190cd1dc7e7 | FN88: 46132.585 | FQ88: submitted_via_web | FS88: vjiNwcPYvtjoD8cL5yiJdz | FU88: uuid:e7904130-81b5-4b0d-8067-c190cd1dc7e7 | FV88: 87
A89: HF core data | B89: 46127.646 | C89: 46132.793 | D89: 019 | E89: 46127 | F89: 17:21:00.000+05:00 | G89: 17:34:00.000+05:00 | H89: Syed Nadeem Abbas | I89: Faisalabad Division | J89: Jhang | K89: Jhang | L89: 31.273243 72.318997 121 14.182000160217285 | M89: 31.273243 | N89: 72.318997 | O89: 121 | P89: 14.182 | Q89: Urban | R89: Baranh jhang | S89: Public place | T89: Eatery ( Restaurant) | U89: Listed Venue | V89: 1 | W89: 0 | X89: Baranh jhang | Y89: Yes( add photo evidence) | Z89: IMG_20260415_153444_858-15_37_19.jpg | AA89: https://kf.kobotoolbox.org/api/v2/assets/a7B4UGoSq7bg72YxNv837d/data/730330188/attachments/attsw3ThnT6CXeQEkYzmGgXC/ | AB89: 2 | AC89: No | AE89: No | AG89: Yes | AH89: Yes | AI89: Yes | AJ89: Does not apply / no one using tobacco or nicotine products | AK89: 0 | AL89: 0 | AM89: 0 | AN89: 0 | AO89: 0 | AP89: 0 | AQ89: 1 | AR89: 0 | AT89: Does not apply / no one using tobacco or nicotine products | AU89: No | AX89: No | BA89: No | BD89: No | BT89: Yes | FL89: 730330188 | FM89: b7cfedfc-3d8b-4b6b-8cde-68690a2f4c6c | FN89: 46132.585 | FQ89: submitted_via_web | FS89: vjiNwcPYvtjoD8cL5yiJdz | FU89: uuid:b7cfedfc-3d8b-4b6b-8cde-68690a2f4c6c | FV89: 88
A90: HF core data | B90: 46127.653 | C90: 46132.794 | D90: 020 | E90: 46127 | F90: 21:16:00.000+05:00 | G90: 21:42:00.000+05:00 | H90: Syed Nadeem Abbas | I90: Faisalabad Division | J90: Jhang | K90: Jhang | L90: 31.277659 72.321077 114.69999694824219 18.742000579833984 | M90: 31.277659 | N90: 72.321077 | O90: 114.7 | P90: 18.742001 | Q90: Urban | R90: Bismillah hotel | S90: Public place | T90: Eatery ( Restaurant) | U90: Unlisted Venue | V90: 0 | W90: 1 | X90: Bismillah hotel | Y90: No | AC90: No | AE90: No | AG90: Yes | AH90: Yes | AI90: Yes | AJ90: Does not apply / no one using tobacco or nicotine products | AK90: 0 | AL90: 0 | AM90: 0 | AN90: 0 | AO90: 0 | AP90: 0 | AQ90: 1 | AR90: 0 | AT90: Does not apply / no one using tobacco or nicotine products | AU90: No | AX90: No | BA90: No | BD90: Yes (add photo Evidence) | BE90: IMG_20260417_083224_855-18_5_18.jpg | BF90: https://kf.kobotoolbox.org/api/v2/assets/a7B4UGoSq7bg72YxNv837d/data/730330821/attachments/attLRdUHjQZVSSsHmpowAzXP/ | BG90: Cigarette Nicotine pouch | BH90: 1 | BI90: 0 | BJ90: 0 | BK90: 1 | BL90: 0 | BM90: 0 | BN90: 0 | BO90: 0 | BQ90: No | BT90: Yes | FL90: 730330821 | FM90: a1b19648-c495-4700-a65b-8afafbd89d44 | FN90: 46132.586 | FQ90: submitted_via_web | FS90: vjiNwcPYvtjoD8cL5yiJdz | FU90: uuid:a1b19648-c495-4700-a65b-8afafbd89d44 | FV90: 89
A91: HF core data | B91: 46132.779 | C91: 46132.797 | D91: Sahiwal 20 | E91: 46132 | F91: 19:01:00.000+05:00 | G91: 19:10:00.000+05:00 | H91: Ashfaq Ahmed Rao | I91: Sahiwal Division | J91: Sahiwal | K91: Sahiwal | L91: 30.682593 73.104334 130.50001525878906 10.777999877929688 | M91: 30.682593 | N91: 73.104334 | O91: 130.50002 | P91: 10.778 | Q91: Urban | R91: Sahiwal drink corner | S91: Retail outlet /Point of Sale (POS) | DC91: Tobacco shop | DE91: Sahiwal drink corner | DF91: Noor shah Road infront of sahiwal teaching hospital | DG91: No | DH91: Never | DI91: No | DL91: No | DP91: No | DT91: No | DW91: Yes | DX91: Yes ( add photo evidence) | DY91: 20260420_190441-19_4_48.jpg | DZ91: https://kf.kobotoolbox.org/api/v2/assets/a7B4UGoSq7bg72YxNv837d/data/730335076/attachments/attB8RZQdDtQ59rf64nLPRaa/ | EA91: No | EE91: Yes | EF91: Marvel, Dunhill, capstan | EG91: 20260420_190540-19_5_51.jpg | EH91: https://kf.kobotoolbox.org/api/v2/assets/a7B4UGoSq7bg72YxNv837d/data/730335076/attachments/attujW2pni2JYXPef7vdroFz/ | EI91: No | EM91: No | EQ91: No | EU91: No | EY91: No | FC91: No | FG91: Yes | FH91: Yes | FJ91: Noor shah Road infront of sahiwal teaching hospital | FL91: 730335076 | FM91: e4b01824-8e75-47f0-a38b-74c10ec470ba | FN91: 46132.588 | FQ91: submitted_via_web | FS91: vjiNwcPYvtjoD8cL5yiJdz | FU91: uuid:e4b01824-8e75-47f0-a38b-74c10ec470ba | FV91: 90
A92: HF core data | B92: 46132.797 | C92: 46132.801 | D92: Sahiwal 21 | E92: 46132 | F92: 19:08:00.000+05:00 | G92: 19:18:00.000+05:00 | H92: Ashfaq Ahmed Rao | I92: Sahiwal Division | J92: Sahiwal | K92: Sahiwal | L92: 30.682775 73.104262 130.40000915527344 20.465999603271484 | M92: 30.682775 | N92: 73.104262 | O92: 130.40001 | P92: 20.466 | Q92: Urban | R92: Kot fareed opposite DHQ | S92: Retail outlet /Point of Sale (POS) | DC92: Convenience / grocery store | DE92: Fareedi Karyana | DF92: Fareed kot | DG92: No | DH92: Sometimes | DI92: No | DL92: No | DP92: No | DT92: No | DW92: Yes | DX92: Yes ( add photo evidence) | DY92: 20260420_191140-19_11_49.jpg | DZ92: https://kf.kobotoolbox.org/api/v2/assets/a7B4UGoSq7bg72YxNv837d/data/730341139/attachments/attkNoH8X52CDYRAimEncskL/ | EA92: No | EE92: No | EI92: No | EM92: No | EQ92: No | EU92: No | EY92: No | FC92: No | FG92: Yes | FH92: Yes | FJ92: Store is located in front of sahiwal teaching hospital | FL92: 730341139 | FM92: 918a6981-830c-47e6-90ca-1d362d0db3ed | FN92: 46132.592 | FQ92: submitted_via_web | FS92: vjiNwcPYvtjoD8cL5yiJdz | FU92: uuid:918a6981-830c-47e6-90ca-1d362d0db3ed | FV92: 91
A93: HF core data | B93: 46132.801 | C93: 46132.805 | D93: Sahiwal 22 | E93: 46132 | F93: 19:15:00.000+05:00 | G93: 19:25:00.000+05:00 | H93: Ashfaq Ahmed Rao | I93: Sahiwal Division | J93: Sahiwal | K93: Sahiwal | L93: 30.6834 73.104291 130.50001525878906 14.807000160217285 | M93: 30.6834 | N93: 73.104291 | O93: 130.50002 | P93: 14.807 | Q93: Urban | R93: Fareed kot DHQ Gate 3 | S93: Retail outlet /Point of Sale (POS) | DC93: Tobacco shop | DE93: Ahmad General Store | DF93: Sahiwal Dhq Gate 3 | DG93: No | DH93: Sometimes | DI93: No | DL93: No | DP93: No | DT93: No | DW93: Yes | DX93: Yes ( add photo evidence) | DY93: 20260420_191841-19_18_49.jpg | DZ93: https://kf.kobotoolbox.org/api/v2/assets/a7B4UGoSq7bg72YxNv837d/data/730348684/attachments/attfbuTyt8zYt6d7sRYQGy6Q/ | EA93: No | EE93: No | EI93: No | EM93: No | EQ93: No | EU93: No | EY93: No | FC93: No | FG93: Yes | FH93: Yes | FL93: 730348684 | FM93: b0daef9a-9be1-4bf1-b7d1-d3acc8841a3a | FN93: 46132.597 | FQ93: submitted_via_web | FS93: vjiNwcPYvtjoD8cL5yiJdz | FU93: uuid:b0daef9a-9be1-4bf1-b7d1-d3acc8841a3a | FV93: 92
A94: HF core data | B94: 46132.805 | C94: 46132.813 | D94: Sahiwal 23 | E94: 46132 | F94: 19:21:00.000+05:00 | G94: 19:30:00.000+05:00 | H94: Ashfaq Ahmed Rao | I94: Sahiwal Division | J94: Sahiwal | K94: Sahiwal | L94: 30.684221 73.104166 131.40000915527344 13.597000122070312 | M94: 30.684221 | N94: 73.104166 | O94: 131.40001 | P94: 13.597 | Q94: Urban | R94: Gate 4 DHQ | S94: Retail outlet /Point of Sale (POS) | DC94: Tobacco shop | DE94: Ahsan Pan Shop | DF94: DHQ Gate 4 | DG94: No | DH94: Sometimes | DI94: No | DL94: No | DP94: No | DT94: No | DW94: Yes | DX94: Yes ( add photo evidence) | DY94: 20260420_192420-19_24_59.jpg | DZ94: https://kf.kobotoolbox.org/api/v2/assets/a7B4UGoSq7bg72YxNv837d/data/730359793/attachments/attqbAHXrvXsdryebQUEftRp/ | EA94: No | EE94: Yes | EF94: Dunhill kisan | EG94: 20260420_192545-19_27_10.jpg | EH94: https://kf.kobotoolbox.org/api/v2/assets/a7B4UGoSq7bg72YxNv837d/data/730359793/attachments/attSp3phWvK5ivnb3mWuRa2r/ | EI94: No | EM94: No | EQ94: No | EU94: No | EY94: No | FC94: No | FG94: Yes | FH94: Yes | FL94: 730359793 | FM94: b7ad7b03-652b-4af4-ab9f-de8cf58e5ead | FN94: 46132.604 | FQ94: submitted_via_web | FS94: vjiNwcPYvtjoD8cL5yiJdz | FU94: uuid:b7ad7b03-652b-4af4-ab9f-de8cf58e5ead | FV94: 93
A95: HF core data | B95: 46132.813 | C95: 46132.818 | D95: Sahiwal 24 | E95: 46132 | F95: 19:32:00.000+05:00 | G95: 19:40:00.000+05:00 | H95: Ashfaq Ahmed Rao | I95: Sahiwal Division | J95: Sahiwal | K95: Sahiwal | L95: 30.684735 73.10412 131.70001220703125 20 | M95: 30.684735 | N95: 73.10412 | O95: 131.70001 | P95: 20 | Q95: Urban | R95: Sahiwal | S95: Retail outlet /Point of Sale (POS) | DC95: Tobacco shop | DE95: Kaka smoke spot | DF95: Noor shah road | DG95: No | DH95: Sometimes | DI95: No | DL95: No | DP95: No | DT95: No | DW95: Yes | DX95: Yes ( add photo evidence) | DY95: 20260420_193510-19_35_19.jpg | DZ95: https://kf.kobotoolbox.org/api/v2/assets/a7B4UGoSq7bg72YxNv837d/data/730367802/attachments/attjfgYEDHwPkJL4ghZt5Gv5/ | EA95: No | EE95: No | EI95: No | EM95: No | EU95: No | EY95: No | FC95: No | FG95: No | FH95: Yes | FL95: 730367802 | FM95: 6e7efc1f-8bf1-48b7-a1bb-d19a83695370 | FN95: 46132.609 | FQ95: submitted_via_web | FS95: vjiNwcPYvtjoD8cL5yiJdz | FU95: uuid:6e7efc1f-8bf1-48b7-a1bb-d19a83695370 | FV95: 94
A96: HF core data | B96: 46132.818 | C96: 46132.823 | D96: Sahiwal 25 | E96: 46132 | F96: 19:40:00.000+05:00 | G96: 19:49:00.000+05:00 | H96: Ashfaq Ahmed Rao | I96: Sahiwal Division | J96: Sahiwal | K96: Sahiwal | L96: 30.68647 73.104345 131.20001220703125 16.28499984741211 | M96: 30.68647 | N96: 73.104345 | O96: 131.20001 | P96: 16.285 | Q96: Urban | R96: Noor Shah Road | S96: Retail outlet /Point of Sale (POS) | DC96: Tobacco shop | DE96: Smoke Spot | DF96: Noor Shah Road | DG96: No | DH96: Sometimes | DI96: No | DL96: No | DP96: No | DT96: No | DW96: Yes | DX96: Yes ( add photo evidence) | DY96: 20260420_194234-19_42_45.jpg | DZ96: https://kf.kobotoolbox.org/api/v2/assets/a7B4UGoSq7bg72YxNv837d/data/730375033/attachments/attm6CbMSrWasMr78oniRYeS/ | EA96: No | EE96: Yes | EF96: Capstan Dunhill | EG96: 20260420_194234-19_43_26.jpg | EH96: https://kf.kobotoolbox.org/api/v2/assets/a7B4UGoSq7bg72YxNv837d/data/730375033/attachments/atthnQMkemdasWAohgkN8weA/ | EI96: No | EM96: Yes | EN96: Velo | EO96: 20260420_194234-19_43_48.jpg | EP96: https://kf.kobotoolbox.org/api/v2/assets/a7B4UGoSq7bg72YxNv837d/data/730375033/attachments/attiaGvo2HFbjd75kqY9Mayu/ | EQ96: No | EU96: Yes | EV96: Velo | EW96: 20260420_194234-19_44_32.jpg | EX96: https://kf.kobotoolbox.org/api/v2/assets/a7B4UGoSq7bg72YxNv837d/data/730375033/attachments/attdfc42iaPjPDGKbdbKVB3M/ | EY96: No | FC96: No | FG96: No | FH96: Yes | FL96: 730375033 | FM96: 79ff927d-3e54-47d8-8c7e-930075bac69a | FN96: 46132.615 | FQ96: submitted_via_web | FS96: vjiNwcPYvtjoD8cL5yiJdz | FU96: uuid:79ff927d-3e54-47d8-8c7e-930075bac69a | FV96: 95
A97: HF core data | B97: 46132.823 | C97: 46132.826 | D97: Sahiwal 26 | E97: 46132 | F97: 19:47:00.000+05:00 | G97: 19:57:00.000+05:00 | H97: Ashfaq Ahmed Rao | I97: Sahiwal Division | J97: Sahiwal | K97: Sahiwal | L97: 30.688238 73.104819 130.70001220703125 18.24799919128418 | M97: 30.688238 | N97: 73.104819 | O97: 130.70001 | P97: 18.247999 | Q97: Urban | R97: Noor Shah Road | S97: Retail outlet /Point of Sale (POS) | DC97: Tobacco shop | DE97: Lady je Smoke and Drink Corner | DF97: Noor Shah road | DG97: No | DH97: Sometimes | DI97: No | DL97: No | DP97: No | DT97: No | DW97: Yes | DX97: Yes ( add photo evidence) | DY97: 20260420_194908-19_49_18.jpg | DZ97: https://kf.kobotoolbox.org/api/v2/assets/a7B4UGoSq7bg72YxNv837d/data/730380474/attachments/attVbf4iXe3Bgde9rQYbg6B7/ | EA97: No | EE97: No | EI97: No | EM97: No | EQ97: No | EU97: No | EY97: No | FC97: No | FG97: No | FH97: Yes | FL97: 730380474 | FM97: fbf69cdd-e84b-496a-b0f4-9e856ea385d7 | FN97: 46132.618 | FQ97: submitted_via_web | FS97: vjiNwcPYvtjoD8cL5yiJdz | FU97: uuid:fbf69cdd-e84b-496a-b0f4-9e856ea385d7 | FV97: 96
A98: HF core data | B98: 46132.826 | C98: 46132.837 | D98: Sahiwal 27 | E98: 46132 | F98: 19:59:00.000+05:00 | G98: 20:10:00.000+05:00 | H98: Ashfaq Ahmed Rao | I98: Sahiwal Division | J98: Sahiwal | K98: Sahiwal | L98: 30.665963 73.106842 131.20001220703125 18.913999557495117 | M98: 30.665963 | N98: 73.106842 | O98: 131.20001 | P98: 18.914 | Q98: Urban | R98: High Street | S98: Retail outlet /Point of Sale (POS) | DC98: Tobacco shop | DE98: Shahi chae and Shahi Tuc shop | DF98: Mission chowk | DG98: No | DH98: Never | DI98: No | DL98: No | DP98: No | DT98: No | DW98: Yes | DX98: Yes ( add photo evidence) | DY98: 20260420_200219-20_3_14.jpg | DZ98: https://kf.kobotoolbox.org/api/v2/assets/a7B4UGoSq7bg72YxNv837d/data/730396318/attachments/attZVGQgF3Ce9FW9Yfmpbs5b/ | EA98: No | EE98: No | EI98: No | EM98: No | EQ98: No | EU98: No | EY98: No | FC98: No | FG98: No | FH98: Yes | FL98: 730396318 | FM98: ad8aac08-a4d7-477f-9cd7-201fa31f97c9 | FN98: 46132.628 | FQ98: submitted_via_web | FS98: vjiNwcPYvtjoD8cL5yiJdz | FU98: uuid:ad8aac08-a4d7-477f-9cd7-201fa31f97c9 | FV98: 97
A99: HF core data | B99: 46132.837 | C99: 46132.845 | D99: Sahiwal 28 | E99: 46132 | F99: 20:13:00.000+05:00 | G99: 20:23:00.000+05:00 | H99: Ashfaq Ahmed Rao | I99: Sahiwal Division | J99: Sahiwal | K99: Sahiwal | L99: 30.655602 73.117483 132.8000030517578 21.148000717163086 | M99: 30.655602 | N99: 73.117483 | O99: 132.8 | P99: 21.148001 | Q99: Urban | R99: Friends Senima Road | S99: Retail outlet /Point of Sale (POS) | DC99: Convenience / grocery store | DE99: Bismillah karyana | DF99: Friends senima road | DG99: No | DH99: Never | DI99: No | DL99: No | DP99: No | DT99: No | DW99: Yes | DX99: No | EA99: No | EE99: No | EI99: No | EM99: No | EQ99: No | EU99: No | EY99: No | FC99: No | FG99: No | FH99: Yes | FL99: 730411592 | FM99: 46849a02-7a01-4529-af5c-365dabeae7b0 | FN99: 46132.637 | FQ99: submitted_via_web | FS99: vjiNwcPYvtjoD8cL5yiJdz | FU99: uuid:46849a02-7a01-4529-af5c-365dabeae7b0 | FV99: 98
A100: HF core data | B100: 46132.845 | C100: 46132.855 | D100: Sahiwal 29 | E100: 46132 | F100: 20:25:00.000+05:00 | G100: 20:35:00.000+05:00 | H100: Ashfaq Ahmed Rao | I100: Sahiwal Division | J100: Sahiwal | K100: Sahiwal | L100: 30.650925 73.118792 131.40000915527344 20.173999786376953 | M100: 30.650925 | N100: 73.118792 | O100: 131.40001 | P100: 20.174 | Q100: Urban | R100: Pakpattan Chowk | S100: Public place | T100: Eatery ( Restaurant) | U100: Unlisted Venue | V100: 0 | W100: 1 | X100: Lal Qila Restaurant | Y100: No | AC100: No | AE100: No | AG100: Yes | AH100: Yes | AI100: Yes | AJ100: Does not apply / no one using tobacco or nicotine products | AK100: 0 | AL100: 0 | AM100: 0 | AN100: 0 | AO100: 0 | AP100: 0 | AQ100: 1 | AR100: 0 | AT100: Does not apply / no one using tobacco or nicotine products | AU100: No | AX100: No | BA100: No | BD100: No | BT100: Yes | FL100: 730426038 | FM100: d7fd9bee-4b87-4f72-8315-302167f4ed8c | FN100: 46132.647 | FQ100: submitted_via_web | FS100: vjiNwcPYvtjoD8cL5yiJdz | FU100: uuid:d7fd9bee-4b87-4f72-8315-302167f4ed8c | FV100: 99
...

Sheet HF core data
A1: sampled or not? | B1: start | C1: end | D1: Form Number | E1: Date of Visit | F1: Start Time | G1: End time | H1: Enumerator | I1: Division | J1: District | K1: city/ Tehsil | L1: Geo Location | M1: _Geo Location _latitude | N1: _Geo Location _longitude | O1: _Geo Location _altitude | P1: _Geo Location _precision | Q1: Urban/ Rural? | R1: Name of Place | S1: Category of Place | T1: OLD A1:Type of public place | U1: Mapping status:Is the venue a Listed Venue or an unlisted venue? | V1: Mapping status:Is the venue a Listed Venue or an unlisted venue?/Listed Venue | W1: Mapping status:Is the venue a Listed Venue or an unlisted venue?/Unlisted Venue | X1: A2: Name of Public place | Y1: A3: “No Smoking Area”, “Smoking is illegal here” or similar boards are visible? | Z1: If yes, add photo Evidence | AA1: If yes, add photo Evidence _URL | AB1: If yes how many | AC1: A4: PEOPLE found smoking in the indoor area at the time of visit? | AD1: If yes, how many? | AE1: A5: STAFF found smoking in the indoor area at the time of visit? | AF1: If yes, how many? | AG1: A6: STAFF is aware of ban on smoking in public place? | AH1: A7: Authorized officer of the public place is aware of legal responsibility to stop persons from smoking indoors? | AI1: A8: Authorized officer of the public place is aware of legal responsibility to display ‘no smoking’ signboard? | AJ1: A9: If any persons were found USING any type of tobacco or nicotine product, what type are they using? | AK1: A9: If any persons were found USING any type of tobacco or nicotine product, what type are they using?/Cigarette | AL1: A9: If any persons were found USING any type of tobacco or nicotine product, what type are they using?/Naswar | AM1: A9: If any persons were found USING any type of tobacco or nicotine product, what type are they using?/Shisha / Hookah | AN1: A9: If any persons were found USING any type of tobacco or nicotine product, what type are they using?/Nicotine pouch | AO1: A9: If any persons were found USING any type of tobacco or nicotine product, what type are they using?/Heated Tobacco Products (HTPs) | AP1: A9: If any persons were found USING any type of tobacco or nicotine product, what type are they using?/E- cigarettes / vapes | AQ1: A9: If any persons were found USING any type of tobacco or nicotine product, what type are they using?/Does not apply / no one using tobacco or nicotine products | AR1: A9: If any persons were found USING any type of tobacco or nicotine product, what type are they using?/other | AS1: specify "other" | AT1: A10: If any persons were USING any type of tobacco or nicotine product, did authorized officer or staff member of the public place try to stop them? | AU1: A11: Cigarette butts are visible in the indoor area? | AV1: IIf Yes, add photo Evidence | AW1: IIf Yes, add photo Evidence _URL | AX1: A12: Ashtrays or matches are visible in the indoor area? | AY1: add photo Evidence | AZ1: add photo Evidence _URL | BA1: A13: Is there a “designated smoking area” in the public place? | BB1: add photo Evidence | BC1: add photo Evidence _URL | BD1: A14: Are there any tobacco or nicotine products being SOLD on the premises? | BE1: add photo Evidence | BF1: add photo Evidence _URL | BG1: A15: If tobacco or nicotine products are being SOLD on the premises, which products are being sold? | BH1: A15: If tobacco or nicotine products are being SOLD on the premises, which products are being sold?/Cigarette | BI1: A15: If tobacco or nicotine products are being SOLD on the premises, which products are being sold?/Naswar | BJ1: A15: If tobacco or nicotine products are being SOLD on the premises, which products are being sold?/Shisha / Hookah | BK1: A15: If tobacco or nicotine products are being SOLD on the premises, which products are being sold?/Nicotine pouch | BL1: A15: If tobacco or nicotine products are being SOLD on the premises, which products are being sold?/Heated Tobacco Products (HTPs) | BM1: A15: If tobacco or nicotine products are being SOLD on the premises, which products are being sold?/E- cigarettes / vapes | BN1: A15: If tobacco or nicotine products are being SOLD on the premises, which products are being sold?/Does not apply / no one using tobacco or nicotine products | BO1: A15: If tobacco or nicotine products are being SOLD on the premises, which products are being sold?/other | BP1: specify "other" | BQ1: A16: If tobacco products are being SOLD on the premises, does the seller have a license under TVA? | BR1: add photo Evidence | BS1: add photo Evidence _URL | BT1: A17: Were you able to complete the observation? | BU1: A18: Reason for incompletion. | BV1: A19: Additional comments (if any) | BW1: B1: Type of public service vehicle | BX1: specify "other" | BY1: B2: Name of PSV or PSV company (if applicable) | BZ1: B3: Route number or name of PSV company (if applicable) | CA1: B4: “No Smoking” sign displayed inside PSV? | CB1: B5: Driver found smoking in public vehicle? | CC1: B6: Conductor found smoking inside PSV? | CD1: B7: Passenger found smoking inside PSV? | CE1: if yes, how many? | CF1: B8: If any persons were found using Tobacco Products, what type of tobacco or nicotine product were they using? | CG1: B8: If any persons were found using Tobacco Products, what type of tobacco or nicotine product were they using?/Cigarette | CH1: B8: If any persons were found using Tobacco Products, what type of tobacco or nicotine product were they using?/Naswar | CI1: B8: If any persons were found using Tobacco Products, what type of tobacco or nicotine product were they using?/Shisha / Hookah | CJ1: B8: If any persons were found using Tobacco Products, what type of tobacco or nicotine product were they using?/Nicotine pouch | CK1: B8: If any persons were found using Tobacco Products, what type of tobacco or nicotine product were they using?/Heated Tobacco Products (HTPs) | CL1: B8: If any persons were found using Tobacco Products, what type of tobacco or nicotine product were they using?/E- cigarettes / vapes | CM1: B8: If any persons were found using Tobacco Products, what type of tobacco or nicotine product were they using?/Does not apply / no one using tobacco or nicotine products | CN1: B8: If any persons were found using Tobacco Products, what type of tobacco or nicotine product were they using?/other | CO1: specify "other" | CP1: B9: If any persons were smoking, did driver/conductor try to stop them? | CQ1: B10: Cigarette butts are visible inside the PSV? | CR1: IIf Yes, add photo Evidence | CS1: IIf Yes, add photo Evidence _URL | CT1: B11: Ashtrays are visible inside the PSV? | CU1: If Yes, add photo Evidence | CV1: If Yes, add photo Evidence _URL | CW1: B12: PSV staff is aware of ban on smoking in PSVs? | CX1: B13: PSV staff is aware of legal responsibility to display ‘no smoking’ signboard? | CY1: B14: PSV staff is aware of legal responsibility to stop persons from smoking in the vehicle? | CZ1: B15: were you able to complete the observation? | DA1: B16: Reason for incompletion. | DB1: B17: Additional comments (if any). | DC1: C1: Type of outlet | DD1: specify "other" | DE1: C2: Name of outlet | DF1: C3: Market / neighborhood of outlet | DG1: C4: Sales of tobacco products to minors (under 18 years of age) taking place at time of visit? | DH1: C5: Was the vendor checking ID cards of YOUNG buyers of tobacco products during purchase at time of visit? | DI1: C6: Is there a ‘No Sales to Minors/Persons Under 18’ sign (or similar ) on display? | DJ1: If Yes, add photo Evidence | DK1: If Yes, add photo Evidence _URL | DL1: C7: Cigarette packs without graphic health warning available for sale? | DM1: if Yes, specify brands | DN1: add photo Evidence | DO1: add photo Evidence _URL | DP1: C8: Cigarette packs without excise stamps available for sale? | DQ1: if Yes, specify brands | DR1: add photo Evidence | DS1: add photo Evidence _URL | DT1: C9: Does the seller have a license under TVA? | DU1: add photo Evidence | DV1: add photo Evidence _URL | DW1: C10: Loose cigarettes are available for sale? | DX1: C11: Cigarettes are placed next to candies, snacks or children’s products? | DY1: add photo Evidence | DZ1: add photo Evidence _URL | EA1: C12-Cig-indoor-advert: Are Cigarette brands advertized indoors? | EB1: C12-Cig-indoor-advert-brands: If yes, which brands? | EC1: C12-Cig-indoor-advert-evidence: add photo Evidence of INDOOR advertisements | ED1: C12-Cig-indoor-advert-evidence: add photo Evidence of INDOOR advertisements_URL | EE1: C12-Cig-Outdoor-advert: Are Cigarette brands advertized Outdoors? | EF1: C12-Cig-Outdoor-advert-brands: If yes, which brands? | EG1: C12-Cig-outdoor-advert-evidence: add photo Evidence of OUTDOOR advertisements | EH1: C12-Cig-outdoor-advert-evidence: add photo Evidence of OUTDOOR advertisements_URL | EI1: C12-ONP-indoor-advert: Are Nicotine Pouches advertized indoors? | EJ1: C12-ONP-indoor-advert-brands: If yes, which brands? | EK1: C12-ONP-indoor-advert-evidence: add photo Evidence of INDOOR advertisements | EL1: C12-ONP-indoor-advert-evidence: add photo Evidence of INDOOR advertisements_URL | EM1: C12-ONP-Outdoor-advert: Are Nicotine Pouches advertized outdoors? | EN1: C12-ONP-Outdoor-advert-brands: If yes, which brands? | EO1: C12-ONP-outdoor-advert-evidence: add photo Evidence of OUTDOOR advertisements | EP1: C12-ONP-outdoor-advert-evidence: add photo Evidence of OUTDOOR advertisements_URL | EQ1: C12-Other-tobacco-indoor-advert: Are "any other Tobacco Products" advertized indoors? | ER1: C12-Other-tobacco-indoor-advert-brands:If yes, which brands? | ES1: C12-Other-tobacco-advert-evidence: add photo Evidence of INDOOR advertisements | ET1: C12-Other-tobacco-advert-evidence: add photo Evidence of INDOOR advertisements_URL | EU1: C12-Other-tobacco-Outdoor-advert: Are "any other Tobacco Products" advertized outdoors? | EV1: C12-Other-tobacco-Outdoor-advert-brands: If yes, which brands? | EW1: C12-Other-tobacco-advert-evidence: add photo Evidence of OUTDOOR advertisements | EX1: C12-Other-tobacco-advert-evidence: add photo Evidence of OUTDOOR advertisements_URL | EY1: C13: Special promotions or discounts offered on purchase of tobacco products | EZ1: If Yes, add photo Evidence | FA1: If Yes, add photo Evidence _URL | FB1: If Yes, provide details | FC1: C14: Any giveaways/gifts associated with tobacco products | FD1: add photo Evidence | FE1: add photo Evidence _URL | FF1: If Yes, provide details | FG1: C15: Is the store located within 50m of an educational institution | FH1: C16: Were you able to complete the observation? | FI1: C17: Reason for incompletion. | FJ1: C18: Additional comments (if any) | FK1: City/Tehsil | FL1: _id | FM1: _uuid | FN1: _submission_time | FO1: _validation_status | FP1: _notes | FQ1: _status | FR1: _submitted_by | FS1: __version__ | FT1: _tags | FU1: meta/rootUuid | FV1: _index
C2: 46131.636 | D2: Sahiwal 001 | E2: 46131 | F2: 15:08:00.000+05:00 | G2: 15:20:00.000+05:00 | H2: Ashfaq Ahmed Rao | I2: Sahiwal Division | J2: Sahiwal | K2: Sahiwal | L2: 30.712628 73.055794 123 82.5 | M2: 30.712628 | N2: 73.055794 | O2: 123 | P2: 82.5 | Q2: Urban | R2: On Board Daewoo Bus | S2: Public Service Vehicle (PSV) | BW2: other | BX2: Daewoo bus sahiwal to faisalabad | BY2: Daewoo bus | BZ2: Sahiwal to faisalabad | CA2: No | CB2: No | CC2: No | CD2: No | CF2: Does not apply / no one using tobacco or nicotine products | CG2: 0 | CH2: 0 | CI2: 0 | CJ2: 0 | CK2: 0 | CL2: 0 | CM2: 1 | CN2: 0 | CP2: Does not apply / no one smoking | CQ2: No | CT2: No | CW2: No | CX2: No | CY2: Yes | CZ2: Yes | DB2: Daewoo is a well disciplined company but conductor was quite unaware of TC laws. | FL2: 729311753 | FM2: ed50e636-4f87-4e82-a888-13da994b8282 | FN2: 46131.427 | FQ2: submitted_via_web | FS2: vjiNwcPYvtjoD8cL5yiJdz | FU2: uuid:ed50e636-4f87-4e82-a888-13da994b8282 | FV2: 1
B3: 46131.636 | C3: 46131.649 | D3: Sahiwal 002 | E3: 46131 | F3: 15:22:00.000+05:00 | G3: 15:35:00.000+05:00 | H3: Ashfaq Ahmed Rao | I3: Sahiwal Division | J3: Sahiwal | K3: Sahiwal | L3: 30.647913 73.095845 131.00001525878906 31.024999618530273 | M3: 30.647913 | N3: 73.095845 | O3: 131.00002 | P3: 31.025 | Q3: Urban | R3: Daewoo Bus terminal | S3: Public place | T3: Transport Terminal (Bus terminal) | U3: Listed Venue | V3: 1 | W3: 0 | X3: Daewoo Bus terminal | Y3: Yes( add photo evidence) | Z3: 20260419_152705-15_27_30.jpg | AA3: https://kf.kobotoolbox.org/api/v2/assets/a7B4UGoSq7bg72YxNv837d/data/729322035/attachments/attggMx9uX6AD9pUkDESpzZm/ | AB3: 2 | AC3: No | AE3: No | AG3: Yes | AH3: Yes | AI3: No | AJ3: Does not apply / no one using tobacco or nicotine products | AK3: 0 | AL3: 0 | AM3: 0 | AN3: 0 | AO3: 0 | AP3: 0 | AQ3: 1 | AR3: 0 | AT3: Does not apply / no one using tobacco or nicotine products | AU3: No | AX3: No | BA3: No | BD3: No | BT3: Yes | BV3: Daewoo is a well established terminal. | FL3: 729322035 | FM3: 235bab69-dd8f-4594-9f19-e661437d2179 | FN3: 46131.441 | FQ3: submitted_via_web | FS3: vjiNwcPYvtjoD8cL5yiJdz | FU3: uuid:235bab69-dd8f-4594-9f19-e661437d2179 | FV3: 2
B4: 46131.649 | C4: 46131.657 | D4: Sahiwal 003 | E4: 46131 | F4: 15:39:00.000+05:00 | G4: 15:50:00.000+05:00 | H4: Ashfaq Ahmed Rao | I4: Sahiwal Division | J4: Sahiwal | K4: Sahiwal | L4: 30.649059 73.099694 130.60000610351562 14.022000312805176 | M4: 30.649059 | N4: 73.099694 | O4: 130.60001 | P4: 14.022 | Q4: Urban | R4: Faisal Movers Bus terminal | S4: Public place | T4: Transport Terminal (Bus terminal) | U4: Listed Venue | V4: 1 | W4: 0 | X4: Faisal Movers | Y4: No | AC4: No | AE4: Yes | AF4: 3 | AG4: Yes | AH4: Yes | AI4: No | AJ4: Cigarette | AK4: 1 | AL4: 0 | AM4: 0 | AN4: 0 | AO4: 0 | AP4: 0 | AQ4: 0 | AR4: 0 | AT4: Yes | AU4: No | AX4: No | BA4: No | BD4: No | BT4: Yes | FL4: 729329290 | FM4: c1438d41-bd27-4ca3-8d49-cdb03c35bbad | FN4: 46131.449 | FQ4: submitted_via_web | FS4: vjiNwcPYvtjoD8cL5yiJdz | FU4: uuid:c1438d41-bd27-4ca3-8d49-cdb03c35bbad | FV4: 3
B5: 46131.657 | C5: 46131.805 | D5: Sahiwal 004 | E5: 46131 | F5: 19:10:00.000+05:00 | G5: 19:25:00.000+05:00 | H5: Ashfaq Ahmed Rao | I5: Sahiwal Division | J5: Sahiwal | K5: Sahiwal | L5: 30.673535 73.108809 134.20001220703125 15.222999572753906 | M5: 30.673535 | N5: 73.108809 | O5: 134.20001 | P5: 15.223 | Q5: Urban | R5: Nomnosh Restaurant | S5: Public place | T5: Eatery ( Restaurant) | U5: Listed Venue | V5: 1 | W5: 0 | X5: Nomnosh Restaurant | Y5: Yes( add photo evidence) | Z5: 20260419_191524-19_15_37.jpg | AA5: https://kf.kobotoolbox.org/api/v2/assets/a7B4UGoSq7bg72YxNv837d/data/729448613/attachments/attekpyUWxQ3Zo7pEFaYiD58/ | AB5: 1 | AC5: No | AE5: No | AG5: Yes | AH5: Yes | AI5: Yes | AJ5: Does not apply / no one using tobacco or nicotine products | AK5: 0 | AL5: 0 | AM5: 0 | AN5: 0 | AO5: 0 | AP5: 0 | AQ5: 1 | AR5: 0 | AT5: Does not apply / no one using tobacco or nicotine products | AU5: No | AX5: No | BA5: No | BD5: No | BT5: Yes | BV5: No one allows to smoke or vape within premises. | FL5: 729448613 | FM5: 987191d7-ddc4-451f-85ae-44975b221227 | FN5: 46131.597 | FQ5: submitted_via_web | FS5: vjiNwcPYvtjoD8cL5yiJdz | FU5: uuid:987191d7-ddc4-451f-85ae-44975b221227 | FV5: 4
B6: 46131.805 | C6: 46131.815 | D6: Sahiwal 005 | E6: 46131 | F6: 19:29:00.000+05:00 | G6: 19:40:00.000+05:00 | H6: Ashfaq Ahmed Rao | I6: Sahiwal Division | J6: Sahiwal | K6: Sahiwal | L6: 30.673768 73.107722 129.8000030517578 12.095000267028809 | M6: 30.673768 | N6: 73.107722 | O6: 129.8 | P6: 12.095 | Q6: Urban | R6: KR Restaurant | S6: Public place | T6: Eatery ( Restaurant) | U6: Listed Venue | V6: 1 | W6: 0 | X6: KR Restaurant | Y6: No | AC6: No | AE6: No | AG6: Yes | AH6: Yes | AI6: Yes | AJ6: Does not apply / no one using tobacco or nicotine products | AK6: 0 | AL6: 0 | AM6: 0 | AN6: 0 | AO6: 0 | AP6: 0 | AQ6: 1 | AR6: 0 | AT6: Does not apply / no one using tobacco or nicotine products | AU6: No | AX6: No | BA6: No | BD6: No | BT6: Yes | FL6: 729456370 | FM6: ef8eeff1-d76a-45b2-af4a-3d4f55c92482 | FN6: 46131.607 | FQ6: submitted_via_web | FS6: vjiNwcPYvtjoD8cL5yiJdz | FU6: uuid:ef8eeff1-d76a-45b2-af4a-3d4f55c92482 | FV6: 5
B7: 46131.815 | C7: 46131.831 | D7: Sahiwal 006 | E7: 46131 | F7: 19:50:00.000+05:00 | G7: 19:59:00.000+05:00 | H7: Ashfaq Ahmed Rao | I7: Sahiwal Division | J7: Sahiwal | K7: Sahiwal | L7: 30.671369 73.109928 130.90000915527344 92.9000015258789 | M7: 30.671369 | N7: 73.109928 | O7: 130.90001 | P7: 92.900002 | Q7: Urban | R7: 14th Street | S7: Public place | T7: Eatery ( Restaurant) | U7: Listed Venue | V7: 1 | W7: 0 | X7: 14th Street | Y7: No | AC7: No | AE7: No | AG7: Yes | AH7: Yes | AI7: Yes | AJ7: Does not apply / no one using tobacco or nicotine products | AK7: 0 | AL7: 0 | AM7: 0 | AN7: 0 | AO7: 0 | AP7: 0 | AQ7: 1 | AR7: 0 | AT7: Does not apply / no one using tobacco or nicotine products | AU7: No | AX7: No | BA7: No | BD7: No | BT7: Yes | FL7: 729469151 | FM7: 81e01791-5ddb-4b0b-954b-37bfbc7eaa2c | FN7: 46131.623 | FQ7: submitted_via_web | FS7: vjiNwcPYvtjoD8cL5yiJdz | FU7: uuid:81e01791-5ddb-4b0b-954b-37bfbc7eaa2c | FV7: 6
B8: 46131.831 | C8: 46131.841 | D8: Sahiwal 007 | E8: 46131 | F8: 20:04:00.000+05:00 | G8: 20:17:00.000+05:00 | H8: Ashfaq Ahmed Rao | I8: Sahiwal Division | J8: Sahiwal | K8: Sahiwal | L8: 30.669103 73.109867 131.10000610351562 16.236000061035156 | M8: 30.669103 | N8: 73.109867 | O8: 131.10001 | P8: 16.236 | Q8: Urban | R8: TenDoz Restaurant | S8: Public place | T8: Eatery ( Restaurant) | U8: Listed Venue | V8: 1 | W8: 0 | X8: TenDoz | Y8: No | AC8: No | AE8: No | AG8: Yes | AH8: Yes | AI8: Yes | AJ8: Does not apply / no one using tobacco or nicotine products | AK8: 0 | AL8: 0 | AM8: 0 | AN8: 0 | AO8: 0 | AP8: 0 | AQ8: 1 | AR8: 0 | AT8: Does not apply / no one using tobacco or nicotine products | AU8: No | AX8: No | BA8: No | BD8: No | BT8: Yes | BV8: Staff was totally aware and knowledgeable regarding above questions. | FL8: 729477083 | FM8: e9253ee9-20ef-47e3-9927-b9b7c8b31851 | FN8: 46131.633 | FQ8: submitted_via_web | FS8: vjiNwcPYvtjoD8cL5yiJdz | FU8: uuid:e9253ee9-20ef-47e3-9927-b9b7c8b31851 | FV8: 7
B9: 46131.841 | C9: 46131.854 | D9: Sahiwal 008 | E9: 46131 | F9: 20:22:00.000+05:00 | G9: 20:35:00.000+05:00 | H9: Ashfaq Ahmed Rao | I9: Sahiwal Division | J9: Sahiwal | K9: Sahiwal | L9: 30.67211 73.113588 130.50001525878906 20 | M9: 30.67211 | N9: 73.113588 | O9: 130.50002 | P9: 20 | Q9: Urban | R9: The Oven Piza | S9: Public place | T9: Eatery ( Restaurant) | U9: Listed Venue | V9: 1 | W9: 0 | X9: The Oven Pizza | Y9: Yes( add photo evidence) | Z9: 20260419_202714-20_27_51.jpg | AA9: https://kf.kobotoolbox.org/api/v2/assets/a7B4UGoSq7bg72YxNv837d/data/729486742/attachments/attQmWurb2xnk5vQYUXcBZP8/ | AB9: 1 | AC9: No | AE9: No | AG9: Yes | AH9: Yes | AI9: Yes | AJ9: Does not apply / no one using tobacco or nicotine products | AK9: 0 | AL9: 0 | AM9: 0 | AN9: 0 | AO9: 0 | AP9: 0 | AQ9: 1 | AR9: 0 | AT9: Does not apply / no one using tobacco or nicotine products | AU9: No | AX9: No | BA9: No | BD9: No | BT9: Yes | FL9: 729486742 | FM9: 32a5cd2c-460b-47a4-931b-210d71ad0b2d | FN9: 46131.645 | FQ9: submitted_via_web | FS9: vjiNwcPYvtjoD8cL5yiJdz | FU9: uuid:32a5cd2c-460b-47a4-931b-210d71ad0b2d | FV9: 8
B10: 46131.854 | C10: 46131.862 | D10: Sahiwal 009 | E10: 46131 | F10: 20:35:00.000+05:00 | G10: 20:48:00.000+05:00 | H10: Ashfaq Ahmed Rao | I10: Sahiwal Division | J10: Sahiwal | K10: Sahiwal | L10: 30.669333 73.112147 131.70001220703125 11.572999954223633 | M10: 30.669333 | N10: 73.112147 | O10: 131.70001 | P10: 11.573 | Q10: Urban | R10: Cheezious | S10: Public place | T10: Eatery ( Restaurant) | U10: Listed Venue | V10: 1 | W10: 0 | X10: Cheezious Restaurant | Y10: Yes( add photo evidence) | Z10: 20260419_203831-20_39_4.jpg | AA10: https://kf.kobotoolbox.org/api/v2/assets/a7B4UGoSq7bg72YxNv837d/data/729493008/attachments/attTaqdJGpRepv7S32meV9Xh/ | AB10: 1 | AC10: No | AE10: No | AG10: Yes | AH10: Yes | AI10: Yes | AJ10: Does not apply / no one using tobacco or nicotine products | AK10: 0 | AL10: 0 | AM10: 0 | AN10: 0 | AO10: 0 | AP10: 0 | AQ10: 1 | AR10: 0 | AT10: Does not apply / no one using tobacco or nicotine products | AU10: No | AX10: No | BA10: No | BD10: No | BT10: Yes | FL10: 729493008 | FM10: 6993718c-e9eb-4af4-88f9-a32b38db888a | FN10: 46131.653 | FQ10: submitted_via_web | FS10: vjiNwcPYvtjoD8cL5yiJdz | FU10: uuid:6993718c-e9eb-4af4-88f9-a32b38db888a | FV10: 9
B11: 46131.862 | C11: 46131.905 | D11: Sahiwal 10 | E11: 46131 | F11: 21:38:00.000+05:00 | G11: 21:55:00.000+05:00 | H11: Ashfaq Ahmed Rao | I11: Sahiwal Division | J11: Sahiwal | K11: Sahiwal | L11: 30.678097 73.0888 127.4000015258789 18.014999389648438 | M11: 30.678097 | N11: 73.0888 | O11: 127.4 | P11: 18.014999 | Q11: Urban | R11: Spice Villa | S11: Public place | T11: Eatery ( Restaurant) | U11: Listed Venue | V11: 1 | W11: 0 | X11: Spice Villa | Y11: Yes( add photo evidence) | Z11: 20260419_214050-21_41_0.jpg | AA11: https://kf.kobotoolbox.org/api/v2/assets/a7B4UGoSq7bg72YxNv837d/data/729526431/attachments/attHDaZGttmRVxddMD2Ba7Mo/ | AB11: 1 | AC11: No | AE11: No | AG11: No | AH11: Yes | AI11: Yes | AJ11: Does not apply / no one using tobacco or nicotine products | AK11: 0 | AL11: 0 | AM11: 0 | AN11: 0 | AO11: 0 | AP11: 0 | AQ11: 1 | AR11: 0 | AT11: Does not apply / no one using tobacco or nicotine products | AU11: No | AX11: No | BA11: No | BD11: No | BT11: Yes | FL11: 729526431 | FM11: 7c9eb1ed-dcab-401e-836b-d7c958e26c98 | FN11: 46131.697 | FQ11: submitted_via_web | FS11: vjiNwcPYvtjoD8cL5yiJdz | FU11: uuid:7c9eb1ed-dcab-401e-836b-d7c958e26c98 | FV11: 10
B12: 46128.619 | C12: 46132.341 | D12: Jhang0079 | E12: 46128 | F12: 15:13:00.000+05:00 | G12: 15:28:00.000+05:00 | H12: Tahir Mustafa | I12: Faisalabad Division | J12: Jhang | K12: Jhang | L12: 31.260871 72.352786 115.5999984741211 21.773000717163086 | M12: 31.260871 | N12: 72.352786 | O12: 115.6 | P12: 21.773001 | Q12: Urban | R12: Town guest house | S12: Public place | T12: Accommodation - Guesthouse | U12: Listed Venue | V12: 1 | W12: 0 | X12: Town guest house | Y12: No | AC12: No | AE12: No | AG12: Yes | AH12: Yes | AI12: Yes | AJ12: Does not apply / no one using tobacco or nicotine products | AK12: 0 | AL12: 0 | AM12: 0 | AN12: 0 | AO12: 0 | AP12: 0 | AQ12: 1 | AR12: 0 | AT12: Does not apply / no one using tobacco or nicotine products | AU12: No | AX12: No | BA12: No | BD12: No | BT12: Yes | BV12: Al Madina guest house map ma town guest tha TU liya ma na town guest Kya ha | FL12: 729957908 | FM12: c8f2d82c-001c-4dd6-93da-d2a8f57ad3a4 | FN12: 46132.328 | FQ12: submitted_via_web | FS12: vjiNwcPYvtjoD8cL5yiJdz | FU12: uuid:c8f2d82c-001c-4dd6-93da-d2a8f57ad3a4 | FV12: 11
B13: 46127.43 | C13: 46132.536 | D13: 0051 | E13: 46127 | F13: 11:20:00.000+05:00 | G13: 11:35:00.000+05:00 | H13: Tahir Mustafa | I13: Faisalabad Division | J13: Jhang | K13: Jhang | L13: 31.262447 72.330422 112.69999694824219 13.836000442504883 | M13: 31.262447 | N13: 72.330422 | O13: 112.7 | P13: 13.836 | Q13: Urban | R13: Chief Executive Office District Health Authority Jhang - Gojra Rd, Jhan | S13: Public place | T13: Government Offices - District Authorities Offices e.g. (Health, Education, DC Office, C & W Office, Social Welfare etc.) | U13: Listed Venue | V13: 1 | W13: 0 | X13: Chief Executive Office District Health Authority Jhang - Gojra Rd, Jhan | Y13: No | AC13: No | AE13: No | AG13: Yes | AH13: Yes | AI13: Yes | AJ13: Does not apply / no one using tobacco or nicotine products | AK13: 0 | AL13: 0 | AM13: 0 | AN13: 0 | AO13: 0 | AP13: 0 | AQ13: 1 | AR13: 0 | AT13: No | AU13: Yes ( add photo Evidence) | AV13: 1000074957-11_33_11.jpg | AW13: https://kf.kobotoolbox.org/api/v2/assets/a7B4UGoSq7bg72YxNv837d/data/729957928/attachments/attQqiFcFBKHZNXSE56A7oCR/ | AX13: Yes (add photo Evidence) | AY13: 1000074956-11_31_27.jpg | AZ13: https://kf.kobotoolbox.org/api/v2/assets/a7B4UGoSq7bg72YxNv837d/data/729957928/attachments/attErBzjuf28RHZRnZuFFuZK/ | BA13: No | BD13: No | BT13: Yes | BV13: Cooperative staff | FL13: 729957928 | FM13: 6081b523-71ce-42c4-b0af-2da5a35a61fc | FN13: 46132.328 | FQ13: submitted_via_web | FS13: vjiNwcPYvtjoD8cL5yiJdz | FU13: uuid:6081b523-71ce-42c4-b0af-2da5a35a61fc | FV13: 12
B14: 46127.488 | C14: 46132.537 | D14: Jhang 0052 | E14: 46128 | F14: 11:48:00.000+05:00 | G14: 12:05:00.000+05:00 | H14: Tahir Mustafa | I14: Faisalabad Division | J14: Jhang | K14: Jhang | L14: 31.279195 72.354852 113.5999984741211 0.9459999799728394 | M14: 31.279195 | N14: 72.354852 | O14: 113.6 | P14: 0.94599998 | Q14: Urban | R14: Expire college group of jhang | S14: Public place | T14: Entertainment/sports venue - Cinema | U14: Listed Venue Unlisted Venue | V14: 1 | W14: 1 | X14: Aspir college group jhang | Y14: No | AC14: No | AE14: No | AG14: Yes | AH14: Yes | AI14: Yes | AJ14: Does not apply / no one using tobacco or nicotine products | AK14: 0 | AL14: 0 | AM14: 0 | AN14: 0 | AO14: 0 | AP14: 0 | AQ14: 1 | AR14: 0 | AT14: Does not apply / no one using tobacco or nicotine products | AU14: No | AX14: No | BA14: No | BD14: No | BT14: Yes | FL14: 729958274 | FM14: bd7acc68-5518-48e9-adfd-33467a217a76 | FN14: 46132.328 | FQ14: submitted_via_web | FS14: vjiNwcPYvtjoD8cL5yiJdz | FU14: uuid:bd7acc68-5518-48e9-adfd-33467a217a76 | FV14: 13
B15: 46127.524 | C15: 46132.537 | D15: Jhang 0053 | E15: 46127 | F15: 12:35:00.000+05:00 | G15: 12:50:00.000+05:00 | H15: Tahir Mustafa | I15: Faisalabad Division | J15: Jhang | K15: Jhang | L15: 31.279135 72.313275 115.0999984741211 32.45100021362305 | M15: 31.279135 | N15: 72.313275 | O15: 115.1 | P15: 32.451 | Q15: Urban | R15: Municipal Corporation Circular Rd, Madina Colony, Jhang | S15: Public place | T15: Government Offices - District court/ Bar council | U15: Listed Venue | V15: 1 | W15: 0 | X15: Municipal Corporation Circular Rd, Madina Colony, Jhang | Y15: No | AC15: Yes | AD15: 1 | AE15: No | AG15: Yes | AH15: No | AI15: No | AJ15: Cigarette | AK15: 1 | AL15: 0 | AM15: 0 | AN15: 0 | AO15: 0 | AP15: 0 | AQ15: 0 | AR15: 0 | AT15: No | AU15: Yes ( add photo Evidence) | AV15: 1000074964-12_41_27.jpg | AW15: https://kf.kobotoolbox.org/api/v2/assets/a7B4UGoSq7bg72YxNv837d/data/729958722/attachments/attdTwZpgLCufAc3XqPDPTPz/ | AX15: No | BA15: No | BD15: No | BT15: Yes | FL15: 729958722 | FM15: 7ae4a41e-e745-44e2-82dd-55727f6a9143 | FN15: 46132.329 | FQ15: submitted_via_web | FS15: vjiNwcPYvtjoD8cL5yiJdz | FU15: uuid:7ae4a41e-e745-44e2-82dd-55727f6a9143 | FV15: 14
B16: 46127.552 | C16: 46132.537 | D16: Jhang 0054 | E16: 46127 | F16: 13:15:00.000+05:00 | G16: 13:30:00.000+05:00 | H16: Tahir Mustafa | I16: Faisalabad Division | J16: Jhang | K16: Jhang | L16: 31.277981 72.32404 123.77 1.4390000104904175 | M16: 31.277981 | N16: 72.32404 | O16: 123.77 | P16: 1.439 | Q16: Urban | R16: Punjab Food Authority Jhang Sadar | S16: Public place | T16: Government Offices - District Authorities Offices e.g. (Health, Education, DC Office, C & W Office, Social Welfare etc.) | U16: Listed Venue | V16: 1 | W16: 0 | X16: Punjab Food Authority Jhang Sadar | Y16: Yes( add photo evidence) | Z16: 1000074971-13_16_49.jpg | AA16: https://kf.kobotoolbox.org/api/v2/assets/a7B4UGoSq7bg72YxNv837d/data/729958993/attachments/attzL2764tSCcDhaQXSXVYxo/ | AB16: 1 | AC16: No | AE16: No | AG16: Yes | AH16: Yes | AI16: Yes | AJ16: Does not apply / no one using tobacco or nicotine products | AK16: 0 | AL16: 0 | AM16: 0 | AN16: 0 | AO16: 0 | AP16: 0 | AQ16: 1 | AR16: 0 | AT16: Does not apply / no one using tobacco or nicotine products | AU16: Yes ( add photo Evidence) | AV16: 1000074972-13_20_23.jpg | AW16: https://kf.kobotoolbox.org/api/v2/assets/a7B4UGoSq7bg72YxNv837d/data/729958993/attachments/attAwsRPSSoszhV74iJ33bVk/ | AX16: No | BA16: Yes (add photo Evidence) | BB16: 1000074974-13_24_2.jpg | BC16: https://kf.kobotoolbox.org/api/v2/assets/a7B4UGoSq7bg72YxNv837d/data/729958993/attachments/attnB39MHzPAofL28DgJF6pK/ | BD16: Yes (add photo Evidence) | BE16: 1000074973-13_23_10.jpg | BF16: https://kf.kobotoolbox.org/api/v2/assets/a7B4UGoSq7bg72YxNv837d/data/729958993/attachments/attnycw62XjaY7iMniXfsDrL/ | BG16: Does not apply / no one using tobacco or nicotine products | BH16: 0 | BI16: 0 | BJ16: 0 | BK16: 0 | BL16: 0 | BM16: 0 | BN16: 1 | BO16: 0 | BQ16: TVA not enforced in the district | BT16: Yes | FL16: 729958993 | FM16: 1725fbef-afb9-4b4f-b2a1-e333496e7f33 | FN16: 46132.329 | FQ16: submitted_via_web | FS16: vjiNwcPYvtjoD8cL5yiJdz | FU16: uuid:1725fbef-afb9-4b4f-b2a1-e333496e7f33 | FV16: 15
B17: 46127.578 | C17: 46132.537 | D17: Jhang 0055 | E17: 46127 | F17: 13:52:00.000+05:00 | G17: 14:08:00.000+05:00 | H17: Tahir Mustafa | I17: Faisalabad Division | J17: Jhang | K17: Jhang | L17: 31.27184 72.318195 115 16.93600082397461 | M17: 31.27184 | N17: 72.318195 | O17: 115 | P17: 16.936001 | Q17: Urban | R17: Habib Bank Limited (HBL) Shaheed Rd, | S17: Public place | T17: Bank - private | U17: Listed Venue | V17: 1 | W17: 0 | X17: Habib Bank Limited (HBL) Shaheed Rd, | Y17: No | AC17: No | AE17: No | AG17: Yes | AH17: Yes | AI17: No | AJ17: Does not apply / no one using tobacco or nicotine products | AK17: 0 | AL17: 0 | AM17: 0 | AN17: 0 | AO17: 0 | AP17: 0 | AQ17: 1 | AR17: 0 | AT17: No | AU17: No | AX17: No | BA17: No | BD17: No | BT17: Yes | FL17: 729959159 | FM17: efadde04-c949-4814-8daa-d8f1c10ee3da | FN17: 46132.329 | FQ17: submitted_via_web | FS17: vjiNwcPYvtjoD8cL5yiJdz | FU17: uuid:efadde04-c949-4814-8daa-d8f1c10ee3da | FV17: 16
B18: 46127.604 | C18: 46132.537 | D18: Jhang0056 | E18: 46127 | F18: 14:29:00.000+05:00 | G18: 14:45:00.000+05:00 | H18: Tahir Mustafa | I18: Faisalabad Division | J18: Jhang | K18: Jhang | L18: 31.268795 72.316982 115.19999694824219 12.597999572753906 | M18: 31.268795 | N18: 72.316982 | O18: 115.2 | P18: 12.598 | Q18: Urban | R18: Nighat Medical Complex Gojra Rd, near Post Office | S18: Public place | T18: Health Facility - Hospital | U18: Listed Venue | V18: 1 | W18: 0 | X18: Nighat Medical Complex Gojra Rd, near Post Office | Y18: Yes( add photo evidence) | Z18: 1000074977-14_43_44.jpg | AA18: https://kf.kobotoolbox.org/api/v2/assets/a7B4UGoSq7bg72YxNv837d/data/729959559/attachments/attAhyxwNri4LKK5kLaALrSy/ | AB18: 1 | AC18: No | AE18: No | AG18: Yes | AH18: Yes | AI18: Yes | AJ18: Does not apply / no one using tobacco or nicotine products | AK18: 0 | AL18: 0 | AM18: 0 | AN18: 0 | AO18: 0 | AP18: 0 | AQ18: 1 | AR18: 0 | AT18: Does not apply / no one using tobacco or nicotine products | AU18: No | AX18: No | BA18: No | BD18: No | BT18: Yes | FL18: 729959559 | FM18: 3ef1fc9a-01eb-4133-a224-4d3c3fe1632f | FN18: 46132.329 | FQ18: submitted_via_web | FS18: vjiNwcPYvtjoD8cL5yiJdz | FU18: uuid:3ef1fc9a-01eb-4133-a224-4d3c3fe1632f | FV18: 17
B19: 46127.624 | C19: 46132.538 | D19: Jhang 0057 | E19: 46127 | F19: 14:58:00.000+05:00 | G19: 15:12:00.000+05:00 | H19: Tahir Mustafa | I19: Faisalabad Division | J19: Jhang | K19: Jhang | L19: 31.261565 72.306956 116.58 10.428999900817871 | M19: 31.261565 | N19: 72.306956 | O19: 116.58 | P19: 10.429 | Q19: Urban | R19: Iqbal Memorial Hospital Bhakkar Rd, Jhang Sadar | S19: Public place | T19: Health Facility - Hospital | U19: Listed Venue | V19: 1 | W19: 0 | X19: Iqbal Memorial Hospital Bhakkar Rd, Jhang Sadar | Y19: Yes( add photo evidence) | Z19: 1000074982-15_3_7.jpg | AA19: https://kf.kobotoolbox.org/api/v2/assets/a7B4UGoSq7bg72YxNv837d/data/729959818/attachments/attWHi2rLujorkU4h5nMhNep/ | AB19: 1 | AC19: No | AE19: No | AG19: Yes | AH19: Yes | AI19: Yes | AJ19: Does not apply / no one using tobacco or nicotine products | AK19: 0 | AL19: 0 | AM19: 0 | AN19: 0 | AO19: 0 | AP19: 0 | AQ19: 1 | AR19: 0 | AT19: Does not apply / no one using tobacco or nicotine products | AU19: No | AX19: No | BA19: No | BD19: No | BT19: Yes | FL19: 729959818 | FM19: f41f2fd5-90f4-426d-8483-88b10a215bbf | FN19: 46132.329 | FQ19: submitted_via_web | FS19: vjiNwcPYvtjoD8cL5yiJdz | FU19: uuid:f41f2fd5-90f4-426d-8483-88b10a215bbf | FV19: 18
B20: 46127.663 | C20: 46132.538 | D20: Jhang0058 | E20: 46127 | F20: 15:55:00.000+05:00 | G20: 16:10:00.000+05:00 | H20: Tahir Mustafa | I20: Faisalabad Division | J20: Jhang | K20: Jhang | L20: 31.274381 72.316068 115.80000305175781 17.81599998474121 | M20: 31.274381 | N20: 72.316068 | O20: 115.8 | P20: 17.816 | Q20: Rural | R20: Telenor Pakistan Franchise Shaheed Rd, Jhang Private Offices 2 | S20: Public place | T20: Bank - private | U20: Listed Venue | V20: 1 | W20: 0 | X20: Telenor Pakistan Franchise Shaheed Rd, Jhang Private Offices 2 | Y20: No | AC20: No | AE20: No | AG20: Yes | AH20: Yes | AI20: Yes | AJ20: Does not apply / no one using tobacco or nicotine products | AK20: 0 | AL20: 0 | AM20: 0 | AN20: 0 | AO20: 0 | AP20: 0 | AQ20: 1 | AR20: 0 | AT20: Does not apply / no one using tobacco or nicotine products | AU20: No | AX20: No | BA20: No | BD20: No | BT20: Yes | FL20: 729960840 | FM20: e7416257-7c09-4d1d-9834-81b48e09f794 | FN20: 46132.33 | FQ20: submitted_via_web | FS20: vjiNwcPYvtjoD8cL5yiJdz | FU20: uuid:e7416257-7c09-4d1d-9834-81b48e09f794 | FV20: 19
B21: 46127.682 | C21: 46132.538 | D21: Jhang 0059 | E21: 46127 | F21: 16:21:00.000+05:00 | G21: 16:37:00.000+05:00 | H21: Tahir Mustafa | I21: Faisalabad Division | J21: Jhang | K21: Jhang | L21: 31.262903 72.335495 115.4000015258789 21.83799934387207 | M21: 31.262903 | N21: 72.335495 | O21: 115.4 | P21: 21.837999 | Q21: Urban | R21: Meet And Eat Opp DHQ Hospital Jhang Gojra Rd | S21: Public place | T21: Eatery ( Restaurant) | U21: Listed Venue | V21: 1 | W21: 0 | X21: Meet And Eat Opp DHQ Hospital Jhang Gojra Rd | Y21: No | AC21: No | AE21: No | AG21: Yes | AH21: Yes | AI21: Yes | AJ21: Does not apply / no one using tobacco or nicotine products | AK21: 0 | AL21: 0 | AM21: 0 | AN21: 0 | AO21: 0 | AP21: 0 | AQ21: 1 | AR21: 0 | AT21: Does not apply / no one using tobacco or nicotine products | AU21: No | AX21: No | BA21: No | BD21: No | BT21: Yes | FL21: 729961044 | FM21: 3f8b283a-bd5b-4871-8f87-097bc60c414d | FN21: 46132.33 | FQ21: submitted_via_web | FS21: vjiNwcPYvtjoD8cL5yiJdz | FU21: uuid:3f8b283a-bd5b-4871-8f87-097bc60c414d | FV21: 20
B22: 46127.702 | C22: 46132.538 | D22: Jhang 0060 | E22: 46127 | F22: 17:15:00.000+05:00 | G22: 17:30:00.000+05:00 | H22: Tahir Mustafa | I22: Faisalabad Division | J22: Jhang | K22: Jhang | L22: 31.268155 72.345802 78.42 1.784999966621399 | M22: 31.268155 | N22: 72.345802 | O22: 78.42 | P22: 1.785 | Q22: Urban | R22: Sakina Hospital Dar-ul-Sakina Rd, Ghaziabad, Jhang | S22: Public place | T22: Health Facility - Hospital | U22: Listed Venue | V22: 1 | W22: 0 | X22: Sakina Hospital Dar-ul-Sakina Rd, Ghaziabad, Jhang | Y22: Yes( add photo evidence) | Z22: 1000075023-17_26_41.jpg | AA22: https://kf.kobotoolbox.org/api/v2/assets/a7B4UGoSq7bg72YxNv837d/data/729961277/attachments/attr6A2SWaG37uqQmLsEzHy5/ | AB22: 1 | AC22: No | AE22: No | AG22: Yes | AH22: Yes | AI22: Yes | AJ22: Does not apply / no one using tobacco or nicotine products | AK22: 0 | AL22: 0 | AM22: 0 | AN22: 0 | AO22: 0 | AP22: 0 | AQ22: 1 | AR22: 0 | AT22: Does not apply / no one using tobacco or nicotine products | AU22: No | AX22: No | BA22: No | BD22: No | BT22: Yes | FL22: 729961277 | FM22: 28ec7e7a-907a-4cf3-ac41-88a04d877eb4 | FN22: 46132.33 | FQ22: submitted_via_web | FS22: vjiNwcPYvtjoD8cL5yiJdz | FU22: uuid:28ec7e7a-907a-4cf3-ac41-88a04d877eb4 | FV22: 21
B23: 46127.747 | C23: 46132.539 | D23: Jhang 0061 | E23: 46127 | F23: 17:56:00.000+05:00 | G23: 18:11:00.000+05:00 | H23: Tahir Mustafa | I23: Faisalabad Division | J23: Jhang | K23: Jhang | L23: 31.27016 72.317782 113.69999694824219 20 | M23: 31.27016 | N23: 72.317782 | O23: 113.7 | P23: 20 | Q23: Urban | R23: The hot spot cafe and restaurants | S23: Public place | T23: Eatery ( Restaurant) | U23: Listed Venue | V23: 1 | W23: 0 | X23: The hot spot cafe and restaurants | Y23: No | AC23: No | AE23: No | AG23: Yes | AH23: No | AI23: No | AJ23: Does not apply / no one using tobacco or nicotine products | AK23: 0 | AL23: 0 | AM23: 0 | AN23: 0 | AO23: 0 | AP23: 0 | AQ23: 1 | AR23: 0 | AT23: Does not apply / no one using tobacco or nicotine products | AU23: No | AX23: No | BA23: No | BD23: No | BT23: Yes | FL23: 729961744 | FM23: 3427bdd2-120c-4314-b5ef-1edbb59f523c | FN23: 46132.33 | FQ23: submitted_via_web | FS23: vjiNwcPYvtjoD8cL5yiJdz | FU23: uuid:3427bdd2-120c-4314-b5ef-1edbb59f523c | FV23: 22
B24: 46127.813 | C24: 46132.539 | D24: Jhang 0062 | E24: 46127 | F24: 19:35:00.000+05:00 | G24: 19:50:00.000+05:00 | H24: Tahir Mustafa | I24: Faisalabad Division | J24: Jhang | K24: Jhang | L24: 31.277684 72.321064 114.80000305175781 24.851999282836914 | M24: 31.277684 | N24: 72.321064 | O24: 114.8 | P24: 24.851999 | Q24: Urban | R24: al jannat bakery | S24: Public place | T24: Eatery ( Bakery) | U24: Unlisted Venue | V24: 0 | W24: 1 | X24: Al jannat bakery | Y24: No | AC24: No | AE24: No | AG24: No | AH24: Yes | AI24: Yes | AJ24: Does not apply / no one using tobacco or nicotine products | AK24: 0 | AL24: 0 | AM24: 0 | AN24: 0 | AO24: 0 | AP24: 0 | AQ24: 1 | AR24: 0 | AT24: Does not apply / no one using tobacco or nicotine products | AU24: Yes ( add photo Evidence) | AV24: 1000075056-19_41_16.jpg | AW24: https://kf.kobotoolbox.org/api/v2/assets/a7B4UGoSq7bg72YxNv837d/data/729962050/attachments/att58Q7qxVkogZtx7RzFbAd6/ | AX24: Yes (add photo Evidence) | AY24: 1000075057-19_41_39.jpg | AZ24: https://kf.kobotoolbox.org/api/v2/assets/a7B4UGoSq7bg72YxNv837d/data/729962050/attachments/attMmB3pb3QG4FStoGiBqa6N/ | BA24: No | BD24: No | BT24: Yes | FL24: 729962050 | FM24: 95e833c7-0812-4681-9d52-842e64f54d57 | FN24: 46132.331 | FQ24: submitted_via_web | FS24: vjiNwcPYvtjoD8cL5yiJdz | FU24: uuid:95e833c7-0812-4681-9d52-842e64f54d57 | FV24: 23
B25: 46127.823 | C25: 46132.539 | D25: Jhang0063 | E25: 46127 | F25: 19:55:00.000+05:00 | G25: 20:10:00.000+05:00 | H25: Tahir Mustafa | I25: Faisalabad Division | J25: Jhang | K25: Jhang | L25: 31.276723 72.320416 115 18.354000091552734 | M25: 31.276723 | N25: 72.320416 | O25: 115 | P25: 18.354 | Q25: Urban | R25: Pso of jhang | S25: Retail outlet /Point of Sale (POS) | DC25: Fuel station | DE25: Pso of jhang | DF25: Ayub Chowk | DG25: No | DH25: Not Applicable/ No Young buyers visited | DI25: No | DL25: No | DP25: No | DT25: No | DW25: No | DX25: No | EA25: No | EE25: Yes | EF25: Capstan | EG25: 1000075070-19_56_49.jpg | EH25: https://kf.kobotoolbox.org/api/v2/assets/a7B4UGoSq7bg72YxNv837d/data/729962878/attachments/attNuj4aWvMr8n6QrsjazZmY/ | EI25: No | EM25: No | EQ25: No | EU25: No | EY25: No | FC25: No | FG25: Yes | FH25: Yes | FL25: 729962878 | FM25: 81ecf395-5223-4a18-bdd0-9c1114322db3 | FN25: 46132.331 | FQ25: submitted_via_web | FS25: vjiNwcPYvtjoD8cL5yiJdz | FU25: uuid:81ecf395-5223-4a18-bdd0-9c1114322db3 | FV25: 24
B26: 46128.255 | C26: 46132.54 | D26: Jhang0064 | E26: 46128 | F26: 06:06:00.000+05:00 | G26: 06:18:00.000+05:00 | H26: Tahir Mustafa | I26: Faisalabad Division | J26: Jhang | K26: Jhang | L26: 31.277014 72.320864 114.80000305175781 23.39299964904785 | M26: 31.277014 | N26: 72.320864 | O26: 114.8 | P26: 23.393 | Q26: Urban | R26: Abdul Majid panwala | S26: Retail outlet /Point of Sale (POS) | DC26: Tobacco shop | DE26: Abdul Majid panwala | DF26: Ayub Chowk | DG26: No | DH26: Not Applicable/ No Young buyers visited | DI26: No | DL26: No | DP26: No | DT26: No | DW26: Yes | DX26: Yes ( add photo evidence) | DY26: 1000075119-6_10_15.jpg | DZ26: https://kf.kobotoolbox.org/api/v2/assets/a7B4UGoSq7bg72YxNv837d/data/729963344/attachments/att6P7dBLtzPnHBdMFjRCwah/ | EA26: Yes | EB26: Capstan | EC26: 1000075119-6_10_31.jpg | ED26: https://kf.kobotoolbox.org/api/v2/assets/a7B4UGoSq7bg72YxNv837d/data/729963344/attachments/attjqK9bS8LDua3GPqoqVNWH/ | EE26: Yes | EF26: Capstan | EG26: 1000075119-6_10_44.jpg | EH26: https://kf.kobotoolbox.org/api/v2/assets/a7B4UGoSq7bg72YxNv837d/data/729963344/attachments/attLk2ZUxqHycuQACbMqRxeV/ | EI26: No | EM26: No | EQ26: Yes | ER26: Zyx | ES26: 1000075120-11_36_54.jpg | ET26: https://kf.kobotoolbox.org/api/v2/assets/a7B4UGoSq7bg72YxNv837d/data/729963344/attachments/attKWpqxzNpmHRtowptQmekf/ | EU26: Yes | EV26: Zyx | EW26: 1000075120-6_11_57.jpg | EX26: https://kf.kobotoolbox.org/api/v2/assets/a7B4UGoSq7bg72YxNv837d/data/729963344/attachments/attRWZj4wxaSmijKh2Zfjsc8/ | EY26: Yes ( add photo evidence) | EZ26: 1000075121-6_12_20.jpg | FA26: https://kf.kobotoolbox.org/api/v2/assets/a7B4UGoSq7bg72YxNv837d/data/729963344/attachments/attXdGBdZp3DPcoa86NsJrud/ | FB26: World no 1 | FC26: No | FG26: Yes | FH26: Yes | FL26: 729963344 | FM26: 898b69c6-4f10-4896-8047-e74ec02fac21 | FN26: 46132.331 | FQ26: submitted_via_web | FS26: vjiNwcPYvtjoD8cL5yiJdz | FU26: uuid:898b69c6-4f10-4896-8047-e74ec02fac21 | FV26: 25
B27: 46128.261 | C27: 46132.542 | D27: Jhang0065 | E27: 46128 | F27: 06:21:00.000+05:00 | G27: 06:26:00.000+05:00 | H27: Tahir Mustafa | I27: Faisalabad Division | J27: Jhang | K27: Jhang | L27: 31.282936 72.33188 111.0999984741211 77.5999984741211 | M27: 31.282936 | N27: 72.33188 | O27: 111.1 | P27: 77.599998 | Q27: Urban | R27: Sargodha road | S27: Public Service Vehicle (PSV) | BW27: other | BX27: Raksha | BY27: Raksha | BZ27: Sargodha road | CA27: No | CB27: No | CC27: No | CD27: No | CF27: Does not apply / no one using tobacco or nicotine products | CG27: 0 | CH27: 0 | CI27: 0 | CJ27: 0 | CK27: 0 | CL27: 0 | CM27: 1 | CN27: 0 | CP27: Does not apply / no one smoking | CQ27: No | CT27: No | CW27: Yes | CX27: Yes | CY27: Yes | CZ27: Yes | FL27: 729967349 | FM27: cee959d5-d6a5-439a-b8ee-6cf07e16d329 | FN27: 46132.334 | FQ27: submitted_via_web | FS27: vjiNwcPYvtjoD8cL5yiJdz | FU27: uuid:cee959d5-d6a5-439a-b8ee-6cf07e16d329 | FV27: 26
B28: 46128.272 | C28: 46132.542 | D28: Jhang066 | E28: 46128 | F28: 06:31:00.000+05:00 | G28: 06:45:00.000+05:00 | H28: Tahir Mustafa | I28: Faisalabad Division | J28: Jhang | K28: Jhang | L28: 31.282935 72.331878 111.0999984741211 87.5999984741211 | M28: 31.282935 | N28: 72.331878 | O28: 111.1 | P28: 87.599998 | Q28: Urban | R28: Akhtar pan shop | S28: Retail outlet /Point of Sale (POS) | DC28: Tobacco shop | DE28: Akhtar pan shop | DF28: Sargodha road | DG28: No | DH28: Not Applicable/ No Young buyers visited | DI28: No | DL28: No | DP28: No | DT28: No | DW28: Yes | DX28: Yes ( add photo evidence) | DY28: 1000075123-6_36_5.jpg | DZ28: https://kf.kobotoolbox.org/api/v2/assets/a7B4UGoSq7bg72YxNv837d/data/729967485/attachments/attiRf2LaEN5ABPLtRswB3X9/ | EA28: Yes | EB28: Capstan | EC28: 1000075123-6_36_18.jpg | ED28: https://kf.kobotoolbox.org/api/v2/assets/a7B4UGoSq7bg72YxNv837d/data/729967485/attachments/attyszacAmb5PooL4Qc6QiK4/ | EE28: No | EI28: No | EM28: No | EQ28: No | EU28: No | EY28: Yes ( add photo evidence) | EZ28: 1000075124-6_36_57.jpg | FA28: https://kf.kobotoolbox.org/api/v2/assets/a7B4UGoSq7bg72YxNv837d/data/729967485/attachments/attPUAArxai2hBjMheznqAUP/ | FB28: Capstan 172 sale | FC28: No | FG28: Yes | FH28: Yes | FL28: 729967485 | FM28: 669206a7-6433-405f-89c5-37172d6fb27e | FN28: 46132.334 | FQ28: submitted_via_web | FS28: vjiNwcPYvtjoD8cL5yiJdz | FU28: uuid:669206a7-6433-405f-89c5-37172d6fb27e | FV28: 27
B29: 46128.292 | C29: 46132.542 | D29: Jhang0067 | E29: 46128 | F29: 07:00:00.000+05:00 | G29: 07:11:00.000+05:00 | H29: Tahir Mustafa | I29: Faisalabad Division | J29: Jhang | K29: Jhang | L29: 31.273754 72.319133 114.19999694824219 5.494999885559082 | M29: 31.273754 | N29: 72.319133 | O29: 114.2 | P29: 5.4949999 | Q29: Urban | R29: Shell v power petrol | S29: Retail outlet /Point of Sale (POS) | DC29: Fuel station | DE29: Shell v power | DF29: Car wash | DG29: No | DH29: Not Applicable/ No Young buyers visited | DI29: No | DL29: No | DP29: No | DT29: No | DW29: No | DX29: No | EA29: No | EE29: No | EI29: No | EM29: No | EQ29: No | EU29: No | EY29: No | FC29: No | FG29: No | FH29: Yes | FL29: 729967601 | FM29: cc7e7013-7357-40e8-a6d6-9ad41bbbb465 | FN29: 46132.334 | FQ29: submitted_via_web | FS29: vjiNwcPYvtjoD8cL5yiJdz | FU29: uuid:cc7e7013-7357-40e8-a6d6-9ad41bbbb465 | FV29: 28
B30: 46128.299 | C30: 46132.542 | D30: Jhang0068 | E30: 46128 | F30: 07:15:00.000+05:00 | G30: 07:28:00.000+05:00 | H30: Tahir Mustafa | I30: Faisalabad Division | J30: Jhang | K30: Jhang | L30: 31.257982 72.306018 112.5 32.0989990234375 | M30: 31.257982 | N30: 72.306018 | O30: 112.5 | P30: 32.098999 | Q30: Urban | R30: Daewoo Express Terminal Jhang–Faisalabad Rd, Jhang | S30: Public place | T30: Transport Terminal (Bus terminal) | U30: Listed Venue | V30: 1 | W30: 0 | X30: Daewoo Express Terminal Jhang–Faisalabad Rd, Jhang | Y30: Yes( add photo evidence) | Z30: 1000075126-7_13_32.jpg | AA30: https://kf.kobotoolbox.org/api/v2/assets/a7B4UGoSq7bg72YxNv837d/data/729967768/attachments/attn3JSCpCy25LcgfFfJSQPV/ | AB30: 1 | AC30: No | AE30: No | AG30: Yes | AH30: Yes | AI30: Yes | AJ30: Does not apply / no one using tobacco or nicotine products | AK30: 0 | AL30: 0 | AM30: 0 | AN30: 0 | AO30: 0 | AP30: 0 | AQ30: 1 | AR30: 0 | AT30: Does not apply / no one using tobacco or nicotine products | AU30: No | AX30: No | BA30: No | BD30: No | BT30: Yes | FL30: 729967768 | FM30: 7907d647-6261-4a01-b052-7d1903d0edd2 | FN30: 46132.334 | FQ30: submitted_via_web | FS30: vjiNwcPYvtjoD8cL5yiJdz | FU30: uuid:7907d647-6261-4a01-b052-7d1903d0edd2 | FV30: 29
B31: 46128.302 | C31: 46132.543 | D31: Jhang0069 | E31: 46128 | F31: 07:39:00.000+05:00 | G31: 07:50:00.000+05:00 | H31: Tahir Mustafa | I31: Faisalabad Division | J31: Jhang | K31: Jhang | L31: 31.280103 72.31512 114.30000305175781 33.499000549316406 | M31: 31.280103 | N31: 72.31512 | O31: 114.3 | P31: 33.499001 | Q31: Urban | R31: Altron permium | S31: Retail outlet /Point of Sale (POS) | DC31: Fuel station | DE31: Altron permum | DF31: Farooq e Azam road | DG31: No | DH31: Not Applicable/ No Young buyers visited | DI31: No | DL31: No | DP31: No | DT31: No | DW31: No | DX31: No | EA31: No | EE31: No | EI31: No | EM31: No | EQ31: No | EU31: No | EY31: No | FC31: No | FG31: Yes | FH31: Yes | FL31: 729968050 | FM31: b4d0312d-d418-4aef-89a1-f3752929f67a | FN31: 46132.334 | FQ31: submitted_via_web | FS31: vjiNwcPYvtjoD8cL5yiJdz | FU31: uuid:b4d0312d-d418-4aef-89a1-f3752929f67a | FV31: 30
B32: 46128.336 | C32: 46132.543 | D32: Jhang 70 | E32: 46128 | F32: 08:04:00.000+05:00 | G32: 08:19:00.000+05:00 | H32: Tahir Mustafa | I32: Faisalabad Division | J32: Jhang | K32: Jhang | L32: 31.277041 72.32083 114.69999694824219 23.10099983215332 | M32: 31.277041 | N32: 72.32083 | O32: 114.7 | P32: 23.101 | Q32: Urban | R32: Gilani restaurant | S32: Public place | T32: Eatery ( Restaurant) | U32: Unlisted Venue | V32: 0 | W32: 1 | X32: Gilani restaurant | Y32: No | AC32: No | AE32: No | AG32: Yes | AH32: Yes | AI32: Yes | AJ32: Does not apply / no one using tobacco or nicotine products | AK32: 0 | AL32: 0 | AM32: 0 | AN32: 0 | AO32: 0 | AP32: 0 | AQ32: 1 | AR32: 0 | AT32: Does not apply / no one using tobacco or nicotine products | AU32: No | AX32: Yes (add photo Evidence) | AY32: 1000075127-8_7_43.jpg | AZ32: https://kf.kobotoolbox.org/api/v2/assets/a7B4UGoSq7bg72YxNv837d/data/729968199/attachments/attctcfKdGsHxxkRUiT8SdTm/ | BA32: No | BD32: Yes (add photo Evidence) | BE32: 1000075129-8_8_18.jpg | BF32: https://kf.kobotoolbox.org/api/v2/assets/a7B4UGoSq7bg72YxNv837d/data/729968199/attachments/attJYhTM6NLPyL2kZAhQpR69/ | BG32: Does not apply / no one using tobacco or nicotine products | BH32: 0 | BI32: 0 | BJ32: 0 | BK32: 0 | BL32: 0 | BM32: 0 | BN32: 1 | BO32: 0 | BQ32: No | BT32: Yes | FL32: 729968199 | FM32: 724ebff3-bdf9-478b-8c3d-852694303771 | FN32: 46132.334 | FQ32: submitted_via_web | FS32: vjiNwcPYvtjoD8cL5yiJdz | FU32: uuid:724ebff3-bdf9-478b-8c3d-852694303771 | FV32: 31
B33: 46128.353 | C33: 46132.543 | D33: Jhang0071 | E33: 46128 | F33: 08:29:00.000+05:00 | G33: 08:34:00.000+05:00 | H33: Tahir Mustafa | I33: Faisalabad Division | J33: Jhang | K33: Jhang | L33: 31.275648 72.322076 114.30000305175781 17.91900062561035 | M33: 31.275648 | N33: 72.322076 | O33: 114.3 | P33: 17.919001 | Q33: Urban | R33: Kachhari road | S33: Public Service Vehicle (PSV) | BW33: other | BX33: Raksha | BY33: Raksha | BZ33: Kachhari road | CA33: No | CB33: No | CC33: No | CD33: No | CF33: Does not apply / no one using tobacco or nicotine products | CG33: 0 | CH33: 0 | CI33: 0 | CJ33: 0 | CK33: 0 | CL33: 0 | CM33: 1 | CN33: 0 | CP33: Does not apply / no one smoking | CQ33: No | CT33: No | CW33: No | CX33: Yes | CY33: Yes | CZ33: Yes | FL33: 729968338 | FM33: cbcf5ab8-06cd-4172-ac4f-9ce1e0ce1a4e | FN33: 46132.334 | FQ33: submitted_via_web | FS33: vjiNwcPYvtjoD8cL5yiJdz | FU33: uuid:cbcf5ab8-06cd-4172-ac4f-9ce1e0ce1a4e | FV33: 32
B34: 46128.358 | C34: 46132.543 | D34: Jhang72 | E34: 46128 | F34: 08:40:00.000+05:00 | G34: 08:55:00.000+05:00 | H34: Tahir Mustafa | I34: Faisalabad Division | J34: Jhang | K34: Jhang | L34: 31.260842 72.351215 114.69999694824219 46.869998931884766 | M34: 31.260842 | N34: 72.351215 | O34: 114.7 | P34: 46.869999 | Q34: Urban | R34: Hockey stadium | S34: Public place | T34: Entertainment/sports venue - sport ground | U34: Listed Venue | V34: 1 | W34: 0 | X34: Hockey stadium | Y34: No | AC34: No | AE34: No | AG34: Yes | AH34: No | AI34: No | AJ34: Does not apply / no one using tobacco or nicotine products | AK34: 0 | AL34: 0 | AM34: 0 | AN34: 0 | AO34: 0 | AP34: 0 | AQ34: 1 | AR34: 0 | AT34: Does not apply / no one using tobacco or nicotine products | AU34: No | AX34: No | BA34: No | BD34: No | BT34: Yes | FL34: 729968499 | FM34: 9b933d40-b699-4b06-aaa5-8ab8c9aad8bb | FN34: 46132.335 | FQ34: submitted_via_web | FS34: vjiNwcPYvtjoD8cL5yiJdz | FU34: uuid:9b933d40-b699-4b06-aaa5-8ab8c9aad8bb | FV34: 33
B35: 46128.368 | C35: 46132.543 | D35: Jhang0073 | E35: 46128 | F35: 00:25:00.000+05:00 | G35: 00:39:00.000+05:00 | H35: Tahir Mustafa | I35: Faisalabad Division | J35: Jhang | K35: Jhang | L35: 31.270794 72.329522 120.637 1.6480000019073486 | M35: 31.270794 | N35: 72.329522 | O35: 120.637 | P35: 1.648 | Q35: Urban | R35: THE ROOMI EDUCATION SYSTEM JHANG opposite M | S35: Public place | T35: Educational institution - School (Private) | U35: Listed Venue | V35: 1 | W35: 0 | X35: THE ROOMI EDUCATION SYSTEM JHANG opposite M | Y35: No | AC35: No | AE35: No | AG35: Yes | AH35: Yes | AI35: Yes | AJ35: Does not apply / no one using tobacco or nicotine products | AK35: 0 | AL35: 0 | AM35: 0 | AN35: 0 | AO35: 0 | AP35: 0 | AQ35: 1 | AR35: 0 | AT35: Does not apply / no one using tobacco or nicotine products | AU35: No | AX35: Yes (add photo Evidence) | AY35: 1000075234-12_28_12.jpg | AZ35: https://kf.kobotoolbox.org/api/v2/assets/a7B4UGoSq7bg72YxNv837d/data/729968642/attachments/attUnfvLyjXBaYPNctTGiqqc/ | BA35: No | BD35: No | BT35: Yes | FL35: 729968642 | FM35: b2cb1100-7f9d-4887-8900-b25dacca2701 | FN35: 46132.335 | FQ35: submitted_via_web | FS35: vjiNwcPYvtjoD8cL5yiJdz | FU35: uuid:b2cb1100-7f9d-4887-8900-b25dacca2701 | FV35: 34
B36: 46128.395 | C36: 46132.543 | D36: Jhang0074 | E36: 46128 | F36: 13:00:00.000+05:00 | G36: 01:15:00.000+05:00 | H36: Tahir Mustafa | I36: Faisalabad Division | J36: Jhang | K36: Jhang | L36: 31.26616 72.322457 131.659 15 | M36: 31.26616 | N36: 72.322457 | O36: 131.659 | P36: 15 | Q36: Urban | R36: Beaconhouse school system jhang camp | S36: Public place | T36: Educational institution - School (Private) | U36: Unlisted Venue | V36: 0 | W36: 1 | X36: Beaconhouse school system jhang camp | Y36: No | AC36: No | AE36: No | AG36: Yes | AH36: Yes | AI36: Yes | AJ36: Does not apply / no one using tobacco or nicotine products | AK36: 0 | AL36: 0 | AM36: 0 | AN36: 0 | AO36: 0 | AP36: 0 | AQ36: 1 | AR36: 0 | AT36: Does not apply / no one using tobacco or nicotine products | AU36: No | AX36: No | BA36: No | BD36: No | BT36: Yes | BV36: 6 THE INNOVATIVE HOUSE (BOYS) HIGH SCHOOL Block No 7 Jhang City map is not correct provide so unlisted give | FL36: 729968859 | FM36: 6ed01fac-36e8-46a2-9f7d-e0f624c27c94 | FN36: 46132.335 | FQ36: submitted_via_web | FS36: vjiNwcPYvtjoD8cL5yiJdz | FU36: uuid:6ed01fac-36e8-46a2-9f7d-e0f624c27c94 | FV36: 35
B37: 46128.52 | C37: 46132.543 | D37: Jhang 0075 | E37: 46128 | F37: 13:20:00.000+05:00 | G37: 13:35:00.000+05:00 | H37: Tahir Mustafa | I37: Faisalabad Division | J37: Jhang | K37: Jhang | L37: 31.25488 72.362708 113.9000015258789 52.400001525878906 | M37: 31.25488 | N37: 72.362708 | O37: 113.9 | P37: 52.400002 | Q37: Urban | R37: Punjab college of jhang | S37: Public place | T37: Educational institution - College | U37: Listed Venue | V37: 1 | W37: 0 | X37: Punjab college of jhang | Y37: No | AC37: No | AE37: No | AG37: Yes | AH37: Yes | AI37: Yes | AJ37: Does not apply / no one using tobacco or nicotine products | AK37: 0 | AL37: 0 | AM37: 0 | AN37: 0 | AO37: 0 | AP37: 0 | AQ37: 1 | AR37: 0 | AT37: Does not apply / no one using tobacco or nicotine products | AU37: No | AX37: No | BA37: No | BD37: No | BT37: Yes | FL37: 729968988 | FM37: 95c9ce7f-e695-48ae-8c41-bf93a929b1eb | FN37: 46132.335 | FQ37: submitted_via_web | FS37: vjiNwcPYvtjoD8cL5yiJdz | FU37: uuid:95c9ce7f-e695-48ae-8c41-bf93a929b1eb | FV37: 36
B38: 46128.564 | C38: 46132.543 | D38: Jhang 0076 | E38: 46128 | F38: 13:36:00.000+05:00 | G38: 13:50:00.000+05:00 | H38: Tahir Mustafa | I38: Faisalabad Division | J38: Jhang | K38: Jhang | L38: 31.25439 72.360583 113.69999694824219 38.45000076293945 | M38: 31.25439 | N38: 72.360583 | O38: 113.7 | P38: 38.450001 | Q38: Urban | R38: Govt graduate college of jhang | S38: Public place | T38: Educational institution - College | U38: Listed Venue | V38: 1 | W38: 0 | X38: Govt granted college gojor rd | Y38: No | AC38: No | AE38: No | AG38: Yes | AH38: Yes | AI38: Yes | AJ38: Does not apply / no one using tobacco or nicotine products | AK38: 0 | AL38: 0 | AM38: 0 | AN38: 0 | AO38: 0 | AP38: 0 | AQ38: 1 | AR38: 0 | AT38: Does not apply / no one using tobacco or nicotine products | AU38: No | AX38: No | BA38: No | BD38: No | BT38: Yes | FL38: 729969246 | FM38: b2fdee1e-5315-4172-a4a7-ecc78ecef048 | FN38: 46132.335 | FQ38: submitted_via_web | FS38: vjiNwcPYvtjoD8cL5yiJdz | FU38: uuid:b2fdee1e-5315-4172-a4a7-ecc78ecef048 | FV38: 37
B39: 46128.569 | C39: 46132.543 | D39: Jhang 0077 | E39: 46128 | F39: 13:54:00.000+05:00 | G39: 14:00:00.000+05:00 | H39: Tahir Mustafa | I39: Sahiwal Division | J39: Jhang | K39: Jhang | L39: 31.256604 72.350908 113.4000015258789 49.551998138427734 | M39: 31.256604 | N39: 72.350908 | O39: 113.4 | P39: 49.551998 | Q39: Urban | R39: Gojra road | S39: Public Service Vehicle (PSV) | BW39: other | BX39: Raksha | BY39: Raksha | BZ39: Gojra road | CA39: No | CB39: No | CC39: No | CD39: No | CF39: Does not apply / no one using tobacco or nicotine products | CG39: 0 | CH39: 0 | CI39: 0 | CJ39: 0 | CK39: 0 | CL39: 0 | CM39: 1 | CN39: 0 | CP39: Does not apply / no one smoking | CQ39: No | CT39: No | CW39: Yes | CX39: Yes | CY39: Yes | CZ39: Yes | FL39: 729969371 | FM39: ecd30efa-2987-4bc9-8d4d-ee817a2ac131 | FN39: 46132.335 | FQ39: submitted_via_web | FS39: vjiNwcPYvtjoD8cL5yiJdz | FU39: uuid:ecd30efa-2987-4bc9-8d4d-ee817a2ac131 | FV39: 38
B40: 46128.574 | C40: 46132.544 | D40: Jhang0078 | E40: 46128 | F40: 14:02:00.000+05:00 | G40: 14:17:00.000+05:00 | H40: Tahir Mustafa | I40: Faisalabad Division | J40: Jhang | K40: Jhang | L40: 31.262425 72.335754 114.80000305175781 26.19300079345703 | M40: 31.262425 | N40: 72.335754 | O40: 114.8 | P40: 26.193001 | Q40: Urban | R40: Total parco petrol | S40: Retail outlet /Point of Sale (POS) | DC40: Fuel station | DE40: Total parco | DF40: Gojor rd | DG40: No | DH40: Not Applicable/ No Young buyers visited | DI40: No | DL40: No | DP40: No | DT40: No | DW40: No | DX40: No | EA40: No | EE40: No | EI40: No | EM40: No | EQ40: No | EU40: No | EY40: No | FC40: No | FG40: No | FH40: Yes | FL40: 729969508 | FM40: 4c5781f9-a5cd-4cd7-b9cb-af2162593ac5 | FN40: 46132.335 | FQ40: submitted_via_web | FS40: vjiNwcPYvtjoD8cL5yiJdz | FU40: uuid:4c5781f9-a5cd-4cd7-b9cb-af2162593ac5 | FV40: 39
B41: 46128.664 | C41: 46132.544 | D41: Jhang0080 | E41: 46128 | F41: 15:57:00.000+05:00 | G41: 16:11:00.000+05:00 | H41: Tahir Mustafa | I41: Faisalabad Division | J41: Jhang | K41: Jhang | L41: 31.271727 72.31831 117.4000015258789 52.400001525878906 | M41: 31.271727 | N41: 72.31831 | O41: 117.4 | P41: 52.400002 | Q41: Urban | R41: Jigar chines restaurant | S41: Public place | T41: Eatery ( Restaurant) | U41: Listed Venue | V41: 1 | W41: 0 | X41: Jigar chines restaurant | Y41: No | AC41: No | AE41: No | AG41: Yes | AH41: Yes | AI41: Yes | AJ41: Does not apply / no one using tobacco or nicotine products | AK41: 0 | AL41: 0 | AM41: 0 | AN41: 0 | AO41: 0 | AP41: 0 | AQ41: 1 | AR41: 0 | AT41: Does not apply / no one using tobacco or nicotine products | AU41: No | AX41: No | BA41: No | BD41: No | BT41: Yes | FL41: 729969880 | FM41: 63b40d96-94a1-4fee-befe-d0811b0b31e3 | FN41: 46132.336 | FQ41: submitted_via_web | FS41: vjiNwcPYvtjoD8cL5yiJdz | FU41: uuid:63b40d96-94a1-4fee-befe-d0811b0b31e3 | FV41: 40
B42: 46128.667 | C42: 46132.544 | D42: Jhang0081 | E42: 46128 | F42: 16:32:00.000+05:00 | G42: 16:48:00.000+05:00 | H42: Tahir Mustafa | I42: Faisalabad Division | J42: Jhang | K42: Jhang | L42: 31.262105 72.30971 114.69999694824219 27.173999786376953 | M42: 31.262105 | N42: 72.30971 | O42: 114.7 | P42: 27.174 | Q42: Urban | R42: Sabir restaurant | S42: Public place | T42: Eatery ( Restaurant) | U42: Listed Venue | V42: 1 | W42: 0 | X42: Sabir restaurant | Y42: No | AC42: No | AE42: No | AG42: No | AH42: No | AI42: No | AJ42: Does not apply / no one using tobacco or nicotine products | AK42: 0 | AL42: 0 | AM42: 0 | AN42: 0 | AO42: 0 | AP42: 0 | AQ42: 1 | AR42: 0 | AT42: No | AU42: No | AX42: No | BA42: No | BD42: No | BT42: Yes | FL42: 729970132 | FM42: 566ad239-7cd9-4f60-8edd-18e0f1446cca | FN42: 46132.336 | FQ42: submitted_via_web | FS42: vjiNwcPYvtjoD8cL5yiJdz | FU42: uuid:566ad239-7cd9-4f60-8edd-18e0f1446cca | FV42: 41
B43: 46128.69 | C43: 46132.544 | D43: Jhang0082 | E43: 46128 | F43: 16:54:00.000+05:00 | G43: 17:10:00.000+05:00 | H43: Tahir Mustafa | I43: Faisalabad Division | J43: Jhang | K43: Jhang | L43: 31.268031 72.320138 114.30000305175781 20 | M43: 31.268031 | N43: 72.320138 | O43: 114.3 | P43: 20 | Q43: Urban | R43: Hotway fast food and pizza | S43: Public place | T43: Eatery ( Restaurant) | U43: Listed Venue | V43: 1 | W43: 0 | X43: Hotway fast food and pizza 🍕 | Y43: No | AC43: No | AE43: No | AG43: No | AH43: No | AI43: No | AJ43: Does not apply / no one using tobacco or nicotine products | AK43: 0 | AL43: 0 | AM43: 0 | AN43: 0 | AO43: 0 | AP43: 0 | AQ43: 1 | AR43: 0 | AT43: Does not apply / no one using tobacco or nicotine products | AU43: Yes ( add photo Evidence) | AV43: 1000075237-16_56_4.jpg | AW43: https://kf.kobotoolbox.org/api/v2/assets/a7B4UGoSq7bg72YxNv837d/data/729970429/attachments/attyjGKU263JbeHjh8oVDgYE/ | AX43: No | BA43: No | BD43: No | BT43: Yes | FL43: 729970429 | FM43: 81d5e04c-f01d-4461-90ff-31618805a8ec | FN43: 46132.336 | FQ43: submitted_via_web | FS43: vjiNwcPYvtjoD8cL5yiJdz | FU43: uuid:81d5e04c-f01d-4461-90ff-31618805a8ec | FV43: 42
B44: 46128.716 | C44: 46132.544 | D44: Jhang0083 | E44: 46128 | F44: 17:15:00.000+05:00 | G44: 17:30:00.000+05:00 | H44: Tahir Mustafa | I44: Faisalabad Division | J44: Jhang | K44: Jhang | L44: 31.271165 72.320264 114.19999694824219 13.342000007629395 | M44: 31.271165 | N44: 72.320264 | O44: 114.2 | P44: 13.342 | Q44: Urban | R44: Rfc fast food and pizza | S44: Public place | T44: Eatery ( Restaurant) | U44: Listed Venue | V44: 1 | W44: 0 | X44: Rfc fast food and pizza | Y44: Yes( add photo evidence) | Z44: 1000075238-17_15_59.jpg | AA44: https://kf.kobotoolbox.org/api/v2/assets/a7B4UGoSq7bg72YxNv837d/data/729970631/attachments/attM8cgpkw9VyDLU2Mz88qUF/ | AB44: 1 | AC44: No | AE44: No | AG44: Yes | AH44: Yes | AI44: Yes | AJ44: Does not apply / no one using tobacco or nicotine products | AK44: 0 | AL44: 0 | AM44: 0 | AN44: 0 | AO44: 0 | AP44: 0 | AQ44: 1 | AR44: 0 | AT44: Does not apply / no one using tobacco or nicotine products | AU44: No | AX44: No | BA44: No | BD44: No | BT44: Yes | FL44: 729970631 | FM44: 1813d6b3-74af-4125-8e02-bbfce4e69dba | FN44: 46132.336 | FQ44: submitted_via_web | FS44: vjiNwcPYvtjoD8cL5yiJdz | FU44: uuid:1813d6b3-74af-4125-8e02-bbfce4e69dba | FV44: 43
B45: 46128.72 | C45: 46132.544 | D45: Jhang0084 | E45: 46128 | F45: 18:03:00.000+05:00 | G45: 18:25:00.000+05:00 | H45: Tahir Mustafa | I45: Faisalabad Division | J45: Jhang | K45: Jhang | L45: 31.273507 72.318891 114.0999984741211 19.797000885009766 | M45: 31.273507 | N45: 72.318891 | O45: 114.1 | P45: 19.797001 | Q45: Urban | R45: Elysian sweet by unze London | S45: Public place | T45: Eatery ( Restaurant) | U45: Listed Venue | V45: 1 | W45: 0 | X45: Elysian sweet by unze London | Y45: No | AC45: No | AE45: No | AG45: Yes | AH45: Yes | AI45: Yes | AJ45: Does not apply / no one using tobacco or nicotine products | AK45: 0 | AL45: 0 | AM45: 0 | AN45: 0 | AO45: 0 | AP45: 0 | AQ45: 1 | AR45: 0 | AT45: Does not apply / no one using tobacco or nicotine products | AU45: No | AX45: No | BA45: No | BD45: No | BT45: Yes | FL45: 729970802 | FM45: 55034dda-71d3-4070-ba8a-9293f5238ba7 | FN45: 46132.336 | FQ45: submitted_via_web | FS45: vjiNwcPYvtjoD8cL5yiJdz | FU45: uuid:55034dda-71d3-4070-ba8a-9293f5238ba7 | FV45: 44
